Workbook

Sheet Sheet3
A3: Row Labels | B3: Sum of TOTAL REVISADO | C3: Sum of VALOR AJUSTADO
A4: 3 | B4: 6238.23 | C4: 2585
A5: 4 | B5: 3827.97 | C5: 2157.78
A6: Grand Total | B6: 10066.2 | C6: 4742.78

Sheet Sheet2
A1: # Factura | B1: Company | C1: Period - Invoice | D1: Month | E1: Year | F1: Period Limena | G1: User actual | H1: # Mobil | I1: Page Number | J1: Monthly Charges | K1: Usage and Purchase Charges | L1: Equipment Charges | M1: Surcharges and Other Charges and Credits | N1: Taxes, Governmental Surcharges and Fees | O1: Third-Party Charges (includes Tax) | P1: Total Charges | Q1: CTA | R1: Director | S1: Manager | T1: DEP | U1: iphone o ipad | V1: migrado | W1: COBRO ACORDADO
A2: 287289507033X06092025 | B2: AT&T | C2: JUNIO | D2: 6 | E2: 2025 | F2: 9 | G2: Group 7 | H2: 629-257-4960 | I2: 5 | J2: - | K2: $40.00 | L2: - | M2: - | N2: - | P2: 40 | Q2: 60311003 | R2: 04 | S2: 0401 | T2: 040101 | U2: =IFERROR(+VLOOKUP(H2,'DISPOSITIVOS ACTIVOS'!B:D,3,FALSE),"IPHONE") -> no aplica | V2: =IFERROR(+VLOOKUP(H2,'[1]Migracion feb25 Ver to ATT'!$B:$G,6,FALSE), "NO MIGRADO") -> NO MIGRADO | W2: 25
A3: 287289507033X06092025 | B3: AT&T | C3: JUNIO | D3: 6 | E3: 2025 | F3: 9 | G3: BACKUP INTERNET 1 | H3: 629-257-4960 | I3: 7 | J3: - | K3: $15.00 | L3: - | M3: $3.75 | N3: - | P3: 18.75 | Q3: 60311003 | R3: 04 | S3: 0401 | T3: 040101 | U3: =IFERROR(+VLOOKUP(H3,'DISPOSITIVOS ACTIVOS'!B:D,3,FALSE),"IPHONE") -> no aplica | V3: =IFERROR(+VLOOKUP(H3,'[1]Migracion feb25 Ver to ATT'!$B:$G,6,FALSE), "NO MIGRADO") -> NO MIGRADO | W3: 25
A4: 287289507033X06092025 | B4: AT&T | C4: JUNIO | D4: 6 | E4: 2025 | F4: 9 | G4: Group 8 | H4: 629-258-0227 | I4: 5 | J4: - | K4: $40.00 | L4: - | M4: - | N4: - | P4: 40 | Q4: 60311003 | R4: 04 | S4: 0401 | T4: 040101 | U4: =IFERROR(+VLOOKUP(H4,'DISPOSITIVOS ACTIVOS'!B:D,3,FALSE),"IPHONE") -> no aplica | V4: =IFERROR(+VLOOKUP(H4,'[1]Migracion feb25 Ver to ATT'!$B:$G,6,FALSE), "NO MIGRADO") -> NO MIGRADO | W4: 25
A5: 287289507033X06092025 | B5: AT&T | C5: JUNIO | D5: 6 | E5: 2025 | F5: 9 | G5: BACKUP INTERNET 2 | H5: 629-258-0227 | I5: 9 | J5: - | K5: $15.00 | L5: - | M5: $3.75 | N5: - | P5: 18.75 | Q5: 60311003 | R5: 04 | S5: 0401 | T5: 040101 | U5: =IFERROR(+VLOOKUP(H5,'DISPOSITIVOS ACTIVOS'!B:D,3,FALSE),"IPHONE") -> no aplica | V5: =IFERROR(+VLOOKUP(H5,'[1]Migracion feb25 Ver to ATT'!$B:$G,6,FALSE), "NO MIGRADO") -> NO MIGRADO | W5: 25
A6: 287289507033X06092025 | B6: AT&T | C6: JUNIO | D6: 6 | E6: 2025 | F6: 9 | G6: JOSE MAITE SA | H6: 205-527-8021 | I6: 11 | J6: $0.00 | K6: $25.00 | L6: $5.00 | M6: $4.54 | N6: $5.83 | P6: 40.37 | Q6: 60311005 | R6: 04 | S6: 0401 | T6: 040105 | U6: =IFERROR(+VLOOKUP(H6,'DISPOSITIVOS ACTIVOS'!B:D,3,FALSE),"IPHONE") -> Iphone | V6: =IFERROR(+VLOOKUP(H6,'[1]Migracion feb25 Ver to ATT'!$B:$G,6,FALSE), "NO MIGRADO") -> NO MIGRADO | W6: 25
A7: 287289507033X06092025 | B7: AT&T | C7: JUNIO | D7: 6 | E7: 2025 | F7: 9 | G7: ROSMARY SILVA | H7: 205-529-6296 | I7: 13 | J7: $0.00 | K7: $50.00 | L7: - | M7: $4.87 | N7: $5.37 | P7: 60.24 | Q7: 60311005 | R7: 04 | S7: 0401 | T7: 040105 | U7: =IFERROR(+VLOOKUP(H7,'DISPOSITIVOS ACTIVOS'!B:D,3,FALSE),"IPHONE") -> Iphone | V7: =IFERROR(+VLOOKUP(H7,'[1]Migracion feb25 Ver to ATT'!$B:$G,6,FALSE), "NO MIGRADO") -> Iphone | W7: 15
A8: 287289507033X06092025 | B8: AT&T | C8: JUNIO | D8: 6 | E8: 2025 | F8: 9 | G8: JESUS GUERRERO | H8: 205-767-8090 | I8: 15 | J8: $0.00 | K8: $50.00 | L8: - | M8: $4.87 | N8: $5.37 | P8: 60.24 | Q8: 60311005 | R8: 04 | S8: 0401 | T8: 040105 | U8: =IFERROR(+VLOOKUP(H8,'DISPOSITIVOS ACTIVOS'!B:D,3,FALSE),"IPHONE") -> Iphone | V8: =IFERROR(+VLOOKUP(H8,'[1]Migracion feb25 Ver to ATT'!$B:$G,6,FALSE), "NO MIGRADO") -> Iphone | W8: 15
A9: 287289507033X06092025 | B9: AT&T | C9: JUNIO | D9: 6 | E9: 2025 | F9: 9 | G9: DANIEL FLORES IPAD SA | H9: 256-631-4188 | I9: 17 | J9: - | K9: $15.00 | L9: - | M9: $3.75 | N9: - | P9: 18.75 | Q9: 60311003 | R9: 04 | S9: 0401 | T9: 040105 | U9: =IFERROR(+VLOOKUP(H9,'DISPOSITIVOS ACTIVOS'!B:D,3,FALSE),"IPHONE") -> Ipad | V9: =IFERROR(+VLOOKUP(H9,'[1]Migracion feb25 Ver to ATT'!$B:$G,6,FALSE), "NO MIGRADO") -> NO MIGRADO | W9: 15
A10: 287289507033X06092025 | B10: AT&T | C10: JUNIO | D10: 6 | E10: 2025 | F10: 9 | G10: DANIEL FLORES SA | H10: 256-724-1530 | I10: 19 | J10: $0.00 | K10: $25.00 | L10: $10.99 | M10: $4.54 | N10: $5.83 | P10: 46.36 | Q10: 60311005 | R10: 04 | S10: 0401 | T10: 040105 | U10: =IFERROR(+VLOOKUP(H10,'DISPOSITIVOS ACTIVOS'!B:D,3,FALSE),"IPHONE") -> Iphone | V10: =IFERROR(+VLOOKUP(H10,'[1]Migracion feb25 Ver to ATT'!$B:$G,6,FALSE), "NO MIGRADO") -> NO MIGRADO | W10: 25
A11: 287289507033X06092025 | B11: AT&T | C11: JUNIO | D11: 6 | E11: 2025 | F11: 9 | G11: AMALIA BENOCMO | H11: 270-779-9642 | I11: 21 | J11: - | K11: $50.00 | L11: - | M11: $5.58 | N11: $1.33 | P11: 56.91 | Q11: 60311005 | R11: 04 | S11: 0401 | T11: 040101 | U11: =IFERROR(+VLOOKUP(H11,'DISPOSITIVOS ACTIVOS'!B:D,3,FALSE),"IPHONE") -> 0 | V11: =IFERROR(+VLOOKUP(H11,'[1]Migracion feb25 Ver to ATT'!$B:$G,6,FALSE), "NO MIGRADO") -> NO MIGRADO | W11: 25
A12: 287289507033X06092025 | B12: AT&T | C12: JUNIO | D12: 6 | E12: 2025 | F12: 9 | G12: ERNESTO PAUMIER - N... | H12: 283-229-3007 | I12: 23 | J12: $21.00 | K12: $50.00 | L12: - | M12: $5.30 | N12: $2.87 | P12: 79.17 | Q12: 60311005 | R12: 03 | S12: 0303 | T12: 030302 | U12: =IFERROR(+VLOOKUP(H12,'DISPOSITIVOS ACTIVOS'!B:D,3,FALSE),"IPHONE") -> Samsung | V12: =IFERROR(+VLOOKUP(H12,'[1]Migracion feb25 Ver to ATT'!$B:$G,6,FALSE), "NO MIGRADO") -> NO MIGRADO | W12: 25
A13: 287289507033X06092025 | B13: AT&T | C13: JUNIO | D13: 6 | E13: 2025 | F13: 9 | G13: WILLIAM HARRIS - NO... | H13: 283-229-3008 | I13: 25 | J13: $21.00 | K13: $50.00 | L13: - | M13: $5.30 | N13: $2.87 | P13: 79.17 | Q13: 60311005 | R13: 03 | S13: 0303 | T13: 030302 | U13: =IFERROR(+VLOOKUP(H13,'DISPOSITIVOS ACTIVOS'!B:D,3,FALSE),"IPHONE") -> Samsung | V13: =IFERROR(+VLOOKUP(H13,'[1]Migracion feb25 Ver to ATT'!$B:$G,6,FALSE), "NO MIGRADO") -> NO MIGRADO | W13: 25
... A20: 287289507033X06092025 | B20: AT&T | C20: JUNIO | D20: 6 | E20: 2025 | F20: 9 | G20: KAREN ORELLANA | H20: 470-330-9757 | I20: 39 | J20: $12.50 | K20: $25.00 | L20: - | M20: $1.47 | N20: $3.71 | P20: 42.68 | Q20: 60311005 | R20: 04 | S20: 0401 | T20: 040101 | U20: =IFERROR(+VLOOKUP(H20,'DISPOSITIVOS ACTIVOS'!B:D,3,FALSE),"IPHONE") -> IPHONE | V20: =IFERROR(+VLOOKUP(H20,'[1]Migracion feb25 Ver to ATT'!$B:$G,6,FALSE), "NO MIGRADO") -> NO MIGRADO | W20: 25
A21: 287289507033X06092025 | B21: AT&T | C21: JUNIO | D21: 6 | E21: 2025 | F21: 9 | G21: DANIEL GARCIA | H21: 470-609-0538 | I21: 41 | J21: $0.00 | K21: $25.00 | L21: - | M21: $4.54 | N21: $2.14 | P21: 31.68 | Q21: 10145003 | U21: =IFERROR(+VLOOKUP(H21,'DISPOSITIVOS ACTIVOS'!B:D,3,FALSE),"IPHONE") -> no aplica | V21: =IFERROR(+VLOOKUP(H21,'[1]Migracion feb25 Ver to ATT'!$B:$G,6,FALSE), "NO MIGRADO") -> NO MIGRADO | W21: 25
A22: 287289507033X06092025 | B22: AT&T | C22: JUNIO | D22: 6 | E22: 2025 | F22: 9 | G22: OSCAR BARRAGAN | H22: 470-609-0570 | I22: 43 | J22: $0.00 | K22: $25.00 | L22: - | M22: $4.54 | N22: $2.14 | P22: 31.68 | Q22: 10145003 | U22: =IFERROR(+VLOOKUP(H22,'DISPOSITIVOS ACTIVOS'!B:D,3,FALSE),"IPHONE") -> no aplica | V22: =IFERROR(+VLOOKUP(H22,'[1]Migracion feb25 Ver to ATT'!$B:$G,6,FALSE), "NO MIGRADO") -> NO MIGRADO | W22: 25
A23: 287289507033X06092025 | B23: AT&T | C23: JUNIO | D23: 6 | E23: 2025 | F23: 9 | G23: ISRAEL LOPEZ | H23: 470-737-8596 | I23: 45 | J23: - | K23: - | L23: - | M23: - | N23: - | P23: 0 | Q23: 60311005 | R23: 03 | S23: 0302 | T23: 030201 | U23: =IFERROR(+VLOOKUP(H23,'DISPOSITIVOS ACTIVOS'!B:D,3,FALSE),"IPHONE") -> IPHONE | V23: =IFERROR(+VLOOKUP(H23,'[1]Migracion feb25 Ver to ATT'!$B:$G,6,FALSE), "NO MIGRADO") -> NO MIGRADO | W23: 25
A24: 287289507033X06092025 | B24: AT&T | C24: JUNIO | D24: 6 | E24: 2025 | F24: 9 | G24: SALES ARKANSAS | H24: 501-773-3738 | I24: 47 | J24: - | K24: $15.00 | L24: - | M24: $3.75 | N24: - | P24: 18.75 | Q24: 60311003 | R24: 04 | S24: 0401 | T24: 040103 | U24: =IFERROR(+VLOOKUP(H24,'DISPOSITIVOS ACTIVOS'!B:D,3,FALSE),"IPHONE") -> Ipad | V24: =IFERROR(+VLOOKUP(H24,'[1]Migracion feb25 Ver to ATT'!$B:$G,6,FALSE), "NO MIGRADO") -> NO MIGRADO | W24: 15
A25: 287289507033X06092025 | B25: AT&T | C25: JUNIO | D25: 6 | E25: 2025 | F25: 9 | G25: ARTURO VILLAVICENCIO | H25: 501-773-3763 | I25: 49 | J25: $0.00 | K25: $50.00 | L25: - | M25: $4.87 | N25: $5.37 | P25: 60.24 | Q25: 60311005 | R25: 04 | S25: 0401 | T25: 040103 | U25: =IFERROR(+VLOOKUP(H25,'DISPOSITIVOS ACTIVOS'!B:D,3,FALSE),"IPHONE") -> Iphone | V25: =IFERROR(+VLOOKUP(H25,'[1]Migracion feb25 Ver to ATT'!$B:$G,6,FALSE), "NO MIGRADO") -> Iphone | W25: 15
A26: 287289507033X06092025 | B26: AT&T | C26: JUNIO | D26: 6 | E26: 2025 | F26: 9 | G26: DILVER GARCIA | H26: 502-341-1558 | I26: 51 | J26: -$8.34 | K26: $50.00 | L26: - | M26: $4.75 | N26: $4.25 | P26: 50.66 | Q26: 60311005 | R26: 04 | S26: 0401 | T26: 040101 | U26: =IFERROR(+VLOOKUP(H26,'DISPOSITIVOS ACTIVOS'!B:D,3,FALSE),"IPHONE") -> 0 | V26: =IFERROR(+VLOOKUP(H26,'[1]Migracion feb25 Ver to ATT'!$B:$G,6,FALSE), "NO MIGRADO") -> Galaxy | W26: 15
A27: 287289507033X06092025 | B27: AT&T | C27: JUNIO | D27: 6 | E27: 2025 | F27: 9 | G27: JAVIER MOJICA LG | H27: 502-558-5770 | I27: 53 | J27: $1.66 | K27: $50.00 | L27: - | M27: $4.88 | N27: $2.36 | P27: 58.9 | Q27: 60311005 | R27: 03 | S27: 0303 | T27: 030301 | U27: =IFERROR(+VLOOKUP(H27,'DISPOSITIVOS ACTIVOS'!B:D,3,FALSE),"IPHONE") -> Galaxy | V27: =IFERROR(+VLOOKUP(H27,'[1]Migracion feb25 Ver to ATT'!$B:$G,6,FALSE), "NO MIGRADO") -> Galaxy | W27: 15
A28: 287289507033X06092025 | B28: AT&T | C28: JUNIO | D28: 6 | E28: 2025 | F28: 9 | G28: CLAUDIA ARMES | H28: 502-974-3915 | I28: 55 | J28: $0.00 | K28: $50.00 | L28: - | M28: $4.87 | N28: $5.37 | P28: 60.24 | Q28: 60311005 | R28: 04 | S28: 0401 | T28: 040102 | U28: =IFERROR(+VLOOKUP(H28,'DISPOSITIVOS ACTIVOS'!B:D,3,FALSE),"IPHONE") -> Iphone | V28: =IFERROR(+VLOOKUP(H28,'[1]Migracion feb25 Ver to ATT'!$B:$G,6,FALSE), "NO MIGRADO") -> Iphone | W28: 15
A29: 287289507033X06092025 | B29: AT&T | C29: JUNIO | D29: 6 | E29: 2025 | F29: 9 | G29: IRIS CORDERO | H29: 513-675-0865 | I29: 57 | J29: $0.00 | K29: $50.00 | L29: - | M29: $4.87 | N29: $5.37 | P29: 60.24 | Q29: 60311005 | R29: 04 | S29: 0401 | T29: 040102 | U29: =IFERROR(+VLOOKUP(H29,'DISPOSITIVOS ACTIVOS'!B:D,3,FALSE),"IPHONE") -> Iphone | V29: =IFERROR(+VLOOKUP(H29,'[1]Migracion feb25 Ver to ATT'!$B:$G,6,FALSE), "NO MIGRADO") -> Iphone | W29: 15
A30: 287289507033X06092025 | B30: AT&T | C30: JUNIO | D30: 6 | E30: 2025 | F30: 9 | G30: CINCINNATI LIMENA | H30: 513-720-1147 | I30: 59 | J30: $0.00 | K30: $25.00 | L30: $5.00 | M30: $4.61 | N30: $5.10 | P30: 39.71 | Q30: 60311005 | R30: 04 | S30: 0402 | T30: 040202 | U30: =IFERROR(+VLOOKUP(H30,'DISPOSITIVOS ACTIVOS'!B:D,3,FALSE),"IPHONE") -> Iphone | V30: =IFERROR(+VLOOKUP(H30,'[1]Migracion feb25 Ver to ATT'!$B:$G,6,FALSE), "NO MIGRADO") -> NO MIGRADO | W30: 25
A31: 287289507033X06092025 | B31: AT&T | C31: JUNIO | D31: 6 | E31: 2025 | F31: 9 | G31: ROSMARY LACRUZ | H31: 601-910-8492 | I31: 61 | J31: $0.00 | K31: $50.00 | L31: - | M31: $4.87 | N31: $5.37 | P31: 60.24 | Q31: 60311005 | R31: 04 | S31: 0401 | T31: 040103 | U31: =IFERROR(+VLOOKUP(H31,'DISPOSITIVOS ACTIVOS'!B:D,3,FALSE),"IPHONE") -> Iphone | V31: =IFERROR(+VLOOKUP(H31,'[1]Migracion feb25 Ver to ATT'!$B:$G,6,FALSE), "NO MIGRADO") -> Iphone | W31: 15
A32: 287289507033X06092025 | B32: AT&T | C32: JUNIO | D32: 6 | E32: 2025 | F32: 9 | G32: OSMAN CABRERA | H32: 615-207-2464 | I32: 63 | J32: $0.00 | K32: $50.00 | L32: - | M32: $4.87 | N32: $5.37 | P32: 60.24 | Q32: 60311005 | R32: 04 | S32: 0401 | T32: 040101 | U32: =IFERROR(+VLOOKUP(H32,'DISPOSITIVOS ACTIVOS'!B:D,3,FALSE),"IPHONE") -> Iphone | V32: =IFERROR(+VLOOKUP(H32,'[1]Migracion feb25 Ver to ATT'!$B:$G,6,FALSE), "NO MIGRADO") -> Iphone | W32: 15
A33: 287289507033X06092025 | B33: AT&T | C33: JUNIO | D33: 6 | E33: 2025 | F33: 9 | G33: SIMON CASTELLANO | H33: 615-299-3640 | I33: 65 | J33: - | K33: $50.00 | L33: - | M33: $4.86 | N33: $2.48 | P33: 57.34 | Q33: 60311005 | R33: 03 | S33: 0303 | T33: 030308 | U33: =IFERROR(+VLOOKUP(H33,'DISPOSITIVOS ACTIVOS'!B:D,3,FALSE),"IPHONE") -> Galaxy | V33: =IFERROR(+VLOOKUP(H33,'[1]Migracion feb25 Ver to ATT'!$B:$G,6,FALSE), "NO MIGRADO") -> Galaxy | W33: 15
A34: 287289507033X06092025 | B34: AT&T | C34: JUNIO | D34: 6 | E34: 2025 | F34: 9 | G34: EDGAR FERNANDEZ LQ | H34: 615-299-3641 | I34: 67 | J34: $0.00 | K34: $25.00 | L34: - | M34: $4.54 | N34: $7.20 | P34: 36.74 | Q34: 60311005 | R34: 03 | S34: 0303 | T34: 030301 | U34: =IFERROR(+VLOOKUP(H34,'DISPOSITIVOS ACTIVOS'!B:D,3,FALSE),"IPHONE") -> Motorola | V34: =IFERROR(+VLOOKUP(H34,'[1]Migracion feb25 Ver to ATT'!$B:$G,6,FALSE), "NO MIGRADO") -> NO MIGRADO | W34: 25
A35: 287289507033X06092025 | B35: AT&T | C35: JUNIO | D35: 6 | E35: 2025 | F35: 9 | G35: IPAD SALES | H35: 615-305-1999 | I35: 69 | J35: - | K35: $10.00 | L35: - | M35: - | N35: - | P35: 10 | Q35: 60311003 | R35: 04 | S35: 0401 | T35: 040101 | U35: =IFERROR(+VLOOKUP(H35,'DISPOSITIVOS ACTIVOS'!B:D,3,FALSE),"IPHONE") -> IPHONE | V35: =IFERROR(+VLOOKUP(H35,'[1]Migracion feb25 Ver to ATT'!$B:$G,6,FALSE), "NO MIGRADO") -> NO MIGRADO | W35: 25
A36: 287289507033X06092025 | B36: AT&T | C36: JUNIO | D36: 6 | E36: 2025 | F36: 9 | G36: ALBERT CARDOZO | H36: 615-310-9970 | I36: 71 | J36: - | K36: $15.00 | L36: - | M36: $3.75 | N36: - | P36: 18.75 | Q36: 10145005 | U36: =IFERROR(+VLOOKUP(H36,'DISPOSITIVOS ACTIVOS'!B:D,3,FALSE),"IPHONE") -> Ipad | V36: =IFERROR(+VLOOKUP(H36,'[1]Migracion feb25 Ver to ATT'!$B:$G,6,FALSE), "NO MIGRADO") -> Ipad | W36: 15
A37: 287289507033X06092025 | B37: AT&T | C37: JUNIO | D37: 6 | E37: 2025 | F37: 9 | G37: HR LIMENA | H37: 615-316-8577 | I37: 73 | J37: $0.00 | K37: $25.00 | L37: $25.00 | M37: $4.54 | N37: $7.20 | P37: 61.74 | Q37: 60311005 | R37: 09 | S37: 0900 | T37: 090000 | U37: =IFERROR(+VLOOKUP(H37,'DISPOSITIVOS ACTIVOS'!B:D,3,FALSE),"IPHONE") -> Iphone | V37: =IFERROR(+VLOOKUP(H37,'[1]Migracion feb25 Ver to ATT'!$B:$G,6,FALSE), "NO MIGRADO") -> NO MIGRADO | W37: 25
A38: 287289507033X06092025 | B38: AT&T | C38: JUNIO | D38: 6 | E38: 2025 | F38: 9 | G38: DAVID CONDE WH | H38: 615-337-4949 | I38: 75 | J38: $0.00 | K38: $50.00 | L38: - | M38: $4.87 | N38: $5.37 | P38: 60.24 | Q38: 60311005 | R38: 03 | S38: 0302 | T38: 030201 | U38: =IFERROR(+VLOOKUP(H38,'DISPOSITIVOS ACTIVOS'!B:D,3,FALSE),"IPHONE") -> Galaxy | V38: =IFERROR(+VLOOKUP(H38,'[1]Migracion feb25 Ver to ATT'!$B:$G,6,FALSE), "NO MIGRADO") -> NO MIGRADO | W38: 25
A39: 287289507033X06092025 | B39: AT&T | C39: JUNIO | D39: 6 | E39: 2025 | F39: 9 | G39: HENRY ESQUIVEL | H39: 615-390-4624 | I39: 77 | J39: $0.00 | K39: $50.00 | L39: - | M39: $4.87 | N39: $5.37 | P39: 60.24 | Q39: 60311005 | R39: 03 | S39: 0302 | T39: 030201 | U39: =IFERROR(+VLOOKUP(H39,'DISPOSITIVOS ACTIVOS'!B:D,3,FALSE),"IPHONE") -> Iphone | V39: =IFERROR(+VLOOKUP(H39,'[1]Migracion feb25 Ver to ATT'!$B:$G,6,FALSE), "NO MIGRADO") -> Iphone | W39: 15
A40: 287289507033X06092025 | B40: AT&T | C40: JUNIO | D40: 6 | E40: 2025 | F40: 9 | G40: MERARI VILLATORO | H40: 615-403-8760 | I40: 79 | J40: $0.44 | K40: $25.00 | L40: $38.89 | M40: $6.74 | N40: $7.65 | P40: 78.72 | Q40: 60311005 | R40: 02 | S40: 0200 | T40: 020000 | U40: =IFERROR(+VLOOKUP(H40,'DISPOSITIVOS ACTIVOS'!B:D,3,FALSE),"IPHONE") -> Iphone | V40: =IFERROR(+VLOOKUP(H40,'[1]Migracion feb25 Ver to ATT'!$B:$G,6,FALSE), "NO MIGRADO") -> NO MIGRADO | W40: 25
A41: 287289507033X06092025 | B41: AT&T | C41: JUNIO | D41: 6 | E41: 2025 | F41: 9 | G41: JESSICA BARAJAS LA | H41: 615-417-0015 | I41: 81 | J41: $0.00 | K41: $25.00 | L41: - | M41: $4.54 | N41: $7.20 | P41: 36.74 | Q41: 60311005 | R41: 04 | S41: 0401 | T41: 040102 | U41: =IFERROR(+VLOOKUP(H41,'DISPOSITIVOS ACTIVOS'!B:D,3,FALSE),"IPHONE") -> Iphone | V41: =IFERROR(+VLOOKUP(H41,'[1]Migracion feb25 Ver to ATT'!$B:$G,6,FALSE), "NO MIGRADO") -> NO MIGRADO | W41: 25
A42: 287289507033X06092025 | B42: AT&T | C42: JUNIO | D42: 6 | E42: 2025 | F42: 9 | G42: NICOLAS FINANZAS | H42: 615-417-9594 | I42: 83 | J42: $0.00 | K42: $25.00 | L42: - | M42: $4.54 | N42: $7.20 | P42: 36.74 | Q42: 60311005 | R42: 06 | S42: 0600 | T42: 060000 | U42: =IFERROR(+VLOOKUP(H42,'DISPOSITIVOS ACTIVOS'!B:D,3,FALSE),"IPHONE") -> Iphone | V42: =IFERROR(+VLOOKUP(H42,'[1]Migracion feb25 Ver to ATT'!$B:$G,6,FALSE), "NO MIGRADO") -> NO MIGRADO | W42: 25
A43: 287289507033X06092025 | B43: AT&T | C43: JUNIO | D43: 6 | E43: 2025 | F43: 9 | G43: ZEDRICK PATINO | H43: 615-426-4622 | I43: 85 | J43: $0.00 | K43: $25.00 | L43: - | M43: $4.54 | N43: $7.20 | P43: 36.74 | Q43: 60311005 | R43: 04 | S43: 0402 | T43: 040201 | U43: =IFERROR(+VLOOKUP(H43,'DISPOSITIVOS ACTIVOS'!B:D,3,FALSE),"IPHONE") -> Iphone | V43: =IFERROR(+VLOOKUP(H43,'[1]Migracion feb25 Ver to ATT'!$B:$G,6,FALSE), "NO MIGRADO") -> NO MIGRADO | W43: 25
A44: 287289507033X06092025 | B44: AT&T | C44: JUNIO | D44: 6 | E44: 2025 | F44: 9 | G44: DANNY CABANZO | H44: 615-456-2536 | I44: 87 | J44: $0.00 | K44: $50.00 | L44: - | M44: $4.87 | N44: $5.37 | P44: 60.24 | Q44: 60311005 | R44: 04 | S44: 0401 | T44: 040101 | U44: =IFERROR(+VLOOKUP(H44,'DISPOSITIVOS ACTIVOS'!B:D,3,FALSE),"IPHONE") -> Iphone | V44: =IFERROR(+VLOOKUP(H44,'[1]Migracion feb25 Ver to ATT'!$B:$G,6,FALSE), "NO MIGRADO") -> Iphone | W44: 15
A45: 287289507033X06092025 | B45: AT&T | C45: JUNIO | D45: 6 | E45: 2025 | F45: 9 | G45: MONICA AYALA | H45: 615-476-5992 | I45: 89 | J45: $12.50 | K45: $25.00 | L45: - | M45: $1.47 | N45: $3.71 | P45: 42.68 | Q45: 60311005 | R45: 04 | S45: 0402 | T45: 040201 | U45: =IFERROR(+VLOOKUP(H45,'DISPOSITIVOS ACTIVOS'!B:D,3,FALSE),"IPHONE") -> IPHONE | V45: =IFERROR(+VLOOKUP(H45,'[1]Migracion feb25 Ver to ATT'!$B:$G,6,FALSE), "NO MIGRADO") -> NO MIGRADO | W45: 25
A46: 287289507033X06092025 | B46: AT&T | C46: JUNIO | D46: 6 | E46: 2025 | F46: 9 | G46: MERARI TWOLINE | H46: 615-477-6490 | I46: 91 | J46: $0.00 | K46: $25.00 | L46: $30.56 | M46: $4.54 | N46: $7.20 | P46: 67.3 | Q46: 60311005 | R46: 02 | S46: 0200 | T46: 020000 | U46: =IFERROR(+VLOOKUP(H46,'DISPOSITIVOS ACTIVOS'!B:D,3,FALSE),"IPHONE") -> Iphone | V46: =IFERROR(+VLOOKUP(H46,'[1]Migracion feb25 Ver to ATT'!$B:$G,6,FALSE), "NO MIGRADO") -> NO MIGRADO | W46: 25
A47: 287289507033X06092025 | B47: AT&T | C47: JUNIO | D47: 6 | E47: 2025 | F47: 9 | G47: JOHAN MADRIZ | H47: 615-496-8278 | I47: 93 | J47: $15.00 | K47: $25.00 | L47: $38.89 | M47: $10.03 | N47: $8.33 | P47: 97.25 | Q47: 60311005 | R47: 11 | S47: 1100 | T47: 110001 | U47: =IFERROR(+VLOOKUP(H47,'DISPOSITIVOS ACTIVOS'!B:D,3,FALSE),"IPHONE") -> Iphone | V47: =IFERROR(+VLOOKUP(H47,'[1]Migracion feb25 Ver to ATT'!$B:$G,6,FALSE), "NO MIGRADO") -> NO MIGRADO | W47: 25
A48: 287289507033X06092025 | B48: AT&T | C48: JUNIO | D48: 6 | E48: 2025 | F48: 9 | G48: SALES DSD IPAD | H48: 615-585-1725 | I48: 95 | J48: - | K48: $10.00 | L48: - | M48: - | N48: - | P48: 10 | Q48: 10145005 | U48: =IFERROR(+VLOOKUP(H48,'DISPOSITIVOS ACTIVOS'!B:D,3,FALSE),"IPHONE") -> IPHONE | V48: =IFERROR(+VLOOKUP(H48,'[1]Migracion feb25 Ver to ATT'!$B:$G,6,FALSE), "NO MIGRADO") -> NO MIGRADO | W48: 25
A49: 287289507033X06092025 | B49: AT&T | C49: JUNIO | D49: 6 | E49: 2025 | F49: 9 | G49: YESENIA LOPEZ SA | H49: 615-586-0725 | I49: 97 | J49: - | K49: $15.00 | L49: - | M49: $3.75 | N49: - | P49: 18.75 | Q49: 60311003 | R49: 04 | S49: 0401 | T49: 040103 | U49: =IFERROR(+VLOOKUP(H49,'DISPOSITIVOS ACTIVOS'!B:D,3,FALSE),"IPHONE") -> Ipad | V49: =IFERROR(+VLOOKUP(H49,'[1]Migracion feb25 Ver to ATT'!$B:$G,6,FALSE), "NO MIGRADO") -> NO MIGRADO | W49: 15
A50: 287289507033X06092025 | B50: AT&T | C50: JUNIO | D50: 6 | E50: 2025 | F50: 9 | G50: JOSE MAITA IPAD | H50: 615-586-4787 | I50: 99 | J50: - | K50: $15.00 | L50: - | M50: $3.75 | N50: - | P50: 18.75 | Q50: 60311003 | R50: 04 | S50: 0401 | T50: 040105 | U50: =IFERROR(+VLOOKUP(H50,'DISPOSITIVOS ACTIVOS'!B:D,3,FALSE),"IPHONE") -> Ipad | V50: =IFERROR(+VLOOKUP(H50,'[1]Migracion feb25 Ver to ATT'!$B:$G,6,FALSE), "NO MIGRADO") -> NO MIGRADO | W50: 15
A51: 287289507033X06092025 | B51: AT&T | C51: JUNIO | D51: 6 | E51: 2025 | F51: 9 | G51: ROSMARY SILVA IPAD | H51: 615-589-2741 | I51: 101 | J51: - | K51: $15.00 | L51: - | M51: $3.75 | N51: - | P51: 18.75 | Q51: 60311003 | R51: 04 | S51: 0401 | T51: 040105 | U51: =IFERROR(+VLOOKUP(H51,'DISPOSITIVOS ACTIVOS'!B:D,3,FALSE),"IPHONE") -> Ipad | V51: =IFERROR(+VLOOKUP(H51,'[1]Migracion feb25 Ver to ATT'!$B:$G,6,FALSE), "NO MIGRADO") -> NO MIGRADO | W51: 15
A52: 287289507033X06092025 | B52: AT&T | C52: JUNIO | D52: 6 | E52: 2025 | F52: 9 | G52: ELIZABETH PELAEZ | H52: 615-589-4199 | I52: 103 | J52: $0.00 | K52: $25.00 | L52: $10.99 | M52: $4.54 | N52: $7.20 | P52: 47.73 | Q52: 60311005 | R52: 04 | S52: 0401 | T52: 040101 | U52: =IFERROR(+VLOOKUP(H52,'DISPOSITIVOS ACTIVOS'!B:D,3,FALSE),"IPHONE") -> Iphone | V52: =IFERROR(+VLOOKUP(H52,'[1]Migracion feb25 Ver to ATT'!$B:$G,6,FALSE), "NO MIGRADO") -> NO MIGRADO | W52: 25
A53: 287289507033X06092025 | B53: AT&T | C53: JUNIO | D53: 6 | E53: 2025 | F53: 9 | G53: DILVER GARCIA | H53: 615-626-2116 | I53: 105 | J53: $0.00 | K53: $50.00 | L53: - | M53: $4.87 | N53: $5.37 | P53: 60.24 | Q53: 10145005 | U53: =IFERROR(+VLOOKUP(H53,'DISPOSITIVOS ACTIVOS'!B:D,3,FALSE),"IPHONE") -> Iphone | V53: =IFERROR(+VLOOKUP(H53,'[1]Migracion feb25 Ver to ATT'!$B:$G,6,FALSE), "NO MIGRADO") -> Iphone | W53: 15
A54: 287289507033X06092025 | B54: AT&T | C54: JUNIO | D54: 6 | E54: 2025 | F54: 9 | G54: LIZET NAJERA | H54: 615-626-2756 | I54: 107 | J54: $0.00 | K54: $50.00 | L54: - | M54: $4.87 | N54: $5.37 | P54: 60.24 | Q54: 60311005 | R54: 04 | S54: 0401 | T54: 040102 | U54: =IFERROR(+VLOOKUP(H54,'DISPOSITIVOS ACTIVOS'!B:D,3,FALSE),"IPHONE") -> Iphone | V54: =IFERROR(+VLOOKUP(H54,'[1]Migracion feb25 Ver to ATT'!$B:$G,6,FALSE), "NO MIGRADO") -> Iphone | W54: 15
A55: 287289507033X06092025 | B55: AT&T | C55: JUNIO | D55: 6 | E55: 2025 | F55: 9 | G55: ALEJANDRA LOPEZ | H55: 615-626-3208 | I55: 109 | J55: $0.00 | K55: $50.00 | L55: - | M55: $4.87 | N55: $5.37 | P55: 60.24 | Q55: 60311005 | R55: 04 | S55: 0401 | T55: 040103 | U55: =IFERROR(+VLOOKUP(H55,'DISPOSITIVOS ACTIVOS'!B:D,3,FALSE),"IPHONE") -> Iphone | V55: =IFERROR(+VLOOKUP(H55,'[1]Migracion feb25 Ver to ATT'!$B:$G,6,FALSE), "NO MIGRADO") -> Iphone | W55: 15
A56: 287289507033X06092025 | B56: AT&T | C56: JUNIO | D56: 6 | E56: 2025 | F56: 9 | G56: ZULLYMAR TOVAR | H56: 615-626-3219 | I56: 111 | J56: $0.00 | K56: $50.00 | L56: - | M56: $4.87 | N56: $5.37 | P56: 60.24 | Q56: 60311005 | R56: 04 | S56: 0401 | T56: 040110 | U56: =IFERROR(+VLOOKUP(H56,'DISPOSITIVOS ACTIVOS'!B:D,3,FALSE),"IPHONE") -> 0 | V56: =IFERROR(+VLOOKUP(H56,'[1]Migracion feb25 Ver to ATT'!$B:$G,6,FALSE), "NO MIGRADO") -> Iphone | W56: 15
A57: 287289507033X06092025 | B57: AT&T | C57: JUNIO | D57: 6 | E57: 2025 | F57: 9 | G57: JOSE HERRERA | H57: 615-626-4243 | I57: 113 | J57: $18.00 | K57: $25.00 | L57: - | M57: $11.13 | N57: $8.55 | P57: 62.68 | Q57: 60311005 | R57: 01 | S57: 0100 | T57: 010000 | U57: =IFERROR(+VLOOKUP(H57,'DISPOSITIVOS ACTIVOS'!B:D,3,FALSE),"IPHONE") -> Iphone | V57: =IFERROR(+VLOOKUP(H57,'[1]Migracion feb25 Ver to ATT'!$B:$G,6,FALSE), "NO MIGRADO") -> NO MIGRADO | W57: 25
A58: 287289507033X06092025 | B58: AT&T | C58: JUNIO | D58: 6 | E58: 2025 | F58: 9 | G58: JORGE PRADO | H58: 615-674-8479 | I58: 115 | J58: $0.00 | K58: $25.00 | L58: $25.00 | M58: $4.54 | N58: $7.20 | P58: 61.74 | Q58: 60311005 | R58: 03 | S58: 0300 | T58: 030000 | U58: =IFERROR(+VLOOKUP(H58,'DISPOSITIVOS ACTIVOS'!B:D,3,FALSE),"IPHONE") -> Iphone | V58: =IFERROR(+VLOOKUP(H58,'[1]Migracion feb25 Ver to ATT'!$B:$G,6,FALSE), "NO MIGRADO") -> NO MIGRADO | W58: 25
A59: 287289507033X06092025 | B59: AT&T | C59: JUNIO | D59: 6 | E59: 2025 | F59: 9 | G59: WAREHOUSE TN NASHVILLE | H59: 615-691-3166 | I59: 117 | J59: $0.00 | K59: $25.00 | L59: - | M59: $4.54 | N59: $7.20 | P59: 36.74 | Q59: 60311005 | R59: 06 | S59: 0600 | T59: 060000 | U59: =IFERROR(+VLOOKUP(H59,'DISPOSITIVOS ACTIVOS'!B:D,3,FALSE),"IPHONE") -> Iphone | V59: =IFERROR(+VLOOKUP(H59,'[1]Migracion feb25 Ver to ATT'!$B:$G,6,FALSE), "NO MIGRADO") -> NO MIGRADO | W59: 25
A60: 287289507033X06092025 | B60: AT&T | C60: JUNIO | D60: 6 | E60: 2025 | F60: 9 | G60: JOHAN TWOLINE | H60: 615-708-0397 | I60: 119 | J60: -$19.45 | K60: $25.00 | L60: $33.34 | M60: $4.54 | N60: $7.20 | P60: 50.63 | Q60: 60311005 | R60: 11 | S60: 1100 | T60: 110001 | U60: =IFERROR(+VLOOKUP(H60,'DISPOSITIVOS ACTIVOS'!B:D,3,FALSE),"IPHONE") -> Iphone | V60: =IFERROR(+VLOOKUP(H60,'[1]Migracion feb25 Ver to ATT'!$B:$G,6,FALSE), "NO MIGRADO") -> NO MIGRADO | W60: 25
A61: 287289507033X06092025 | B61: AT&T | C61: JUNIO | D61: 6 | E61: 2025 | F61: 9 | G61: IVAN TELLO SA | H61: 615-730-3104 | I61: 121 | J61: $0.00 | K61: $25.00 | L61: $5.00 | M61: $4.54 | N61: $7.20 | P61: 41.74 | Q61: 60311005 | R61: 04 | S61: 0401 | T61: 040101 | U61: =IFERROR(+VLOOKUP(H61,'DISPOSITIVOS ACTIVOS'!B:D,3,FALSE),"IPHONE") -> Iphone | V61: =IFERROR(+VLOOKUP(H61,'[1]Migracion feb25 Ver to ATT'!$B:$G,6,FALSE), "NO MIGRADO") -> NO MIGRADO | W61: 25
A62: 287289507033X06092025 | B62: AT&T | C62: JUNIO | D62: 6 | E62: 2025 | F62: 9 | G62: ELISA GECHELE IPAD | H62: 615-768-6114 | I62: 123 | J62: - | K62: $15.00 | L62: - | M62: $3.75 | N62: - | P62: 18.75 | Q62: 60311003 | R62: 04 | S62: 0401 | T62: 040103 | U62: =IFERROR(+VLOOKUP(H62,'DISPOSITIVOS ACTIVOS'!B:D,3,FALSE),"IPHONE") -> Ipad | V62: =IFERROR(+VLOOKUP(H62,'[1]Migracion feb25 Ver to ATT'!$B:$G,6,FALSE), "NO MIGRADO") -> NO MIGRADO | W62: 15
A63: 287289507033X06092025 | B63: AT&T | C63: JUNIO | D63: 6 | E63: 2025 | F63: 9 | G63: ANDRES FUENMAYOR | H63: 615-795-8193 | I63: 125 | J63: -$8.34 | K63: $50.00 | L63: - | M63: $4.75 | N63: $4.25 | P63: 50.66 | Q63: 60311005 | R63: 03 | S63: 0303 | T63: 030308 | U63: =IFERROR(+VLOOKUP(H63,'DISPOSITIVOS ACTIVOS'!B:D,3,FALSE),"IPHONE") -> Galaxy | V63: =IFERROR(+VLOOKUP(H63,'[1]Migracion feb25 Ver to ATT'!$B:$G,6,FALSE), "NO MIGRADO") -> Galaxy | W63: 15
A64: 287289507033X06092025 | B64: AT&T | C64: JUNIO | D64: 6 | E64: 2025 | F64: 9 | G64: MERVIN FERERR | H64: 615-795-8195 | I64: 127 | J64: -$8.34 | K64: $50.00 | L64: - | M64: $4.75 | N64: $4.25 | P64: 50.66 | Q64: 60311005 | R64: 03 | S64: 0303 | T64: 030301 | U64: =IFERROR(+VLOOKUP(H64,'DISPOSITIVOS ACTIVOS'!B:D,3,FALSE),"IPHONE") -> Galaxy | V64: =IFERROR(+VLOOKUP(H64,'[1]Migracion feb25 Ver to ATT'!$B:$G,6,FALSE), "NO MIGRADO") -> Galaxy | W64: 15
A65: 287289507033X06092025 | B65: AT&T | C65: JUNIO | D65: 6 | E65: 2025 | F65: 9 | G65: YULIN REYES | H65: 615-804-0516 | I65: 129 | J65: -$8.34 | K65: $50.00 | L65: - | M65: $4.75 | N65: $4.30 | P65: 50.71 | Q65: 60311005 | R65: 04 | S65: 0401 | T65: 040101 | U65: =IFERROR(+VLOOKUP(H65,'DISPOSITIVOS ACTIVOS'!B:D,3,FALSE),"IPHONE") -> Iphone | V65: =IFERROR(+VLOOKUP(H65,'[1]Migracion feb25 Ver to ATT'!$B:$G,6,FALSE), "NO MIGRADO") -> Iphone | W65: 15
A66: 287289507033X06092025 | B66: AT&T | C66: JUNIO | D66: 6 | E66: 2025 | F66: 9 | G66: ELISA SILVA | H66: 615-812-5934 | I66: 131 | J66: $0.00 | K66: $25.00 | L66: - | M66: $4.54 | N66: $7.20 | P66: 36.74 | Q66: 60311005 | R66: 04 | S66: 0401 | T66: 040103 | U66: =IFERROR(+VLOOKUP(H66,'DISPOSITIVOS ACTIVOS'!B:D,3,FALSE),"IPHONE") -> Iphone | V66: =IFERROR(+VLOOKUP(H66,'[1]Migracion feb25 Ver to ATT'!$B:$G,6,FALSE), "NO MIGRADO") -> NO MIGRADO | W66: 25
A67: 287289507033X06092025 | B67: AT&T | C67: JUNIO | D67: 6 | E67: 2025 | F67: 9 | G67: IPADAMALIA BENOCMO | H67: 615-821-7053 | I67: 133 | J67: - | K67: $15.00 | L67: - | M67: $3.75 | N67: - | P67: 18.75 | Q67: 60311003 | R67: 04 | S67: 0401 | T67: 040101 | U67: =IFERROR(+VLOOKUP(H67,'DISPOSITIVOS ACTIVOS'!B:D,3,FALSE),"IPHONE") -> Ipad | V67: =IFERROR(+VLOOKUP(H67,'[1]Migracion feb25 Ver to ATT'!$B:$G,6,FALSE), "NO MIGRADO") -> NO MIGRADO | W67: 15
A68: 287289507033X06092025 | B68: AT&T | C68: JUNIO | D68: 6 | E68: 2025 | F68: 9 | G68: RENYA VIVAS DSD | H68: 615-821-8577 | I68: 135 | J68: -$1.39 | K68: $15.00 | L68: - | M68: $3.75 | N68: - | P68: 17.36 | Q68: 10145005 | U68: =IFERROR(+VLOOKUP(H68,'DISPOSITIVOS ACTIVOS'!B:D,3,FALSE),"IPHONE") -> 0 | V68: =IFERROR(+VLOOKUP(H68,'[1]Migracion feb25 Ver to ATT'!$B:$G,6,FALSE), "NO MIGRADO") -> NO MIGRADO | W68: 25
A69: 287289507033X06092025 | B69: AT&T | C69: JUNIO | D69: 6 | E69: 2025 | F69: 9 | G69: LEONARDO PALENCIA SA | H69: 615-828-8926 | I69: 137 | J69: $0.00 | K69: $25.00 | L69: $5.00 | M69: $4.54 | N69: $7.20 | P69: 41.74 | Q69: 60311005 | R69: 04 | S69: 0401 | T69: 040101 | U69: =IFERROR(+VLOOKUP(H69,'DISPOSITIVOS ACTIVOS'!B:D,3,FALSE),"IPHONE") -> Iphone | V69: =IFERROR(+VLOOKUP(H69,'[1]Migracion feb25 Ver to ATT'!$B:$G,6,FALSE), "NO MIGRADO") -> NO MIGRADO | W69: 25
A70: 287289507033X06092025 | B70: AT&T | C70: JUNIO | D70: 6 | E70: 2025 | F70: 9 | G70: YULIER PEREZ | H70: 615-830-4944 | I70: 139 | J70: -$8.34 | K70: $50.00 | L70: - | M70: $4.75 | N70: $4.25 | P70: 50.66 | Q70: 60311005 | R70: 03 | S70: 0303 | T70: 030301 | U70: =IFERROR(+VLOOKUP(H70,'DISPOSITIVOS ACTIVOS'!B:D,3,FALSE),"IPHONE") -> Galaxy | V70: =IFERROR(+VLOOKUP(H70,'[1]Migracion feb25 Ver to ATT'!$B:$G,6,FALSE), "NO MIGRADO") -> Galaxy | W70: 15
A71: 287289507033X06092025 | B71: AT&T | C71: JUNIO | D71: 6 | E71: 2025 | F71: 9 | G71: NICOLAS QUIJANO 2 | H71: 615-830-6700 | I71: 141 | J71: -$8.34 | K71: $50.00 | L71: - | M71: $4.75 | N71: $4.30 | P71: 50.71 | Q71: 60311005 | R71: 06 | S71: 0600 | T71: 060000 | U71: =IFERROR(+VLOOKUP(H71,'DISPOSITIVOS ACTIVOS'!B:D,3,FALSE),"IPHONE") -> Iphone | V71: =IFERROR(+VLOOKUP(H71,'[1]Migracion feb25 Ver to ATT'!$B:$G,6,FALSE), "NO MIGRADO") -> NO MIGRADO | W71: 25
A72: 287289507033X06092025 | B72: AT&T | C72: JUNIO | D72: 6 | E72: 2025 | F72: 9 | G72: NAYRE PEREZ | H72: 615-840-0789 | I72: 143 | J72: -$8.34 | K72: $50.00 | L72: - | M72: $4.75 | N72: $4.30 | P72: 50.71 | Q72: 60311005 | R72: 04 | S72: 0401 | T72: 040101 | U72: =IFERROR(+VLOOKUP(H72,'DISPOSITIVOS ACTIVOS'!B:D,3,FALSE),"IPHONE") -> Iphone | V72: =IFERROR(+VLOOKUP(H72,'[1]Migracion feb25 Ver to ATT'!$B:$G,6,FALSE), "NO MIGRADO") -> Iphone | W72: 15
A73: 287289507033X06092025 | B73: AT&T | C73: JUNIO | D73: 6 | E73: 2025 | F73: 9 | G73: MARCELA ROA | H73: 615-854-5649 | I73: 145 | J73: -$8.34 | K73: $50.00 | L73: - | M73: $4.75 | N73: $4.30 | P73: 50.71 | Q73: 60311005 | R73: 04 | S73: 0401 | T73: 040105 | U73: =IFERROR(+VLOOKUP(H73,'DISPOSITIVOS ACTIVOS'!B:D,3,FALSE),"IPHONE") -> Iphone | V73: =IFERROR(+VLOOKUP(H73,'[1]Migracion feb25 Ver to ATT'!$B:$G,6,FALSE), "NO MIGRADO") -> Iphone | W73: 15
A74: 287289507033X06092025 | B74: AT&T | C74: JUNIO | D74: 6 | E74: 2025 | F74: 9 | G74: CAROLINA TORREALBA | H74: 615-854-5797 | I74: 147 | J74: -$8.34 | K74: $50.00 | L74: - | M74: $4.75 | N74: $4.30 | P74: 50.71 | Q74: 60311005 | R74: 04 | S74: 0401 | T74: 040103 | U74: =IFERROR(+VLOOKUP(H74,'DISPOSITIVOS ACTIVOS'!B:D,3,FALSE),"IPHONE") -> Iphone | V74: =IFERROR(+VLOOKUP(H74,'[1]Migracion feb25 Ver to ATT'!$B:$G,6,FALSE), "NO MIGRADO") -> Iphone | W74: 15
A75: 287289507033X06092025 | B75: AT&T | C75: JUNIO | D75: 6 | E75: 2025 | F75: 9 | G75: JORGE TENGREDI | H75: 615-862-1976 | I75: 149 | J75: -$8.34 | K75: $50.00 | L75: - | M75: $4.75 | N75: $4.25 | P75: 50.66 | Q75: 60311005 | R75: 03 | S75: 0303 | T75: 030301 | U75: =IFERROR(+VLOOKUP(H75,'DISPOSITIVOS ACTIVOS'!B:D,3,FALSE),"IPHONE") -> Galaxy | V75: =IFERROR(+VLOOKUP(H75,'[1]Migracion feb25 Ver to ATT'!$B:$G,6,FALSE), "NO MIGRADO") -> Galaxy | W75: 15
A76: 287289507033X06092025 | B76: AT&T | C76: JUNIO | D76: 6 | E76: 2025 | F76: 9 | G76: RUDY BAHENA LG | H76: 615-862-9402 | I76: 151 | J76: $0.00 | K76: $25.00 | L76: - | M76: $4.54 | N76: $7.20 | P76: 36.74 | Q76: 60311005 | R76: 03 | S76: 0303 | T76: 030303 | U76: =IFERROR(+VLOOKUP(H76,'DISPOSITIVOS ACTIVOS'!B:D,3,FALSE),"IPHONE") -> Galaxy | V76: =IFERROR(+VLOOKUP(H76,'[1]Migracion feb25 Ver to ATT'!$B:$G,6,FALSE), "NO MIGRADO") -> NO MIGRADO | W76: 25
A77: 287289507033X06092025 | B77: AT&T | C77: JUNIO | D77: 6 | E77: 2025 | F77: 9 | G77: LUIS PARADA | H77: 615-878-0405 | I77: 153 | J77: -$8.34 | K77: $50.00 | L77: - | M77: $4.75 | N77: $4.30 | P77: 50.71 | Q77: 60311005 | R77: 04 | S77: 0402 | T77: 040202 | U77: =IFERROR(+VLOOKUP(H77,'DISPOSITIVOS ACTIVOS'!B:D,3,FALSE),"IPHONE") -> 0 | V77: =IFERROR(+VLOOKUP(H77,'[1]Migracion feb25 Ver to ATT'!$B:$G,6,FALSE), "NO MIGRADO") -> Iphone | W77: 15
A78: 287289507033X06092025 | B78: AT&T | C78: JUNIO | D78: 6 | E78: 2025 | F78: 9 | G78: ANDRES FUENMAYOR | H78: 615-879-8762 | I78: 155 | J78: -$8.34 | K78: $50.00 | L78: - | M78: $4.75 | N78: $4.25 | P78: 50.66 | Q78: 60311005 | R78: 03 | S78: 0303 | T78: 030301 | U78: =IFERROR(+VLOOKUP(H78,'DISPOSITIVOS ACTIVOS'!B:D,3,FALSE),"IPHONE") -> Galaxy | V78: =IFERROR(+VLOOKUP(H78,'[1]Migracion feb25 Ver to ATT'!$B:$G,6,FALSE), "NO MIGRADO") -> Galaxy | W78: 15
A79: 287289507033X06092025 | B79: AT&T | C79: JUNIO | D79: 6 | E79: 2025 | F79: 9 | G79: RUDY BAHENA | H79: 615-906-5129 | I79: 157 | J79: -$8.34 | K79: $50.00 | L79: - | M79: $4.75 | N79: $4.25 | P79: 50.66 | Q79: 60311005 | R79: 03 | S79: 0303 | T79: 030303 | U79: =IFERROR(+VLOOKUP(H79,'DISPOSITIVOS ACTIVOS'!B:D,3,FALSE),"IPHONE") -> Galaxy | V79: =IFERROR(+VLOOKUP(H79,'[1]Migracion feb25 Ver to ATT'!$B:$G,6,FALSE), "NO MIGRADO") -> Galaxy | W79: 15
A80: 287289507033X06092025 | B80: AT&T | C80: JUNIO | D80: 6 | E80: 2025 | F80: 9 | G80: GABRIEL NASHVILLE | H80: 615-939-6293 | I80: 159 | J80: $12.50 | K80: $25.00 | L80: - | M80: $1.47 | N80: $3.66 | P80: 42.63 | Q80: 60311005 | R80: 04 | S80: 0401 | T80: 040101 | U80: =IFERROR(+VLOOKUP(H80,'DISPOSITIVOS ACTIVOS'!B:D,3,FALSE),"IPHONE") -> IPHONE | V80: =IFERROR(+VLOOKUP(H80,'[1]Migracion feb25 Ver to ATT'!$B:$G,6,FALSE), "NO MIGRADO") -> NO MIGRADO | W80: 25
A81: 287289507033X06092025 | B81: AT&T | C81: JUNIO | D81: 6 | E81: 2025 | F81: 9 | G81: ALBERT CARDOZO | H81: 615-939-8241 | I81: 161 | J81: -$8.34 | K81: $50.00 | L81: - | M81: $4.75 | N81: $4.30 | P81: 50.71 | Q81: 10145005 | U81: =IFERROR(+VLOOKUP(H81,'DISPOSITIVOS ACTIVOS'!B:D,3,FALSE),"IPHONE") -> Iphone | V81: =IFERROR(+VLOOKUP(H81,'[1]Migracion feb25 Ver to ATT'!$B:$G,6,FALSE), "NO MIGRADO") -> Iphone | W81: 15
A82: 287289507033X06092025 | B82: AT&T | C82: JUNIO | D82: 6 | E82: 2025 | F82: 9 | G82: EDWIN GONZALEZ | H82: 615-939-9582 | I82: 163 | J82: $0.00 | K82: $25.00 | L82: - | M82: $4.54 | N82: $7.20 | P82: 36.74 | Q82: 60311005 | R82: 06 | S82: 0600 | T82: 060000 | U82: =IFERROR(+VLOOKUP(H82,'DISPOSITIVOS ACTIVOS'!B:D,3,FALSE),"IPHONE") -> Galaxy | V82: =IFERROR(+VLOOKUP(H82,'[1]Migracion feb25 Ver to ATT'!$B:$G,6,FALSE), "NO MIGRADO") -> NO MIGRADO | W82: 25
A83: 287289507033X06092025 | B83: AT&T | C83: JUNIO | D83: 6 | E83: 2025 | F83: 9 | G83: LEONARDO PALENCIA I... | H83: 615-944-5380 | I83: 165 | J83: - | K83: $15.00 | L83: - | M83: $3.75 | N83: - | P83: 18.75 | Q83: 60311003 | R83: 04 | S83: 0401 | T83: 040101 | U83: =IFERROR(+VLOOKUP(H83,'DISPOSITIVOS ACTIVOS'!B:D,3,FALSE),"IPHONE") -> Ipad | V83: =IFERROR(+VLOOKUP(H83,'[1]Migracion feb25 Ver to ATT'!$B:$G,6,FALSE), "NO MIGRADO") -> NO MIGRADO | W83: 15
A84: 287289507033X06092025 | B84: AT&T | C84: JUNIO | D84: 6 | E84: 2025 | F84: 9 | G84: IVAN TELLO IPAD | H84: 615-945-4365 | I84: 167 | J84: - | K84: $15.00 | L84: - | M84: $3.75 | N84: - | P84: 18.75 | Q84: 60311003 | R84: 04 | S84: 0401 | T84: 040101 | U84: =IFERROR(+VLOOKUP(H84,'DISPOSITIVOS ACTIVOS'!B:D,3,FALSE),"IPHONE") -> Ipad | V84: =IFERROR(+VLOOKUP(H84,'[1]Migracion feb25 Ver to ATT'!$B:$G,6,FALSE), "NO MIGRADO") -> NO MIGRADO | W84: 15
A85: 287289507033X06092025 | B85: AT&T | C85: JUNIO | D85: 6 | E85: 2025 | F85: 9 | G85: JOSE BURGOS | H85: 615-961-5944 | I85: 169 | J85: -$8.34 | K85: $50.00 | L85: - | M85: $4.75 | N85: $4.30 | P85: 50.71 | Q85: 60311005 | R85: 04 | S85: 0401 | T85: 040103 | U85: =IFERROR(+VLOOKUP(H85,'DISPOSITIVOS ACTIVOS'!B:D,3,FALSE),"IPHONE") -> Iphone | V85: =IFERROR(+VLOOKUP(H85,'[1]Migracion feb25 Ver to ATT'!$B:$G,6,FALSE), "NO MIGRADO") -> Iphone | W85: 15
A86: 287289507033X06092025 | B86: AT&T | C86: JUNIO | D86: 6 | E86: 2025 | F86: 9 | G86: AUGUSTO IPAD | H86: 615-967-4046 | I86: 171 | J86: - | K86: $15.00 | L86: - | M86: $3.75 | N86: - | P86: 18.75 | Q86: 60311003 | R86: 04 | S86: 0401 | T86: 040102 | U86: =IFERROR(+VLOOKUP(H86,'DISPOSITIVOS ACTIVOS'!B:D,3,FALSE),"IPHONE") -> Ipad | V86: =IFERROR(+VLOOKUP(H86,'[1]Migracion feb25 Ver to ATT'!$B:$G,6,FALSE), "NO MIGRADO") -> NO MIGRADO | W86: 15
A87: 287289507033X06092025 | B87: AT&T | C87: JUNIO | D87: 6 | E87: 2025 | F87: 9 | G87: KARLA SOLIS | H87: 615-969-5642 | I87: 173 | J87: $0.00 | K87: $25.00 | L87: - | M87: $4.54 | N87: $7.20 | P87: 36.74 | Q87: 60311005 | R87: 04 | S87: 0401 | T87: 040103 | U87: =IFERROR(+VLOOKUP(H87,'DISPOSITIVOS ACTIVOS'!B:D,3,FALSE),"IPHONE") -> Iphone | V87: =IFERROR(+VLOOKUP(H87,'[1]Migracion feb25 Ver to ATT'!$B:$G,6,FALSE), "NO MIGRADO") -> NO MIGRADO | W87: 25
A88: 287289507033X06092025 | B88: AT&T | C88: JUNIO | D88: 6 | E88: 2025 | F88: 9 | G88: DILVER GARCIA IPAD | H88: 615-984-9515 | I88: 175 | J88: - | K88: $15.00 | L88: - | M88: $3.75 | N88: - | P88: 18.75 | Q88: 10145005 | U88: =IFERROR(+VLOOKUP(H88,'DISPOSITIVOS ACTIVOS'!B:D,3,FALSE),"IPHONE") -> Galaxy | V88: =IFERROR(+VLOOKUP(H88,'[1]Migracion feb25 Ver to ATT'!$B:$G,6,FALSE), "NO MIGRADO") -> NO MIGRADO | W88: 25
A89: 287289507033X06092025 | B89: AT&T | C89: JUNIO | D89: 6 | E89: 2025 | F89: 9 | G89: CARMEN LONGA LG | H89: 629-239-0377 | I89: 177 | J89: $0.00 | K89: $25.00 | L89: - | M89: $4.54 | N89: $7.20 | P89: 36.74 | Q89: 60311005 | R89: 03 | S89: 0303 | T89: 030303 | U89: =IFERROR(+VLOOKUP(H89,'DISPOSITIVOS ACTIVOS'!B:D,3,FALSE),"IPHONE") -> Iphone | V89: =IFERROR(+VLOOKUP(H89,'[1]Migracion feb25 Ver to ATT'!$B:$G,6,FALSE), "NO MIGRADO") -> NO MIGRADO | W89: 25
A90: 287289507033X06092025 | B90: AT&T | C90: JUNIO | D90: 6 | E90: 2025 | F90: 9 | G90: JOSE LUCIO | H90: 629-239-0999 | I90: 179 | J90: -$8.34 | K90: $50.00 | L90: - | M90: $4.75 | N90: $4.30 | P90: 50.71 | Q90: 60311005 | R90: 04 | S90: 0401 | T90: 040102 | U90: =IFERROR(+VLOOKUP(H90,'DISPOSITIVOS ACTIVOS'!B:D,3,FALSE),"IPHONE") -> Iphone | V90: =IFERROR(+VLOOKUP(H90,'[1]Migracion feb25 Ver to ATT'!$B:$G,6,FALSE), "NO MIGRADO") -> Iphone | W90: 15
A91: 287289507033X06092025 | B91: AT&T | C91: JUNIO | D91: 6 | E91: 2025 | F91: 9 | G91: YNGEL GUTIERREZ | H91: 629-256-6967 | I91: 181 | J91: - | K91: $15.00 | L91: - | M91: $3.75 | N91: - | P91: 18.75 | Q91: 60311003 | R91: 04 | S91: 0401 | T91: 040101 | U91: =IFERROR(+VLOOKUP(H91,'DISPOSITIVOS ACTIVOS'!B:D,3,FALSE),"IPHONE") -> Ipad | V91: =IFERROR(+VLOOKUP(H91,'[1]Migracion feb25 Ver to ATT'!$B:$G,6,FALSE), "NO MIGRADO") -> NO MIGRADO | W91: 15
A92: 287289507033X06092025 | B92: AT&T | C92: JUNIO | D92: 6 | E92: 2025 | F92: 9 | G92: YNGEL GUTIERREZ | H92: 629-256-9168 | I92: 183 | J92: -$8.34 | K92: $50.00 | L92: - | M92: $4.75 | N92: $4.30 | P92: 50.71 | Q92: 60311005 | R92: 04 | S92: 0401 | T92: 040101 | U92: =IFERROR(+VLOOKUP(H92,'DISPOSITIVOS ACTIVOS'!B:D,3,FALSE),"IPHONE") -> Iphone | V92: =IFERROR(+VLOOKUP(H92,'[1]Migracion feb25 Ver to ATT'!$B:$G,6,FALSE), "NO MIGRADO") -> Iphone | W92: 15
A93: 287289507033X06092025 | B93: AT&T | C93: JUNIO | D93: 6 | E93: 2025 | F93: 9 | G93: RICARDO BRITO HR | H93: 629-264-3070 | I93: 185 | J93: $0.00 | K93: $25.00 | L93: - | M93: $4.54 | N93: $7.20 | P93: 36.74 | Q93: 60311005 | R93: 09 | S93: 0900 | T93: 090000 | U93: =IFERROR(+VLOOKUP(H93,'DISPOSITIVOS ACTIVOS'!B:D,3,FALSE),"IPHONE") -> Iphone | V93: =IFERROR(+VLOOKUP(H93,'[1]Migracion feb25 Ver to ATT'!$B:$G,6,FALSE), "NO MIGRADO") -> NO MIGRADO | W93: 25
A94: 287289507033X06092025 | B94: AT&T | C94: JUNIO | D94: 6 | E94: 2025 | F94: 9 | G94: MIGUEL ZUBILLAGA | H94: 629-285-9899 | I94: 187 | J94: $0.00 | K94: $25.00 | L94: $20.00 | M94: $4.54 | N94: $7.20 | P94: 56.74 | Q94: 60311005 | R94: 11 | S94: 1100 | T94: 110002 | U94: =IFERROR(+VLOOKUP(H94,'DISPOSITIVOS ACTIVOS'!B:D,3,FALSE),"IPHONE") -> Iphone | V94: =IFERROR(+VLOOKUP(H94,'[1]Migracion feb25 Ver to ATT'!$B:$G,6,FALSE), "NO MIGRADO") -> NO MIGRADO | W94: 25
A95: 287289507033X06092025 | B95: AT&T | C95: JUNIO | D95: 6 | E95: 2025 | F95: 9 | G95: IPADALA BAMADSD | H95: 629-318-8877 | I95: 189 | J95: - | K95: $15.00 | L95: - | M95: $3.75 | N95: - | P95: 18.75 | Q95: 10145005 | U95: =IFERROR(+VLOOKUP(H95,'DISPOSITIVOS ACTIVOS'!B:D,3,FALSE),"IPHONE") -> Ipad | V95: =IFERROR(+VLOOKUP(H95,'[1]Migracion feb25 Ver to ATT'!$B:$G,6,FALSE), "NO MIGRADO") -> NO MIGRADO | W95: 15
A96: 287289507033X06092025 | B96: AT&T | C96: JUNIO | D96: 6 | E96: 2025 | F96: 9 | G96: IPAD DE NACOMY | H96: 629-318-9009 | I96: 191 | J96: - | K96: $10.00 | L96: - | M96: - | N96: - | P96: 10 | Q96: 60311005 | R96: 04 | S96: 0401 | T96: 040101 | U96: =IFERROR(+VLOOKUP(H96,'DISPOSITIVOS ACTIVOS'!B:D,3,FALSE),"IPHONE") -> IPHONE | V96: =IFERROR(+VLOOKUP(H96,'[1]Migracion feb25 Ver to ATT'!$B:$G,6,FALSE), "NO MIGRADO") -> NO MIGRADO | W96: 25
A97: 287289507033X06092025 | B97: AT&T | C97: JUNIO | D97: 6 | E97: 2025 | F97: 9 | G97: IPADREYNA VIVASDSD | H97: 629-318-9109 | I97: 193 | J97: - | K97: $15.00 | L97: - | M97: $3.75 | N97: - | P97: 18.75 | Q97: 10145005 | U97: =IFERROR(+VLOOKUP(H97,'DISPOSITIVOS ACTIVOS'!B:D,3,FALSE),"IPHONE") -> Ipad | V97: =IFERROR(+VLOOKUP(H97,'[1]Migracion feb25 Ver to ATT'!$B:$G,6,FALSE), "NO MIGRADO") -> NO MIGRADO | W97: 15
A98: 287289507033X06092025 | B98: AT&T | C98: JUNIO | D98: 6 | E98: 2025 | F98: 9 | G98: ROSMARY LA CRUZ IPA... | H98: 629-345-1182 | I98: 195 | J98: - | K98: $15.00 | L98: - | M98: $3.75 | N98: - | P98: 18.75 | Q98: 60311003 | R98: 04 | S98: 0401 | T98: 040103 | U98: =IFERROR(+VLOOKUP(H98,'DISPOSITIVOS ACTIVOS'!B:D,3,FALSE),"IPHONE") -> Ipad | V98: =IFERROR(+VLOOKUP(H98,'[1]Migracion feb25 Ver to ATT'!$B:$G,6,FALSE), "NO MIGRADO") -> NO MIGRADO | W98: 15
A99: 287289507033X06092025 | B99: AT&T | C99: JUNIO | D99: 6 | E99: 2025 | F99: 9 | G99: IPHONE 14 | H99: 629-345-1381 | I99: 197 | J99: $0.00 | K99: $25.00 | L99: $5.99 | M99: $4.54 | N99: $7.20 | P99: 42.73 | Q99: 60311005 | R99: 04 | S99: 0401 | T99: 040101 | U99: =IFERROR(+VLOOKUP(H99,'DISPOSITIVOS ACTIVOS'!B:D,3,FALSE),"IPHONE") -> Iphone | V99: =IFERROR(+VLOOKUP(H99,'[1]Migracion feb25 Ver to ATT'!$B:$G,6,FALSE), "NO MIGRADO") -> NO MIGRADO | W99: 25
A100: 287289507033X06092025 | B100: AT&T | C100: JUNIO | D100: 6 | E100: 2025 | F100: 9 | G100: IPAD DISTRIBUIDORA ... | H100: 629-345-1574 | I100: 199 | J100: - | K100: $15.00 | L100: $12.78 | M100: $3.75 | N100: - | P100: 31.53 | Q100: 60311003 | R100: 04 | S100: 0401 | T100: 040101 | U100: =IFERROR(+VLOOKUP(H100,'DISPOSITIVOS ACTIVOS'!B:D,3,FALSE),"IPHONE") -> Ipad | V100: =IFERROR(+VLOOKUP(H100,'[1]Migracion feb25 Ver to ATT'!$B:$G,6,FALSE), "NO MIGRADO") -> NO MIGRADO | W100: 15
A101: 287289507033X06092025 | B101: AT&T | C101: JUNIO | D101: 6 | E101: 2025 | F101: 9 | G101: IPHONE 14 | H101: 629-345-1642 | I101: 201 | J101: $0.00 | K101: $25.00 | L101: $5.99 | M101: $4.54 | N101: $7.20 | P101: 42.73 | Q101: 60311005 | R101: 04 | S101: 0402 | T101: 040204 | U101: =IFERROR(+VLOOKUP(H101,'DISPOSITIVOS ACTIVOS'!B:D,3,FALSE),"IPHONE") -> Iphone | V101: =IFERROR(+VLOOKUP(H101,'[1]Migracion feb25 Ver to ATT'!$B:$G,6,FALSE), "NO MIGRADO") -> NO MIGRADO | W101: 25
A102: 287289507033X06092025 | B102: AT&T | C102: JUNIO | D102: 6 | E102: 2025 | F102: 9 | G102: RADDY GARCIA SA | H102: 629-345-1645 | I102: 203 | J102: $0.00 | K102: $25.00 | L102: $5.99 | M102: $4.54 | N102: $7.20 | P102: 42.73 | Q102: 60311005 | R102: 04 | S102: 0401 | T102: 040102 | U102: =IFERROR(+VLOOKUP(H102,'DISPOSITIVOS ACTIVOS'!B:D,3,FALSE),"IPHONE") -> Iphone | V102: =IFERROR(+VLOOKUP(H102,'[1]Migracion feb25 Ver to ATT'!$B:$G,6,FALSE), "NO MIGRADO") -> NO MIGRADO | W102: 25
A103: 287289507033X06092025 | B103: AT&T | C103: JUNIO | D103: 6 | E103: 2025 | F103: 9 | G103: IPAD DISTRIBUIDORA ... | H103: 629-345-1705 | I103: 205 | J103: - | K103: $15.00 | L103: $12.78 | M103: $3.75 | N103: - | P103: 31.53 | Q103: 60311003 | R103: 04 | S103: 0402 | T103: 040204 | U103: =IFERROR(+VLOOKUP(H103,'DISPOSITIVOS ACTIVOS'!B:D,3,FALSE),"IPHONE") -> Ipad | V103: =IFERROR(+VLOOKUP(H103,'[1]Migracion feb25 Ver to ATT'!$B:$G,6,FALSE), "NO MIGRADO") -> NO MIGRADO | W103: 15
A104: 287289507033X06092025 | B104: AT&T | C104: JUNIO | D104: 6 | E104: 2025 | F104: 9 | G104: IPAD DISTRIBUIDORA ... | H104: 629-345-1728 | I104: 207 | J104: - | K104: $15.00 | L104: $12.78 | M104: $3.75 | N104: - | P104: 31.53 | Q104: 60311003 | R104: 04 | S104: 0401 | T104: 040102 | U104: =IFERROR(+VLOOKUP(H104,'DISPOSITIVOS ACTIVOS'!B:D,3,FALSE),"IPHONE") -> Ipad | V104: =IFERROR(+VLOOKUP(H104,'[1]Migracion feb25 Ver to ATT'!$B:$G,6,FALSE), "NO MIGRADO") -> NO MIGRADO | W104: 15
A105: 287289507033X06092025 | B105: AT&T | C105: JUNIO | D105: 6 | E105: 2025 | F105: 9 | G105: REPLACEMENT LOST PHONE | H105: 629-468-1066 | I105: 209 | J105: - | K105: - | L105: $5.99 | M105: - | N105: - | P105: 5.99 | Q105: 60311005 | R105: 04 | S105: 0401 | T105: 040101 | U105: =IFERROR(+VLOOKUP(H105,'DISPOSITIVOS ACTIVOS'!B:D,3,FALSE),"IPHONE") -> IPHONE | V105: =IFERROR(+VLOOKUP(H105,'[1]Migracion feb25 Ver to ATT'!$B:$G,6,FALSE), "NO MIGRADO") -> NO MIGRADO | W105: 25
A106: 287289507033X06092025 | B106: AT&T | C106: JUNIO | D106: 6 | E106: 2025 | F106: 9 | G106: MARANGELIE RIVERA | H106: 629-468-8256 | I106: 211 | J106: $0.00 | K106: $25.00 | L106: - | M106: $4.54 | N106: $7.20 | P106: 36.74 | Q106: 10145005 | U106: =IFERROR(+VLOOKUP(H106,'DISPOSITIVOS ACTIVOS'!B:D,3,FALSE),"IPHONE") -> 0 | V106: =IFERROR(+VLOOKUP(H106,'[1]Migracion feb25 Ver to ATT'!$B:$G,6,FALSE), "NO MIGRADO") -> NO MIGRADO | W106: 25
...

Sheet Sheet4
A1: Proveedor | B1: (All)
A3: Row Labels | B3: Sum of TOTAL REVISADO | C3: Sum of VALOR AJUSTADO
A4: 3 | B4: 6238.23 | C4: 2585
A5: 4 | B5: 3827.97 | C5: 2157.78
A6: 5 | B6: 5246.05 | C6: 2780
A7: Grand Total | B7: 15312.25 | C7: 7522.78

Sheet FACTURAS
A1: Proveedor | B1: Year | C1: Month | D1: Number | E1: USER | F1: asa | G1: Activity | H1: Monthly charges | I1: Equipment | J1: Company | K1: Government | L1: total | M1: TOTAL REVISADO | N1: DISPOSITIVO | O1: USER REAL | P1: CECO | Q1: MIGRADO | R1: VALOR AJUSTADO
A2: AT&T | B2: 25 | C2: 3 | D2: 629-345-1381 | E2: IPHONE 14 | F2: 13 | G2: -4.17 | H2: 45 | I2: 5.99 | J2: 4.36 | K2: 2.08 | L2: 53.26 | M2: =+L2 -> 53.26 | N2: =+VLOOKUP(D2,'DISPOSITIVOS ACTIVOS'!B:D,3,FALSE) -> Iphone | O2: =+VLOOKUP(D2,'DISPOSITIVOS ACTIVOS'!B:G,6,FALSE) -> RIVERO, LUIS MARIANO | P2: =+VLOOKUP(D2,'DISPOSITIVOS ACTIVOS'!$B$1:$H$299,7,FALSE) -> SALES CENTRAL | Q2: =IFERROR(+VLOOKUP(D2,'[1]Migracion feb25 Ver to ATT'!$B:$B,1,FALSE), "NO") -> NO | R2: =+IF(Q2="NO",25,15) -> 25
A3: AT&T | B3: 25 | C3: 3 | D3: 629-345-1642 | E3: IPHONE 14 | F3: 15 | G3: -4.17 | H3: 45 | I3: 5.99 | J3: 4.36 | K3: 2.08 | L3: 53.26 | M3: =+L3 -> 53.26 | N3: =+VLOOKUP(D3,'DISPOSITIVOS ACTIVOS'!B:D,3,FALSE) -> Iphone | O3: =+VLOOKUP(D3,'DISPOSITIVOS ACTIVOS'!B:G,6,FALSE) -> CALDERON, PILAR ESTRADA | P3: =+VLOOKUP(D3,'DISPOSITIVOS ACTIVOS'!$B$1:$H$299,7,FALSE) -> MERCHANDISER SOUTH | Q3: =IFERROR(+VLOOKUP(D3,'[1]Migracion feb25 Ver to ATT'!$B:$B,1,FALSE), "NO") -> NO | R3: =+IF(Q3="NO",25,15) -> 25
A4: AT&T | B4: 25 | C4: 3 | D4: 629-345-1645 | E4: RADDY GARCIA SA | F4: 17 | G4: -4.17 | H4: 45 | I4: 5.99 | J4: 4.36 | K4: 2.08 | L4: 53.26 | M4: =+L4 -> 53.26 | N4: =+VLOOKUP(D4,'DISPOSITIVOS ACTIVOS'!B:D,3,FALSE) -> Iphone | O4: =+VLOOKUP(D4,'DISPOSITIVOS ACTIVOS'!B:G,6,FALSE) -> GARCIA, RADDY | P4: =+VLOOKUP(D4,'DISPOSITIVOS ACTIVOS'!$B$1:$H$299,7,FALSE) -> SALES NORTH | Q4: =IFERROR(+VLOOKUP(D4,'[1]Migracion feb25 Ver to ATT'!$B:$B,1,FALSE), "NO") -> NO | R4: =+IF(Q4="NO",25,15) -> 25
A5: AT&T | B5: 25 | C5: 3 | D5: 678-477-4654 | E5: IPAD SALES | F5: 19 | G5: -5 | H5: 20 | I5: - | J5: 3.75 | K5: - | L5: 18.75 | M5: =+L5 -> 18.75 | N5: =+VLOOKUP(D5,'DISPOSITIVOS ACTIVOS'!B:D,3,FALSE) -> no aplica | O5: =+VLOOKUP(D5,'DISPOSITIVOS ACTIVOS'!B:G,6,FALSE) -> IPAD SALES | P5: =+VLOOKUP(D5,'DISPOSITIVOS ACTIVOS'!$B$1:$H$299,7,FALSE) -> ATLANTA | Q5: =IFERROR(+VLOOKUP(D5,'[1]Migracion feb25 Ver to ATT'!$B:$B,1,FALSE), "NO") -> NO | R5: =+IF(Q5="NO",25,15) -> 25
A6: AT&T | B6: 25 | C6: 3 | D6: 678-925-1523 | E6: IPAD SALES | F6: 21 | G6: -5 | H6: 20 | I6: - | J6: 3.75 | K6: - | L6: 18.75 | M6: =+L6 -> 18.75 | N6: =+VLOOKUP(D6,'DISPOSITIVOS ACTIVOS'!B:D,3,FALSE) -> no aplica | O6: =+VLOOKUP(D6,'DISPOSITIVOS ACTIVOS'!B:G,6,FALSE) -> IPAD SALES | P6: =+VLOOKUP(D6,'DISPOSITIVOS ACTIVOS'!$B$1:$H$299,7,FALSE) -> ATLANTA | Q6: =IFERROR(+VLOOKUP(D6,'[1]Migracion feb25 Ver to ATT'!$B:$B,1,FALSE), "NO") -> NO | R6: =+IF(Q6="NO",25,15) -> 25
A7: AT&T | B7: 25 | C7: 3 | D7: 678-925-6858 | E7: IPAD SALES | F7: 23 | G7: -5 | H7: 20 | I7: - | J7: 3.75 | K7: - | L7: 18.75 | M7: =+L7 -> 18.75 | N7: =+VLOOKUP(D7,'DISPOSITIVOS ACTIVOS'!B:D,3,FALSE) -> no aplica | O7: =+VLOOKUP(D7,'DISPOSITIVOS ACTIVOS'!B:G,6,FALSE) -> IPAD SALES | P7: =+VLOOKUP(D7,'DISPOSITIVOS ACTIVOS'!$B$1:$H$299,7,FALSE) -> ATLANTA | Q7: =IFERROR(+VLOOKUP(D7,'[1]Migracion feb25 Ver to ATT'!$B:$B,1,FALSE), "NO") -> NO | R7: =+IF(Q7="NO",25,15) -> 25
A8: AT&T | B8: 25 | C8: 3 | D8: 901-464-6471 | E8: HELEN MADRIGAL | F8: 25 | G8: - | H8: 50 | I8: -0.79 | J8: 4.4 | K8: 2.12 | L8: 55.73 | M8: =+L8 -> 55.73 | N8: =+VLOOKUP(D8,'DISPOSITIVOS ACTIVOS'!B:D,3,FALSE) -> Iphone | O8: =+VLOOKUP(D8,'DISPOSITIVOS ACTIVOS'!B:G,6,FALSE) -> MADRIGAL GARCIA, HELEN C | P8: =+VLOOKUP(D8,'DISPOSITIVOS ACTIVOS'!$B$1:$H$299,7,FALSE) -> SALES NORTH | Q8: =IFERROR(+VLOOKUP(D8,'[1]Migracion feb25 Ver to ATT'!$B:$B,1,FALSE), "NO") -> NO | R8: =+IF(Q8="NO",25,15) -> 25
A9: AT&T | B9: 25 | C9: 3 | D9: 615-474-6646 | E9: JOHAN MADRIZ | F9: 27 | G9: - | H9: 20 | I9: - | J9: 3.75 | K9: - | L9: 23.75 | M9: 88.75 | N9: CANCELADO | O9: CANCELADO | P9: =+VLOOKUP(D9,'DISPOSITIVOS ACTIVOS'!$B$1:$H$299,7,FALSE) -> #N/A | Q9: =IFERROR(+VLOOKUP(D9,'[1]Migracion feb25 Ver to ATT'!$B:$B,1,FALSE), "NO") -> NO | R9: =+IF(Q9="NO",25,15) -> 25
A10: AT&T | B10: 25 | C10: 3 | D10: 629-257-4960 | E10: BACKUP INTERNET 1 | F10: 29 | G10: - | H10: 20 | I10: - | J10: 3.75 | K10: - | L10: 23.75 | M10: 63.75 | N10: Samsung | O10: =+VLOOKUP(D10,'DISPOSITIVOS ACTIVOS'!B:G,6,FALSE) -> Backup Internet | P10: =+VLOOKUP(D10,'DISPOSITIVOS ACTIVOS'!$B$1:$H$299,7,FALSE) -> SALES CENTRAL | Q10: =IFERROR(+VLOOKUP(D10,'[1]Migracion feb25 Ver to ATT'!$B:$B,1,FALSE), "NO") -> NO | R10: =+IF(Q10="NO",25,15) -> 25
A11: AT&T | B11: 25 | C11: 3 | D11: 629-258-0227 | E11: BACKUP INTERNET 2 | F11: 31 | G11: - | H11: 20 | I11: - | J11: 3.75 | K11: - | L11: 23.75 | M11: 63.75 | N11: Samsung | O11: =+VLOOKUP(D11,'DISPOSITIVOS ACTIVOS'!B:G,6,FALSE) -> Backup Internet | P11: =+VLOOKUP(D11,'DISPOSITIVOS ACTIVOS'!$B$1:$H$299,7,FALSE) -> SALES CENTRAL | Q11: =IFERROR(+VLOOKUP(D11,'[1]Migracion feb25 Ver to ATT'!$B:$B,1,FALSE), "NO") -> NO | R11: =+IF(Q11="NO",25,15) -> 25
A12: AT&T | B12: 25 | C12: 3 | D12: 615-945-4365 | E12: IVAN TELLO IPAD | F12: 33 | G12: - | H12: - | I12: - | J12: 3.75 | K12: - | L12: 3.75 | M12: 23.75 | N12: =+VLOOKUP(D12,'DISPOSITIVOS ACTIVOS'!B:D,3,FALSE) -> Ipad | O12: =+VLOOKUP(D12,'DISPOSITIVOS ACTIVOS'!B:G,6,FALSE) -> TELLO, IVAN E | P12: =+VLOOKUP(D12,'DISPOSITIVOS ACTIVOS'!$B$1:$H$299,7,FALSE) -> SALES CENTRAL | Q12: =IFERROR(+VLOOKUP(D12,'[1]Migracion feb25 Ver to ATT'!$B:$B,1,FALSE), "NO") -> NO | R12: =+IF(Q12="NO",25,15) -> 25
A13: AT&T | B13: 25 | C13: 3 | D13: 615-944-5380 | E13: LEONARDO PALENCIA I... | F13: 35 | G13: - | H13: - | I13: - | J13: 3.75 | K13: - | L13: 3.75 | M13: 23.75 | N13: =+VLOOKUP(D13,'DISPOSITIVOS ACTIVOS'!B:D,3,FALSE) -> Ipad | O13: =+VLOOKUP(D13,'DISPOSITIVOS ACTIVOS'!B:G,6,FALSE) -> PALENCIA RODRIGUEZ, LEONARDO R | P13: =+VLOOKUP(D13,'DISPOSITIVOS ACTIVOS'!$B$1:$H$299,7,FALSE) -> SALES CENTRAL | Q13: =IFERROR(+VLOOKUP(D13,'[1]Migracion feb25 Ver to ATT'!$B:$B,1,FALSE), "NO") -> NO | R13: =+IF(Q13="NO",25,15) -> 25
A14: AT&T | B14: 25 | C14: 3 | D14: 615-585-1725 | E14: SALES DSD IPAD | F14: 37 | G14: - | H14: - | I14: - | J14: 3.75 | K14: - | L14: 3.75 | M14: 23.75 | N14: CANCELADO | O14: CANCELADO | P14: =+VLOOKUP(D14,'DISPOSITIVOS ACTIVOS'!$B$1:$H$299,7,FALSE) -> #N/A | Q14: =IFERROR(+VLOOKUP(D14,'[1]Migracion feb25 Ver to ATT'!$B:$B,1,FALSE), "NO") -> NO | R14: =+IF(Q14="NO",25,15) -> 25
A15: AT&T | B15: 25 | C15: 3 | D15: 256-631-4188 | E15: DANIEL FLORES IPAD SA | F15: 39 | G15: 4.12 | H15: - | I15: - | J15: 3.75 | K15: - | L15: 7.87 | M15: 27.87 | N15: =+VLOOKUP(D15,'DISPOSITIVOS ACTIVOS'!B:D,3,FALSE) -> Ipad | O15: =+VLOOKUP(D15,'DISPOSITIVOS ACTIVOS'!B:G,6,FALSE) -> FLORES, JOSE DANIEL | P15: =+VLOOKUP(D15,'DISPOSITIVOS ACTIVOS'!$B$1:$H$299,7,FALSE) -> SALES SOUTH | Q15: =IFERROR(+VLOOKUP(D15,'[1]Migracion feb25 Ver to ATT'!$B:$B,1,FALSE), "NO") -> NO | R15: =+IF(Q15="NO",25,15) -> 25
A16: AT&T | B16: 25 | C16: 3 | D16: 629-345-1182 | E16: ROSMARY LA CRUZ IPA... | F16: 41 | G16: - | H16: - | I16: - | J16: 3.75 | K16: - | L16: 3.75 | M16: 23.75 | N16: =+VLOOKUP(D16,'DISPOSITIVOS ACTIVOS'!B:D,3,FALSE) -> Ipad | O16: =+VLOOKUP(D16,'DISPOSITIVOS ACTIVOS'!B:G,6,FALSE) -> LACRUZ, ROSMARY | P16: =+VLOOKUP(D16,'DISPOSITIVOS ACTIVOS'!$B$1:$H$299,7,FALSE) -> SALES WEST | Q16: =IFERROR(+VLOOKUP(D16,'[1]Migracion feb25 Ver to ATT'!$B:$B,1,FALSE), "NO") -> NO | R16: =+IF(Q16="NO",25,15) -> 25
A17: AT&T | B17: 25 | C17: 3 | D17: 901-467-5902 | E17: HELEN MADRIGAL IPAD SA | F17: 43 | G17: - | H17: - | I17: - | J17: 3.75 | K17: - | L17: 3.75 | M17: 23.75 | N17: =+VLOOKUP(D17,'DISPOSITIVOS ACTIVOS'!B:D,3,FALSE) -> Ipad | O17: =+VLOOKUP(D17,'DISPOSITIVOS ACTIVOS'!B:G,6,FALSE) -> MADRIGAL GARCIA, HELEN C | P17: =+VLOOKUP(D17,'DISPOSITIVOS ACTIVOS'!$B$1:$H$299,7,FALSE) -> SALES NORTH | Q17: =IFERROR(+VLOOKUP(D17,'[1]Migracion feb25 Ver to ATT'!$B:$B,1,FALSE), "NO") -> NO | R17: =+IF(Q17="NO",25,15) -> 25
A18: AT&T | B18: 25 | C18: 3 | D18: 629-345-1728 | E18: IPAD DISTRIBUIDORA ... | F18: 45 | G18: - | H18: - | I18: 12.78 | J18: 3.75 | K18: - | L18: 16.53 | M18: 36.53 | N18: =+VLOOKUP(D18,'DISPOSITIVOS ACTIVOS'!B:D,3,FALSE) -> Ipad | O18: =+VLOOKUP(D18,'DISPOSITIVOS ACTIVOS'!B:G,6,FALSE) -> GARCIA, RADDY | P18: =+VLOOKUP(D18,'DISPOSITIVOS ACTIVOS'!$B$1:$H$299,7,FALSE) -> SALES NORTH | Q18: =IFERROR(+VLOOKUP(D18,'[1]Migracion feb25 Ver to ATT'!$B:$B,1,FALSE), "NO") -> NO | R18: =+IF(Q18="NO",25,15) -> 25
A19: AT&T | B19: 25 | C19: 3 | D19: 629-345-1705 | E19: IPAD DISTRIBUIDORA ... | F19: 47 | G19: - | H19: - | I19: 12.78 | J19: 3.75 | K19: - | L19: 16.53 | M19: 36.53 | N19: =+VLOOKUP(D19,'DISPOSITIVOS ACTIVOS'!B:D,3,FALSE) -> Ipad | O19: =+VLOOKUP(D19,'DISPOSITIVOS ACTIVOS'!B:G,6,FALSE) -> CALDERON, PILAR ESTRADA | P19: =+VLOOKUP(D19,'DISPOSITIVOS ACTIVOS'!$B$1:$H$299,7,FALSE) -> MERCHANDISER SOUTH | Q19: =IFERROR(+VLOOKUP(D19,'[1]Migracion feb25 Ver to ATT'!$B:$B,1,FALSE), "NO") -> NO | R19: =+IF(Q19="NO",25,15) -> 25
A20: AT&T | B20: 25 | C20: 3 | D20: 629-345-1574 | E20: IPAD DISTRIBUIDORA ... | F20: 49 | G20: - | H20: - | I20: 12.78 | J20: 3.75 | K20: - | L20: 16.53 | M20: 36.53 | N20: =+VLOOKUP(D20,'DISPOSITIVOS ACTIVOS'!B:D,3,FALSE) -> Ipad | O20: =+VLOOKUP(D20,'DISPOSITIVOS ACTIVOS'!B:G,6,FALSE) -> RIVERO, LUIS MARIANO | P20: =+VLOOKUP(D20,'DISPOSITIVOS ACTIVOS'!$B$1:$H$299,7,FALSE) -> SALES CENTRAL | Q20: =IFERROR(+VLOOKUP(D20,'[1]Migracion feb25 Ver to ATT'!$B:$B,1,FALSE), "NO") -> NO | R20: =+IF(Q20="NO",25,15) -> 25
A21: AT&T | B21: 25 | C21: 3 | D21: 629-729-3294 | E21: IPAD EDILIA SHINE | F21: 51 | G21: - | H21: - | I21: - | J21: 3.75 | K21: - | L21: 3.75 | M21: 23.75 | N21: =+VLOOKUP(D21,'DISPOSITIVOS ACTIVOS'!B:D,3,FALSE) -> Ipad | O21: =+VLOOKUP(D21,'DISPOSITIVOS ACTIVOS'!B:G,6,FALSE) -> SHINE, EDILIA D | P21: =+VLOOKUP(D21,'DISPOSITIVOS ACTIVOS'!$B$1:$H$299,7,FALSE) -> SALES NORTH | Q21: =IFERROR(+VLOOKUP(D21,'[1]Migracion feb25 Ver to ATT'!$B:$B,1,FALSE), "NO") -> NO | R21: =+IF(Q21="NO",25,15) -> 25
A22: AT&T | B22: 25 | C22: 3 | D22: 629-729-3287 | E22: IPAD RAFAEL CHANCHA... | F22: 53 | G22: - | H22: - | I22: - | J22: 3.75 | K22: - | L22: 3.75 | M22: 23.75 | N22: =+VLOOKUP(D22,'DISPOSITIVOS ACTIVOS'!B:D,3,FALSE) -> Ipad | O22: =+VLOOKUP(D22,'DISPOSITIVOS ACTIVOS'!B:G,6,FALSE) -> CHANCHAMIRE, RAFAEL A | P22: =+VLOOKUP(D22,'DISPOSITIVOS ACTIVOS'!$B$1:$H$299,7,FALSE) -> SALES WEST | Q22: =IFERROR(+VLOOKUP(D22,'[1]Migracion feb25 Ver to ATT'!$B:$B,1,FALSE), "NO") -> NO | R22: =+IF(Q22="NO",25,15) -> 25
A23: AT&T | B23: 25 | C23: 3 | D23: 205-527-8021 | E23: JOSE MAITE SA | F23: 55 | G23: 4.11 | H23: 50 | I23: 5 | J23: 4.87 | K23: 2.9 | L23: 66.88 | M23: =+L23 -> 66.88 | N23: =+VLOOKUP(D23,'DISPOSITIVOS ACTIVOS'!B:D,3,FALSE) -> Iphone | O23: =+VLOOKUP(D23,'DISPOSITIVOS ACTIVOS'!B:G,6,FALSE) -> MAITA, JOSE | P23: =+VLOOKUP(D23,'DISPOSITIVOS ACTIVOS'!$B$1:$H$299,7,FALSE) -> SALES SOUTH | Q23: =IFERROR(+VLOOKUP(D23,'[1]Migracion feb25 Ver to ATT'!$B:$B,1,FALSE), "NO") -> NO | R23: =+IF(Q23="NO",25,15) -> 25
A24: AT&T | B24: 25 | C24: 3 | D24: 205-529-6296 | E24: ROSMARY SILVA | F24: 57 | G24: -30.88 | H24: 50 | I24: - | J24: 4.23 | K24: 1.92 | L24: 25.27 | M24: =+L24 -> 25.27 | N24: =+VLOOKUP(D24,'DISPOSITIVOS ACTIVOS'!B:D,3,FALSE) -> Iphone | O24: =+VLOOKUP(D24,'DISPOSITIVOS ACTIVOS'!B:G,6,FALSE) -> SILVA R, ROSMARY JOSE | P24: =+VLOOKUP(D24,'DISPOSITIVOS ACTIVOS'!$B$1:$H$299,7,FALSE) -> SALES SOUTH | Q24: =IFERROR(+VLOOKUP(D24,'[1]Migracion feb25 Ver to ATT'!$B:$B,1,FALSE), "NO") -> 205-529-6296 | R24: =+IF(Q24="NO",25,15) -> 15
A25: AT&T | B25: 25 | C25: 3 | D25: 205-767-8090 | E25: JESUS GUERRERO | F25: 59 | G25: -35 | H25: 50 | I25: - | J25: 4.23 | K25: 1.92 | L25: 21.15 | M25: =+L25 -> 21.15 | N25: =+VLOOKUP(D25,'DISPOSITIVOS ACTIVOS'!B:D,3,FALSE) -> Iphone | O25: =+VLOOKUP(D25,'DISPOSITIVOS ACTIVOS'!B:G,6,FALSE) -> GUERRERO, JESUS | P25: =+VLOOKUP(D25,'DISPOSITIVOS ACTIVOS'!$B$1:$H$299,7,FALSE) -> SALES SOUTH | Q25: =IFERROR(+VLOOKUP(D25,'[1]Migracion feb25 Ver to ATT'!$B:$B,1,FALSE), "NO") -> 205-767-8090 | R25: =+IF(Q25="NO",25,15) -> 15
A26: AT&T | B26: 25 | C26: 3 | D26: 256-724-1530 | E26: DANIEL FLORES SA | F26: 61 | G26: 4.12 | H26: 50 | I26: 10.99 | J26: 4.87 | K26: 2.9 | L26: 72.88 | M26: =+L26 -> 72.88 | N26: =+VLOOKUP(D26,'DISPOSITIVOS ACTIVOS'!B:D,3,FALSE) -> Iphone | O26: =+VLOOKUP(D26,'DISPOSITIVOS ACTIVOS'!B:G,6,FALSE) -> FLORES, JOSE DANIEL | P26: =+VLOOKUP(D26,'DISPOSITIVOS ACTIVOS'!$B$1:$H$299,7,FALSE) -> SALES SOUTH | Q26: =IFERROR(+VLOOKUP(D26,'[1]Migracion feb25 Ver to ATT'!$B:$B,1,FALSE), "NO") -> NO | R26: =+IF(Q26="NO",25,15) -> 25
A27: AT&T | B27: 25 | C27: 3 | D27: 314-309-4058 | E27: YESENIA LOPEZ | F27: 63 | G27: - | H27: 50 | I27: 5 | J27: 4.87 | K27: 2.57 | L27: 62.44 | M27: =+L27 -> 62.44 | N27: =+VLOOKUP(D27,'DISPOSITIVOS ACTIVOS'!B:D,3,FALSE) -> Iphone | O27: =+VLOOKUP(D27,'DISPOSITIVOS ACTIVOS'!B:G,6,FALSE) -> LOPEZ, YESENIA | P27: =+VLOOKUP(D27,'DISPOSITIVOS ACTIVOS'!$B$1:$H$299,7,FALSE) -> SALES WEST | Q27: =IFERROR(+VLOOKUP(D27,'[1]Migracion feb25 Ver to ATT'!$B:$B,1,FALSE), "NO") -> NO | R27: =+IF(Q27="NO",25,15) -> 25
A28: AT&T | B28: 25 | C28: 3 | D28: 314-580-3315 | E28: VICTOR CAICEDO | F28: 65 | G28: -30.88 | H28: 50 | I28: - | J28: 4.23 | K28: 1.92 | L28: 25.27 | M28: =+L28 -> 25.27 | N28: =+VLOOKUP(D28,'DISPOSITIVOS ACTIVOS'!B:D,3,FALSE) -> Iphone | O28: =+VLOOKUP(D28,'DISPOSITIVOS ACTIVOS'!B:G,6,FALSE) -> CAICEDO, VICTOR M | P28: =+VLOOKUP(D28,'DISPOSITIVOS ACTIVOS'!$B$1:$H$299,7,FALSE) -> SALES WEST | Q28: =IFERROR(+VLOOKUP(D28,'[1]Migracion feb25 Ver to ATT'!$B:$B,1,FALSE), "NO") -> 314-580-3315 | R28: =+IF(Q28="NO",25,15) -> 15
A29: AT&T | B29: 25 | C29: 3 | D29: 317-500-7156 | E29: NAYELY SORIANO | F29: 67 | G29: -30.88 | H29: 50 | I29: - | J29: 4.23 | K29: 1.92 | L29: 25.27 | M29: =+L29 -> 25.27 | N29: =+VLOOKUP(D29,'DISPOSITIVOS ACTIVOS'!B:D,3,FALSE) -> Iphone | O29: =+VLOOKUP(D29,'DISPOSITIVOS ACTIVOS'!B:G,6,FALSE) -> SORIANO, NAYELY | P29: =+VLOOKUP(D29,'DISPOSITIVOS ACTIVOS'!$B$1:$H$299,7,FALSE) -> SALES NORTH | Q29: =IFERROR(+VLOOKUP(D29,'[1]Migracion feb25 Ver to ATT'!$B:$B,1,FALSE), "NO") -> 317-500-7156 | R29: =+IF(Q29="NO",25,15) -> 15
A30: AT&T | B30: 25 | C30: 3 | D30: 423-321-4014 | E30: JUAN CARLOS CORADO | F30: 69 | G30: -35 | H30: 50 | I30: - | J30: 4.23 | K30: 1.92 | L30: 21.15 | M30: =+L30 -> 21.15 | N30: =+VLOOKUP(D30,'DISPOSITIVOS ACTIVOS'!B:D,3,FALSE) -> Iphone | O30: =+VLOOKUP(D30,'DISPOSITIVOS ACTIVOS'!B:G,6,FALSE) -> CORADO, JUAN CARLOS | P30: =+VLOOKUP(D30,'DISPOSITIVOS ACTIVOS'!$B$1:$H$299,7,FALSE) -> SALES SOUTH | Q30: =IFERROR(+VLOOKUP(D30,'[1]Migracion feb25 Ver to ATT'!$B:$B,1,FALSE), "NO") -> 423-321-4014 | R30: =+IF(Q30="NO",25,15) -> 15
A31: AT&T | B31: 25 | C31: 3 | D31: 463-209-9259 | E31: EDILIA SSHINE SA | F31: 71 | G31: 4.12 | H31: 50 | I31: - | J31: 4.87 | K31: 2.57 | L31: 61.56 | M31: =+L31 -> 61.56 | N31: =+VLOOKUP(D31,'DISPOSITIVOS ACTIVOS'!B:D,3,FALSE) -> Iphone | O31: =+VLOOKUP(D31,'DISPOSITIVOS ACTIVOS'!B:G,6,FALSE) -> SHINE, EDILIA D | P31: =+VLOOKUP(D31,'DISPOSITIVOS ACTIVOS'!$B$1:$H$299,7,FALSE) -> SALES NORTH | Q31: =IFERROR(+VLOOKUP(D31,'[1]Migracion feb25 Ver to ATT'!$B:$B,1,FALSE), "NO") -> NO | R31: =+IF(Q31="NO",25,15) -> 25
A32: AT&T | B32: 25 | C32: 3 | D32: 463-867-7910 | E32: NEW INDY USER DISTR... | F32: 73 | G32: 4.12 | H32: 50 | I32: 5.99 | J32: 5.02 | K32: 1.78 | L32: 66.91 | M32: =+L32 -> 66.91 | N32: CANCELADO | O32: CANCELADO | P32: =+VLOOKUP(D32,'DISPOSITIVOS ACTIVOS'!$B$1:$H$299,7,FALSE) -> #N/A | Q32: =IFERROR(+VLOOKUP(D32,'[1]Migracion feb25 Ver to ATT'!$B:$B,1,FALSE), "NO") -> NO | R32: =+IF(Q32="NO",25,15) -> 25
A33: AT&T | B33: 25 | C33: 3 | D33: 470-330-9757 | E33: KAREN ORELLANA | F33: 75 | G33: - | H33: 50 | I33: - | J33: 4.87 | K33: 2.57 | L33: 57.44 | M33: =+L33 -> 57.44 | N33: CANCELADO | O33: CANCELADO | P33: =+VLOOKUP(D33,'DISPOSITIVOS ACTIVOS'!$B$1:$H$299,7,FALSE) -> #N/A | Q33: =IFERROR(+VLOOKUP(D33,'[1]Migracion feb25 Ver to ATT'!$B:$B,1,FALSE), "NO") -> NO | R33: =+IF(Q33="NO",25,15) -> 25
A34: AT&T | B34: 25 | C34: 3 | D34: 470-609-0538 | E34: DANIEL GARCIA | F34: 77 | G34: 4.12 | H34: 50 | I34: - | J34: 4.87 | K34: 2.39 | L34: 61.38 | M34: =+L34 -> 61.38 | N34: =+VLOOKUP(D34,'DISPOSITIVOS ACTIVOS'!B:D,3,FALSE) -> no aplica | O34: =+VLOOKUP(D34,'DISPOSITIVOS ACTIVOS'!B:G,6,FALSE) -> DANIEL GARCIA | P34: =+VLOOKUP(D34,'DISPOSITIVOS ACTIVOS'!$B$1:$H$299,7,FALSE) -> ATLANTA | Q34: =IFERROR(+VLOOKUP(D34,'[1]Migracion feb25 Ver to ATT'!$B:$B,1,FALSE), "NO") -> NO | R34: =+IF(Q34="NO",25,15) -> 25
A35: AT&T | B35: 25 | C35: 3 | D35: 470-609-0570 | E35: OSCAR BARRAGAN | F35: 79 | G35: 4.12 | H35: 50 | I35: - | J35: 4.87 | K35: 2.39 | L35: 61.38 | M35: =+L35 -> 61.38 | N35: =+VLOOKUP(D35,'DISPOSITIVOS ACTIVOS'!B:D,3,FALSE) -> no aplica | O35: =+VLOOKUP(D35,'DISPOSITIVOS ACTIVOS'!B:G,6,FALSE) -> OSCAR BARRAGAN | P35: =+VLOOKUP(D35,'DISPOSITIVOS ACTIVOS'!$B$1:$H$299,7,FALSE) -> ATLANTA | Q35: =IFERROR(+VLOOKUP(D35,'[1]Migracion feb25 Ver to ATT'!$B:$B,1,FALSE), "NO") -> NO | R35: =+IF(Q35="NO",25,15) -> 25
A36: AT&T | B36: 25 | C36: 3 | D36: 470-737-8596 | E36: ISRAEL LOPEZ | F36: 81 | G36: - | H36: 50 | I36: - | J36: 4.87 | K36: 2.57 | L36: 57.44 | M36: =+L36 -> 57.44 | N36: CANCELADO | O36: CANCELADO | P36: =+VLOOKUP(D36,'DISPOSITIVOS ACTIVOS'!$B$1:$H$299,7,FALSE) -> #N/A | Q36: =IFERROR(+VLOOKUP(D36,'[1]Migracion feb25 Ver to ATT'!$B:$B,1,FALSE), "NO") -> NO | R36: =+IF(Q36="NO",25,15) -> 25
A37: AT&T | B37: 25 | C37: 3 | D37: 501-773-3738 | E37: SALES ARKANSAS | F37: 83 | G37: 4.11 | H37: 30 | I37: - | J37: 3.75 | K37: - | L37: 37.86 | M37: =+L37 -> 37.86 | N37: =+VLOOKUP(D37,'DISPOSITIVOS ACTIVOS'!B:D,3,FALSE) -> Ipad | O37: =+VLOOKUP(D37,'DISPOSITIVOS ACTIVOS'!B:G,6,FALSE) -> VILLAVICENCIO, ARTURO J | P37: =+VLOOKUP(D37,'DISPOSITIVOS ACTIVOS'!$B$1:$H$299,7,FALSE) -> SALES WEST | Q37: =IFERROR(+VLOOKUP(D37,'[1]Migracion feb25 Ver to ATT'!$B:$B,1,FALSE), "NO") -> NO | R37: =+IF(Q37="NO",25,15) -> 25
A38: AT&T | B38: 25 | C38: 3 | D38: 501-773-3763 | E38: ARTURO VILLAVICENCIO | F38: 85 | G38: -30.89 | H38: 50 | I38: - | J38: 4.23 | K38: 1.92 | L38: 25.26 | M38: =+L38 -> 25.26 | N38: =+VLOOKUP(D38,'DISPOSITIVOS ACTIVOS'!B:D,3,FALSE) -> Iphone | O38: =+VLOOKUP(D38,'DISPOSITIVOS ACTIVOS'!B:G,6,FALSE) -> VILLAVICENCIO, ARTURO J | P38: =+VLOOKUP(D38,'DISPOSITIVOS ACTIVOS'!$B$1:$H$299,7,FALSE) -> SALES WEST | Q38: =IFERROR(+VLOOKUP(D38,'[1]Migracion feb25 Ver to ATT'!$B:$B,1,FALSE), "NO") -> 501-773-3763 | R38: =+IF(Q38="NO",25,15) -> 15
A39: AT&T | B39: 25 | C39: 3 | D39: 502-341-1558 | E39: DILVER GARCIA | F39: 87 | G39: -16.67 | H39: 50 | I39: - | J39: 4.56 | K39: 0.97 | L39: 38.86 | M39: =+L39 -> 38.86 | N39: =+VLOOKUP(D39,'DISPOSITIVOS ACTIVOS'!B:D,3,FALSE) -> 0 | O39: =+VLOOKUP(D39,'DISPOSITIVOS ACTIVOS'!B:G,6,FALSE) -> Backup | P39: =+VLOOKUP(D39,'DISPOSITIVOS ACTIVOS'!$B$1:$H$299,7,FALSE) -> SALES CENTRAL | Q39: =IFERROR(+VLOOKUP(D39,'[1]Migracion feb25 Ver to ATT'!$B:$B,1,FALSE), "NO") -> 502-341-1558 | R39: =+IF(Q39="NO",25,15) -> 15
A40: AT&T | B40: 25 | C40: 3 | D40: 502-558-5770 | E40: JAVIER MOJICA LG | F40: 89 | G40: 12.84 | H40: 25 | I40: - | J40: 5.53 | K40: 3.23 | L40: 46.6 | M40: =+L40 -> 46.6 | N40: =+VLOOKUP(D40,'DISPOSITIVOS ACTIVOS'!B:D,3,FALSE) -> Galaxy | O40: =+VLOOKUP(D40,'DISPOSITIVOS ACTIVOS'!B:G,6,FALSE) -> MOJICA, FRANCISCO JAVIER | P40: =+VLOOKUP(D40,'DISPOSITIVOS ACTIVOS'!$B$1:$H$299,7,FALSE) -> LOGISTICS CENTRAL | Q40: =IFERROR(+VLOOKUP(D40,'[1]Migracion feb25 Ver to ATT'!$B:$B,1,FALSE), "NO") -> 502-558-5770 | R40: =+IF(Q40="NO",25,15) -> 15
A41: AT&T | B41: 25 | C41: 3 | D41: 502-974-3915 | E41: CLAUDIA ARMES | F41: 91 | G41: -35 | H41: 50 | I41: - | J41: 4.23 | K41: 1.92 | L41: 21.15 | M41: =+L41 -> 21.15 | N41: =+VLOOKUP(D41,'DISPOSITIVOS ACTIVOS'!B:D,3,FALSE) -> Iphone | O41: =+VLOOKUP(D41,'DISPOSITIVOS ACTIVOS'!B:G,6,FALSE) -> ARMES, CLAUDIA | P41: =+VLOOKUP(D41,'DISPOSITIVOS ACTIVOS'!$B$1:$H$299,7,FALSE) -> SALES NORTH | Q41: =IFERROR(+VLOOKUP(D41,'[1]Migracion feb25 Ver to ATT'!$B:$B,1,FALSE), "NO") -> 502-974-3915 | R41: =+IF(Q41="NO",25,15) -> 15
A42: AT&T | B42: 25 | C42: 3 | D42: 513-675-0865 | E42: IRIS CORDERO | F42: 93 | G42: -30.89 | H42: 50 | I42: - | J42: 4.23 | K42: 1.92 | L42: 25.26 | M42: =+L42 -> 25.26 | N42: =+VLOOKUP(D42,'DISPOSITIVOS ACTIVOS'!B:D,3,FALSE) -> Iphone | O42: =+VLOOKUP(D42,'DISPOSITIVOS ACTIVOS'!B:G,6,FALSE) -> CORDERO, IRIS | P42: =+VLOOKUP(D42,'DISPOSITIVOS ACTIVOS'!$B$1:$H$299,7,FALSE) -> SALES NORTH | Q42: =IFERROR(+VLOOKUP(D42,'[1]Migracion feb25 Ver to ATT'!$B:$B,1,FALSE), "NO") -> 513-675-0865 | R42: =+IF(Q42="NO",25,15) -> 15
A43: AT&T | B43: 25 | C43: 3 | D43: 513-720-1147 | E43: CINCINNATI LIMENA | F43: 95 | G43: 4.11 | H43: 50 | I43: 5 | J43: 5 | K43: 1.29 | L43: 65.4 | M43: =+L43 -> 65.4 | N43: =+VLOOKUP(D43,'DISPOSITIVOS ACTIVOS'!B:D,3,FALSE) -> Iphone | O43: =+VLOOKUP(D43,'DISPOSITIVOS ACTIVOS'!B:G,6,FALSE) -> ALVAREZ PALOMARES M, PAULA MAYREN | P43: =+VLOOKUP(D43,'DISPOSITIVOS ACTIVOS'!$B$1:$H$299,7,FALSE) -> MERCHANDISER NORTH | Q43: =IFERROR(+VLOOKUP(D43,'[1]Migracion feb25 Ver to ATT'!$B:$B,1,FALSE), "NO") -> NO | R43: =+IF(Q43="NO",25,15) -> 25
A44: AT&T | B44: 25 | C44: 3 | D44: 601-910-8492 | E44: ROSMARY LACRUZ | F44: 97 | G44: -35 | H44: 50 | I44: - | J44: 4.23 | K44: 1.92 | L44: 21.15 | M44: =+L44 -> 21.15 | N44: =+VLOOKUP(D44,'DISPOSITIVOS ACTIVOS'!B:D,3,FALSE) -> Iphone | O44: =+VLOOKUP(D44,'DISPOSITIVOS ACTIVOS'!B:G,6,FALSE) -> LACRUZ, ROSMARY | P44: =+VLOOKUP(D44,'DISPOSITIVOS ACTIVOS'!$B$1:$H$299,7,FALSE) -> SALES WEST | Q44: =IFERROR(+VLOOKUP(D44,'[1]Migracion feb25 Ver to ATT'!$B:$B,1,FALSE), "NO") -> 601-910-8492 | R44: =+IF(Q44="NO",25,15) -> 15
A45: AT&T | B45: 25 | C45: 3 | D45: 615-207-2464 | E45: OSMAN CABRERA | F45: 99 | G45: -30.89 | H45: 50 | I45: - | J45: 4.23 | K45: 1.92 | L45: 25.26 | M45: =+L45 -> 25.26 | N45: =+VLOOKUP(D45,'DISPOSITIVOS ACTIVOS'!B:D,3,FALSE) -> Iphone | O45: =+VLOOKUP(D45,'DISPOSITIVOS ACTIVOS'!B:G,6,FALSE) -> CABRERA, OSMAN A | P45: =+VLOOKUP(D45,'DISPOSITIVOS ACTIVOS'!$B$1:$H$299,7,FALSE) -> SALES CENTRAL | Q45: =IFERROR(+VLOOKUP(D45,'[1]Migracion feb25 Ver to ATT'!$B:$B,1,FALSE), "NO") -> 615-207-2464 | R45: =+IF(Q45="NO",25,15) -> 15
A46: AT&T | B46: 25 | C46: 3 | D46: 615-299-3640 | E46: SIMON CASTELLANO | F46: 101 | G46: 12.84 | H46: 25 | I46: - | J46: 4.71 | K46: 5.49 | L46: 48.04 | M46: =+L46 -> 48.04 | N46: =+VLOOKUP(D46,'DISPOSITIVOS ACTIVOS'!B:D,3,FALSE) -> Galaxy | O46: =+VLOOKUP(D46,'DISPOSITIVOS ACTIVOS'!B:G,6,FALSE) -> DE LOS SANTOS, LUIS | P46: =+VLOOKUP(D46,'DISPOSITIVOS ACTIVOS'!$B$1:$H$299,7,FALSE) -> LOGISTIC SOUTH | Q46: =IFERROR(+VLOOKUP(D46,'[1]Migracion feb25 Ver to ATT'!$B:$B,1,FALSE), "NO") -> 615-299-3640 | R46: =+IF(Q46="NO",25,15) -> 15
A47: AT&T | B47: 25 | C47: 3 | D47: 615-299-3641 | E47: EDGAR FERNANDEZ LQ | F47: 103 | G47: 4.11 | H47: 50 | I47: -0.99 | J47: 4.87 | K47: 2.57 | L47: 60.56 | M47: =+L47 -> 60.56 | N47: =+VLOOKUP(D47,'DISPOSITIVOS ACTIVOS'!B:D,3,FALSE) -> Motorola | O47: =+VLOOKUP(D47,'DISPOSITIVOS ACTIVOS'!B:G,6,FALSE) -> FERNANDEZ, EDGAR | P47: =+VLOOKUP(D47,'DISPOSITIVOS ACTIVOS'!$B$1:$H$299,7,FALSE) -> LOGISTICS CENTRAL | Q47: =IFERROR(+VLOOKUP(D47,'[1]Migracion feb25 Ver to ATT'!$B:$B,1,FALSE), "NO") -> NO | R47: =+IF(Q47="NO",25,15) -> 25
A48: AT&T | B48: 25 | C48: 3 | D48: 615-305-1999 | E48: IPAD SALES | F48: 105 | G48: - | H48: 30 | I48: - | J48: 3.75 | K48: - | L48: 33.75 | M48: =+L48 -> 33.75 | N48: Ipad | O48: =+VLOOKUP(D48,'DISPOSITIVOS ACTIVOS'!B:G,6,FALSE) -> #N/A | P48: =+VLOOKUP(D48,'DISPOSITIVOS ACTIVOS'!$B$1:$H$299,7,FALSE) -> #N/A | Q48: =IFERROR(+VLOOKUP(D48,'[1]Migracion feb25 Ver to ATT'!$B:$B,1,FALSE), "NO") -> NO | R48: =+IF(Q48="NO",25,15) -> 25
A49: AT&T | B49: 25 | C49: 3 | D49: 615-310-9970 | E49: ALBERT CARDOZO | F49: 107 | G49: - | H49: 15 | I49: - | J49: 3.75 | K49: - | L49: 18.75 | M49: =+L49 -> 18.75 | N49: =+VLOOKUP(D49,'DISPOSITIVOS ACTIVOS'!B:D,3,FALSE) -> Ipad | O49: =+VLOOKUP(D49,'DISPOSITIVOS ACTIVOS'!B:G,6,FALSE) -> CARDOZO, ALBERT YVAN | P49: =+VLOOKUP(D49,'DISPOSITIVOS ACTIVOS'!$B$1:$H$299,7,FALSE) -> SALES RITEFILL DSD CENTRAL | Q49: =IFERROR(+VLOOKUP(D49,'[1]Migracion feb25 Ver to ATT'!$B:$B,1,FALSE), "NO") -> 615-310-9970 | R49: =+IF(Q49="NO",25,15) -> 15
A50: AT&T | B50: 25 | C50: 3 | D50: 615-316-8577 | E50: HR LIMENA | F50: 109 | G50: - | H50: 50 | I50: 25 | J50: 4.87 | K50: 2.57 | L50: 82.44 | M50: =+L50 -> 82.44 | N50: =+VLOOKUP(D50,'DISPOSITIVOS ACTIVOS'!B:D,3,FALSE) -> Iphone | O50: =+VLOOKUP(D50,'DISPOSITIVOS ACTIVOS'!B:G,6,FALSE) -> DUQUE IYENGAR, DANIELA | P50: =+VLOOKUP(D50,'DISPOSITIVOS ACTIVOS'!$B$1:$H$299,7,FALSE) -> HR | Q50: =IFERROR(+VLOOKUP(D50,'[1]Migracion feb25 Ver to ATT'!$B:$B,1,FALSE), "NO") -> NO | R50: =+IF(Q50="NO",25,15) -> 25
A51: AT&T | B51: 25 | C51: 3 | D51: 615-337-4949 | E51: DAVID CONDE WH | F51: 111 | G51: - | H51: 50 | I51: - | J51: 4.87 | K51: 2.57 | L51: 57.44 | M51: =+L51 -> 57.44 | N51: =+VLOOKUP(D51,'DISPOSITIVOS ACTIVOS'!B:D,3,FALSE) -> Galaxy | O51: =+VLOOKUP(D51,'DISPOSITIVOS ACTIVOS'!B:G,6,FALSE) -> CONDE TORRES, DAVID A | P51: =+VLOOKUP(D51,'DISPOSITIVOS ACTIVOS'!$B$1:$H$299,7,FALSE) -> WAREHOUSE CENTRAL | Q51: =IFERROR(+VLOOKUP(D51,'[1]Migracion feb25 Ver to ATT'!$B:$B,1,FALSE), "NO") -> NO | R51: =+IF(Q51="NO",25,15) -> 25
A52: AT&T | B52: 25 | C52: 3 | D52: 615-390-4624 | E52: HENRY ESQUIVEL | F52: 113 | G52: -35 | H52: 50 | I52: - | J52: 4.23 | K52: 1.92 | L52: 21.15 | M52: =+L52 -> 21.15 | N52: =+VLOOKUP(D52,'DISPOSITIVOS ACTIVOS'!B:D,3,FALSE) -> Iphone | O52: =+VLOOKUP(D52,'DISPOSITIVOS ACTIVOS'!B:G,6,FALSE) -> ESQUIVEL, HENRY | P52: =+VLOOKUP(D52,'DISPOSITIVOS ACTIVOS'!$B$1:$H$299,7,FALSE) -> WAREHOUSE CENTRAL | Q52: =IFERROR(+VLOOKUP(D52,'[1]Migracion feb25 Ver to ATT'!$B:$B,1,FALSE), "NO") -> 615-390-4624 | R52: =+IF(Q52="NO",25,15) -> 15
A53: AT&T | B53: 25 | C53: 3 | D53: 615-403-8760 | E53: MERARI VILLATORO | F53: 115 | G53: 600.93 | H53: 50 | I53: 38.89 | J53: 9.86 | K53: 5.27 | L53: 704.95 | M53: =+L53 -> 704.95 | N53: =+VLOOKUP(D53,'DISPOSITIVOS ACTIVOS'!B:D,3,FALSE) -> Iphone | O53: =+VLOOKUP(D53,'DISPOSITIVOS ACTIVOS'!B:G,6,FALSE) -> VILLATORO, MERARI | P53: =+VLOOKUP(D53,'DISPOSITIVOS ACTIVOS'!$B$1:$H$299,7,FALSE) -> VP | Q53: =IFERROR(+VLOOKUP(D53,'[1]Migracion feb25 Ver to ATT'!$B:$B,1,FALSE), "NO") -> NO | R53: =+IF(Q53="NO",25,15) -> 25
A54: AT&T | B54: 25 | C54: 3 | D54: 615-417-0015 | E54: JESSICA BARAJAS LA | F54: 117 | G54: - | H54: 50 | I54: - | J54: 4.87 | K54: 2.57 | L54: 57.44 | M54: =+L54 -> 57.44 | N54: =+VLOOKUP(D54,'DISPOSITIVOS ACTIVOS'!B:D,3,FALSE) -> Iphone | O54: =+VLOOKUP(D54,'DISPOSITIVOS ACTIVOS'!B:G,6,FALSE) -> BARAJAS, JESSICA | P54: =+VLOOKUP(D54,'DISPOSITIVOS ACTIVOS'!$B$1:$H$299,7,FALSE) -> SALES NORTH | Q54: =IFERROR(+VLOOKUP(D54,'[1]Migracion feb25 Ver to ATT'!$B:$B,1,FALSE), "NO") -> NO | R54: =+IF(Q54="NO",25,15) -> 25
A55: AT&T | B55: 25 | C55: 3 | D55: 615-417-9594 | E55: NICOLAS FINANZAS | F55: 119 | G55: - | H55: 50 | I55: - | J55: 4.87 | K55: 2.57 | L55: 57.44 | M55: =+L55 -> 57.44 | N55: =+VLOOKUP(D55,'DISPOSITIVOS ACTIVOS'!B:D,3,FALSE) -> Iphone | O55: =+VLOOKUP(D55,'DISPOSITIVOS ACTIVOS'!B:G,6,FALSE) -> QUIJANO, NICOLAS | P55: =+VLOOKUP(D55,'DISPOSITIVOS ACTIVOS'!$B$1:$H$299,7,FALSE) -> CFO | Q55: =IFERROR(+VLOOKUP(D55,'[1]Migracion feb25 Ver to ATT'!$B:$B,1,FALSE), "NO") -> NO | R55: =+IF(Q55="NO",25,15) -> 25
A56: AT&T | B56: 25 | C56: 3 | D56: 615-426-4622 | E56: ZEDRICK PATINO | F56: 121 | G56: - | H56: 50 | I56: - | J56: 4.87 | K56: 2.57 | L56: 57.44 | M56: =+L56 -> 57.44 | N56: =+VLOOKUP(D56,'DISPOSITIVOS ACTIVOS'!B:D,3,FALSE) -> Iphone | O56: =+VLOOKUP(D56,'DISPOSITIVOS ACTIVOS'!B:G,6,FALSE) -> PATINO, ZEDERICK | P56: =+VLOOKUP(D56,'DISPOSITIVOS ACTIVOS'!$B$1:$H$299,7,FALSE) -> MERCHANDISER CENTRAL | Q56: =IFERROR(+VLOOKUP(D56,'[1]Migracion feb25 Ver to ATT'!$B:$B,1,FALSE), "NO") -> NO | R56: =+IF(Q56="NO",25,15) -> 25
A57: AT&T | B57: 25 | C57: 3 | D57: 615-456-2536 | E57: DANNY CABANZO | F57: 123 | G57: -30.88 | H57: 50 | I57: - | J57: 4.23 | K57: 1.92 | L57: 25.27 | M57: =+L57 -> 25.27 | N57: =+VLOOKUP(D57,'DISPOSITIVOS ACTIVOS'!B:D,3,FALSE) -> Iphone | O57: =+VLOOKUP(D57,'DISPOSITIVOS ACTIVOS'!B:G,6,FALSE) -> CABANZO, DANNY | P57: =+VLOOKUP(D57,'DISPOSITIVOS ACTIVOS'!$B$1:$H$299,7,FALSE) -> SALES CENTRAL | Q57: =IFERROR(+VLOOKUP(D57,'[1]Migracion feb25 Ver to ATT'!$B:$B,1,FALSE), "NO") -> 615-456-2536 | R57: =+IF(Q57="NO",25,15) -> 15
A58: AT&T | B58: 25 | C58: 3 | D58: 615-476-5992 | E58: MONICA AYALA | F58: 125 | G58: - | H58: 50 | I58: - | J58: 4.87 | K58: 2.57 | L58: 57.44 | M58: =+L58 -> 57.44 | N58: CANCELADO | O58: CANCELADO | P58: =+VLOOKUP(D58,'DISPOSITIVOS ACTIVOS'!$B$1:$H$299,7,FALSE) -> #N/A | Q58: =IFERROR(+VLOOKUP(D58,'[1]Migracion feb25 Ver to ATT'!$B:$B,1,FALSE), "NO") -> NO | R58: =+IF(Q58="NO",25,15) -> 25
A59: AT&T | B59: 25 | C59: 3 | D59: 615-477-6490 | E59: MERARI TWOLINE | F59: 127 | G59: - | H59: 50 | I59: 30.56 | J59: 4.87 | K59: 2.57 | L59: 88 | M59: =+L59 -> 88 | N59: =+VLOOKUP(D59,'DISPOSITIVOS ACTIVOS'!B:D,3,FALSE) -> Iphone | O59: =+VLOOKUP(D59,'DISPOSITIVOS ACTIVOS'!B:G,6,FALSE) -> VILLATORO, MERARI | P59: =+VLOOKUP(D59,'DISPOSITIVOS ACTIVOS'!$B$1:$H$299,7,FALSE) -> VP | Q59: =IFERROR(+VLOOKUP(D59,'[1]Migracion feb25 Ver to ATT'!$B:$B,1,FALSE), "NO") -> NO | R59: =+IF(Q59="NO",25,15) -> 25
A60: AT&T | B60: 25 | C60: 3 | D60: 615-496-8278 | E60: JOHAN MADRIZ | F60: 129 | G60: 307.5 | H60: 50 | I60: 38.89 | J60: 14.22 | K60: 6.17 | L60: 416.78 | M60: =+L60 -> 416.78 | N60: =+VLOOKUP(D60,'DISPOSITIVOS ACTIVOS'!B:D,3,FALSE) -> Iphone | O60: =+VLOOKUP(D60,'DISPOSITIVOS ACTIVOS'!B:G,6,FALSE) -> MADRIZ, JOHAN | P60: =+VLOOKUP(D60,'DISPOSITIVOS ACTIVOS'!$B$1:$H$299,7,FALSE) -> President | Q60: =IFERROR(+VLOOKUP(D60,'[1]Migracion feb25 Ver to ATT'!$B:$B,1,FALSE), "NO") -> NO | R60: =+IF(Q60="NO",25,15) -> 25
A61: AT&T | B61: 25 | C61: 3 | D61: 615-586-0725 | E61: YESENIA LOPEZ SA | F61: 131 | G61: - | H61: 30 | I61: - | J61: 3.75 | K61: - | L61: 33.75 | M61: =+L61 -> 33.75 | N61: =+VLOOKUP(D61,'DISPOSITIVOS ACTIVOS'!B:D,3,FALSE) -> Ipad | O61: =+VLOOKUP(D61,'DISPOSITIVOS ACTIVOS'!B:G,6,FALSE) -> LOPEZ, YESENIA | P61: =+VLOOKUP(D61,'DISPOSITIVOS ACTIVOS'!$B$1:$H$299,7,FALSE) -> SALES WEST | Q61: =IFERROR(+VLOOKUP(D61,'[1]Migracion feb25 Ver to ATT'!$B:$B,1,FALSE), "NO") -> NO | R61: =+IF(Q61="NO",25,15) -> 25
A62: AT&T | B62: 25 | C62: 3 | D62: 615-586-4787 | E62: JOSE MAITA IPAD | F62: 133 | G62: - | H62: 30 | I62: - | J62: 3.75 | K62: - | L62: 33.75 | M62: =+L62 -> 33.75 | N62: =+VLOOKUP(D62,'DISPOSITIVOS ACTIVOS'!B:D,3,FALSE) -> Ipad | O62: =+VLOOKUP(D62,'DISPOSITIVOS ACTIVOS'!B:G,6,FALSE) -> MAITA, JOSE | P62: =+VLOOKUP(D62,'DISPOSITIVOS ACTIVOS'!$B$1:$H$299,7,FALSE) -> SALES SOUTH | Q62: =IFERROR(+VLOOKUP(D62,'[1]Migracion feb25 Ver to ATT'!$B:$B,1,FALSE), "NO") -> NO | R62: =+IF(Q62="NO",25,15) -> 25
A63: AT&T | B63: 25 | C63: 3 | D63: 615-589-2741 | E63: ROSMARY SILVA IPAD | F63: 135 | G63: - | H63: 30 | I63: - | J63: 3.75 | K63: - | L63: 33.75 | M63: =+L63 -> 33.75 | N63: =+VLOOKUP(D63,'DISPOSITIVOS ACTIVOS'!B:D,3,FALSE) -> Ipad | O63: =+VLOOKUP(D63,'DISPOSITIVOS ACTIVOS'!B:G,6,FALSE) -> SILVA R, ROSMARY JOSE | P63: =+VLOOKUP(D63,'DISPOSITIVOS ACTIVOS'!$B$1:$H$299,7,FALSE) -> SALES SOUTH | Q63: =IFERROR(+VLOOKUP(D63,'[1]Migracion feb25 Ver to ATT'!$B:$B,1,FALSE), "NO") -> NO | R63: =+IF(Q63="NO",25,15) -> 25
A64: AT&T | B64: 25 | C64: 3 | D64: 615-589-4199 | E64: ELIZABETH PELAEZ | F64: 137 | G64: - | H64: 50 | I64: 10.99 | J64: 4.87 | K64: 2.57 | L64: 68.43 | M64: =+L64 -> 68.43 | N64: =+VLOOKUP(D64,'DISPOSITIVOS ACTIVOS'!B:D,3,FALSE) -> Iphone | O64: =+VLOOKUP(D64,'DISPOSITIVOS ACTIVOS'!B:G,6,FALSE) -> PELAEZ, ELIZABETH | P64: =+VLOOKUP(D64,'DISPOSITIVOS ACTIVOS'!$B$1:$H$299,7,FALSE) -> SALES CENTRAL | Q64: =IFERROR(+VLOOKUP(D64,'[1]Migracion feb25 Ver to ATT'!$B:$B,1,FALSE), "NO") -> NO | R64: =+IF(Q64="NO",25,15) -> 25
A65: AT&T | B65: 25 | C65: 3 | D65: 615-626-2116 | E65: DILVER GARCIA | F65: 139 | G65: -35 | H65: 50 | I65: - | J65: 4.23 | K65: 1.92 | L65: 21.15 | M65: =+L65 -> 21.15 | N65: =+VLOOKUP(D65,'DISPOSITIVOS ACTIVOS'!B:D,3,FALSE) -> Iphone | O65: =+VLOOKUP(D65,'DISPOSITIVOS ACTIVOS'!B:G,6,FALSE) -> SUAREZ LEZCANO, FERNANDO M | P65: =+VLOOKUP(D65,'DISPOSITIVOS ACTIVOS'!$B$1:$H$299,7,FALSE) -> SALES RITEFILL DSD CENTRAL | Q65: =IFERROR(+VLOOKUP(D65,'[1]Migracion feb25 Ver to ATT'!$B:$B,1,FALSE), "NO") -> 615-626-2116 | R65: =+IF(Q65="NO",25,15) -> 15
A66: AT&T | B66: 25 | C66: 3 | D66: 615-626-2756 | E66: LIZET NAJERA | F66: 141 | G66: -35 | H66: 50 | I66: - | J66: 4.23 | K66: 1.92 | L66: 21.15 | M66: =+L66 -> 21.15 | N66: =+VLOOKUP(D66,'DISPOSITIVOS ACTIVOS'!B:D,3,FALSE) -> Iphone | O66: =+VLOOKUP(D66,'DISPOSITIVOS ACTIVOS'!B:G,6,FALSE) -> NAJERA, LIZET | P66: =+VLOOKUP(D66,'DISPOSITIVOS ACTIVOS'!$B$1:$H$299,7,FALSE) -> SALES NORTH | Q66: =IFERROR(+VLOOKUP(D66,'[1]Migracion feb25 Ver to ATT'!$B:$B,1,FALSE), "NO") -> 615-626-2756 | R66: =+IF(Q66="NO",25,15) -> 15
A67: AT&T | B67: 25 | C67: 3 | D67: 615-626-3208 | E67: ALEJANDRA LOPEZ | F67: 143 | G67: -35 | H67: 50 | I67: - | J67: 4.23 | K67: 1.92 | L67: 21.15 | M67: =+L67 -> 21.15 | N67: =+VLOOKUP(D67,'DISPOSITIVOS ACTIVOS'!B:D,3,FALSE) -> Iphone | O67: =+VLOOKUP(D67,'DISPOSITIVOS ACTIVOS'!B:G,6,FALSE) -> LOPEZ, ALEJANDRA C | P67: =+VLOOKUP(D67,'DISPOSITIVOS ACTIVOS'!$B$1:$H$299,7,FALSE) -> SALES WEST | Q67: =IFERROR(+VLOOKUP(D67,'[1]Migracion feb25 Ver to ATT'!$B:$B,1,FALSE), "NO") -> 615-626-3208 | R67: =+IF(Q67="NO",25,15) -> 15
A68: AT&T | B68: 25 | C68: 3 | D68: 615-626-3219 | E68: ZULLYMAR TOVAR | F68: 145 | G68: -35 | H68: 50 | I68: - | J68: 4.23 | K68: 1.92 | L68: 21.15 | M68: =+L68 -> 21.15 | N68: =+VLOOKUP(D68,'DISPOSITIVOS ACTIVOS'!B:D,3,FALSE) -> 0 | O68: =+VLOOKUP(D68,'DISPOSITIVOS ACTIVOS'!B:G,6,FALSE) -> TOVAR, ZULLYMAR | P68: =+VLOOKUP(D68,'DISPOSITIVOS ACTIVOS'!$B$1:$H$299,7,FALSE) -> SALES CENTRAL | Q68: =IFERROR(+VLOOKUP(D68,'[1]Migracion feb25 Ver to ATT'!$B:$B,1,FALSE), "NO") -> 615-626-3219 | R68: =+IF(Q68="NO",25,15) -> 15
A69: AT&T | B69: 25 | C69: 3 | D69: 615-626-4243 | E69: JOSE HERRERA | F69: 147 | G69: - | H69: 50 | I69: 23.61 | J69: 4.87 | K69: 2.57 | L69: 81.05 | M69: =+L69 -> 81.05 | N69: =+VLOOKUP(D69,'DISPOSITIVOS ACTIVOS'!B:D,3,FALSE) -> Iphone | O69: =+VLOOKUP(D69,'DISPOSITIVOS ACTIVOS'!B:G,6,FALSE) -> HERRERA MOLINA, JOSE CARLOS | P69: =+VLOOKUP(D69,'DISPOSITIVOS ACTIVOS'!$B$1:$H$299,7,FALSE) -> CEO | Q69: =IFERROR(+VLOOKUP(D69,'[1]Migracion feb25 Ver to ATT'!$B:$B,1,FALSE), "NO") -> NO | R69: =+IF(Q69="NO",25,15) -> 25
A70: AT&T | B70: 25 | C70: 3 | D70: 615-674-8479 | E70: JORGE PRADO | F70: 149 | G70: - | H70: 60 | I70: 25 | J70: 4.99 | K70: 7.68 | L70: 97.67 | M70: =+L70 -> 97.67 | N70: =+VLOOKUP(D70,'DISPOSITIVOS ACTIVOS'!B:D,3,FALSE) -> Iphone | O70: =+VLOOKUP(D70,'DISPOSITIVOS ACTIVOS'!B:G,6,FALSE) -> PRADO, JORGE A | P70: =+VLOOKUP(D70,'DISPOSITIVOS ACTIVOS'!$B$1:$H$299,7,FALSE) -> COO | Q70: =IFERROR(+VLOOKUP(D70,'[1]Migracion feb25 Ver to ATT'!$B:$B,1,FALSE), "NO") -> NO | R70: =+IF(Q70="NO",25,15) -> 25
A71: AT&T | B71: 25 | C71: 3 | D71: 615-691-3166 | E71: WAREHOUSE TN NASHVILLE | F71: 151 | G71: -6.75 | H71: 50 | I71: - | J71: 4.87 | K71: 2.57 | L71: 50.69 | M71: =+L71 -> 50.69 | N71: =+VLOOKUP(D71,'DISPOSITIVOS ACTIVOS'!B:D,3,FALSE) -> Iphone | O71: =+VLOOKUP(D71,'DISPOSITIVOS ACTIVOS'!B:G,6,FALSE) -> QUIJANO, NICOLAS | P71: =+VLOOKUP(D71,'DISPOSITIVOS ACTIVOS'!$B$1:$H$299,7,FALSE) -> CFO | Q71: =IFERROR(+VLOOKUP(D71,'[1]Migracion feb25 Ver to ATT'!$B:$B,1,FALSE), "NO") -> NO | R71: =+IF(Q71="NO",25,15) -> 25
A72: AT&T | B72: 25 | C72: 3 | D72: 615-708-0397 | E72: JOHAN TWOLINE | F72: 153 | G72: -19.45 | H72: 50 | I72: 33.34 | J72: 4.87 | K72: 2.57 | L72: 71.33 | M72: =+L72 -> 71.33 | N72: =+VLOOKUP(D72,'DISPOSITIVOS ACTIVOS'!B:D,3,FALSE) -> Iphone | O72: =+VLOOKUP(D72,'DISPOSITIVOS ACTIVOS'!B:G,6,FALSE) -> MADRIZ, JOHAN | P72: =+VLOOKUP(D72,'DISPOSITIVOS ACTIVOS'!$B$1:$H$299,7,FALSE) -> President | Q72: =IFERROR(+VLOOKUP(D72,'[1]Migracion feb25 Ver to ATT'!$B:$B,1,FALSE), "NO") -> NO | R72: =+IF(Q72="NO",25,15) -> 25
A73: AT&T | B73: 25 | C73: 3 | D73: 615-730-3104 | E73: IVAN TELLO SA | F73: 155 | G73: - | H73: 50 | I73: 5 | J73: 4.87 | K73: 2.57 | L73: 62.44 | M73: =+L73 -> 62.44 | N73: =+VLOOKUP(D73,'DISPOSITIVOS ACTIVOS'!B:D,3,FALSE) -> Iphone | O73: =+VLOOKUP(D73,'DISPOSITIVOS ACTIVOS'!B:G,6,FALSE) -> TELLO, IVAN E | P73: =+VLOOKUP(D73,'DISPOSITIVOS ACTIVOS'!$B$1:$H$299,7,FALSE) -> SALES CENTRAL | Q73: =IFERROR(+VLOOKUP(D73,'[1]Migracion feb25 Ver to ATT'!$B:$B,1,FALSE), "NO") -> NO | R73: =+IF(Q73="NO",25,15) -> 25
A74: AT&T | B74: 25 | C74: 3 | D74: 615-768-6114 | E74: IPAD BYOD | F74: 157 | G74: 7 | H74: 15 | I74: - | J74: 3.75 | K74: - | L74: 25.75 | M74: =+L74 -> 25.75 | N74: =+VLOOKUP(D74,'DISPOSITIVOS ACTIVOS'!B:D,3,FALSE) -> Ipad | O74: =+VLOOKUP(D74,'DISPOSITIVOS ACTIVOS'!B:G,6,FALSE) -> SILVA, ELISA | P74: =+VLOOKUP(D74,'DISPOSITIVOS ACTIVOS'!$B$1:$H$299,7,FALSE) -> SALES WEST | Q74: =IFERROR(+VLOOKUP(D74,'[1]Migracion feb25 Ver to ATT'!$B:$B,1,FALSE), "NO") -> NO | R74: =+IF(Q74="NO",25,15) -> 25
A75: AT&T | B75: 25 | C75: 3 | D75: 615-795-8193 | E75: ANDRES FUENMAYOR | F75: 159 | G75: -16.67 | H75: 50 | I75: - | J75: 4.23 | K75: 1.92 | L75: 39.48 | M75: =+L75 -> 39.48 | N75: =+VLOOKUP(D75,'DISPOSITIVOS ACTIVOS'!B:D,3,FALSE) -> Galaxy | O75: =+VLOOKUP(D75,'DISPOSITIVOS ACTIVOS'!B:G,6,FALSE) -> REMBERT, ANTORIUS DAVUN | P75: =+VLOOKUP(D75,'DISPOSITIVOS ACTIVOS'!$B$1:$H$299,7,FALSE) -> LOGISTICS SOUTH | Q75: =IFERROR(+VLOOKUP(D75,'[1]Migracion feb25 Ver to ATT'!$B:$B,1,FALSE), "NO") -> 615-795-8193 | R75: =+IF(Q75="NO",25,15) -> 15
A76: AT&T | B76: 25 | C76: 3 | D76: 615-795-8195 | E76: MERVIN FERERR | F76: 161 | G76: -16.67 | H76: 50 | I76: - | J76: 4.23 | K76: 1.92 | L76: 39.48 | M76: =+L76 -> 39.48 | N76: =+VLOOKUP(D76,'DISPOSITIVOS ACTIVOS'!B:D,3,FALSE) -> Galaxy | O76: =+VLOOKUP(D76,'DISPOSITIVOS ACTIVOS'!B:G,6,FALSE) -> FERRER BRACHO, MERVIN J | P76: =+VLOOKUP(D76,'DISPOSITIVOS ACTIVOS'!$B$1:$H$299,7,FALSE) -> LOGISTICS CENTRAL | Q76: =IFERROR(+VLOOKUP(D76,'[1]Migracion feb25 Ver to ATT'!$B:$B,1,FALSE), "NO") -> 615-795-8195 | R76: =+IF(Q76="NO",25,15) -> 15
A77: AT&T | B77: 25 | C77: 3 | D77: 615-804-0516 | E77: YULIN REYES | F77: 163 | G77: -35 | H77: 50 | I77: - | J77: 4.23 | K77: 1.92 | L77: 21.15 | M77: =+L77 -> 21.15 | N77: =+VLOOKUP(D77,'DISPOSITIVOS ACTIVOS'!B:D,3,FALSE) -> Iphone | O77: =+VLOOKUP(D77,'DISPOSITIVOS ACTIVOS'!B:G,6,FALSE) -> REYES, YULIN | P77: =+VLOOKUP(D77,'DISPOSITIVOS ACTIVOS'!$B$1:$H$299,7,FALSE) -> SALES CENTRAL | Q77: =IFERROR(+VLOOKUP(D77,'[1]Migracion feb25 Ver to ATT'!$B:$B,1,FALSE), "NO") -> 615-804-0516 | R77: =+IF(Q77="NO",25,15) -> 15
A78: AT&T | B78: 25 | C78: 3 | D78: 615-812-5934 | E78: ELISA SILVA | F78: 165 | G78: - | H78: 50 | I78: - | J78: 4.87 | K78: 2.57 | L78: 57.44 | M78: =+L78 -> 57.44 | N78: =+VLOOKUP(D78,'DISPOSITIVOS ACTIVOS'!B:D,3,FALSE) -> Iphone | O78: =+VLOOKUP(D78,'DISPOSITIVOS ACTIVOS'!B:G,6,FALSE) -> QUEVEDO, NAIROVI Y | P78: =+VLOOKUP(D78,'DISPOSITIVOS ACTIVOS'!$B$1:$H$299,7,FALSE) -> SALES WEST | Q78: =IFERROR(+VLOOKUP(D78,'[1]Migracion feb25 Ver to ATT'!$B:$B,1,FALSE), "NO") -> NO | R78: =+IF(Q78="NO",25,15) -> 25
A79: AT&T | B79: 25 | C79: 3 | D79: 615-828-8926 | E79: LEONARDO PALENCIA SA | F79: 167 | G79: - | H79: 50 | I79: 5 | J79: 4.87 | K79: 2.57 | L79: 62.44 | M79: =+L79 -> 62.44 | N79: =+VLOOKUP(D79,'DISPOSITIVOS ACTIVOS'!B:D,3,FALSE) -> Iphone | O79: =+VLOOKUP(D79,'DISPOSITIVOS ACTIVOS'!B:G,6,FALSE) -> PALENCIA RODRIGUEZ, LEONARDO R | P79: =+VLOOKUP(D79,'DISPOSITIVOS ACTIVOS'!$B$1:$H$299,7,FALSE) -> SALES CENTRAL | Q79: =IFERROR(+VLOOKUP(D79,'[1]Migracion feb25 Ver to ATT'!$B:$B,1,FALSE), "NO") -> NO | R79: =+IF(Q79="NO",25,15) -> 25
A80: AT&T | B80: 25 | C80: 3 | D80: 615-830-4944 | E80: YULIER PEREZ | F80: 169 | G80: -16.67 | H80: 50 | I80: - | J80: 4.23 | K80: 1.92 | L80: 39.48 | M80: =+L80 -> 39.48 | N80: =+VLOOKUP(D80,'DISPOSITIVOS ACTIVOS'!B:D,3,FALSE) -> Galaxy | O80: =+VLOOKUP(D80,'DISPOSITIVOS ACTIVOS'!B:G,6,FALSE) -> PEREZ, YULIER | P80: =+VLOOKUP(D80,'DISPOSITIVOS ACTIVOS'!$B$1:$H$299,7,FALSE) -> LOGISTICS CENTRAL | Q80: =IFERROR(+VLOOKUP(D80,'[1]Migracion feb25 Ver to ATT'!$B:$B,1,FALSE), "NO") -> 615-830-4944 | R80: =+IF(Q80="NO",25,15) -> 15
A81: AT&T | B81: 25 | C81: 3 | D81: 615-830-6700 | E81: NICOLAS QUIJANO 2 | F81: 171 | G81: - | H81: 50 | I81: - | J81: 4.87 | K81: 2.57 | L81: 57.44 | M81: =+L81 -> 57.44 | N81: =+VLOOKUP(D81,'DISPOSITIVOS ACTIVOS'!B:D,3,FALSE) -> Iphone | O81: =+VLOOKUP(D81,'DISPOSITIVOS ACTIVOS'!B:G,6,FALSE) -> QUIJANO, NICOLAS | P81: =+VLOOKUP(D81,'DISPOSITIVOS ACTIVOS'!$B$1:$H$299,7,FALSE) -> CFO | Q81: =IFERROR(+VLOOKUP(D81,'[1]Migracion feb25 Ver to ATT'!$B:$B,1,FALSE), "NO") -> NO | R81: =+IF(Q81="NO",25,15) -> 25
A82: AT&T | B82: 25 | C82: 3 | D82: 615-840-0789 | E82: NAYRE PEREZ | F82: 173 | G82: -35 | H82: 50 | I82: - | J82: 4.23 | K82: 1.92 | L82: 21.15 | M82: =+L82 -> 21.15 | N82: =+VLOOKUP(D82,'DISPOSITIVOS ACTIVOS'!B:D,3,FALSE) -> Iphone | O82: =+VLOOKUP(D82,'DISPOSITIVOS ACTIVOS'!B:G,6,FALSE) -> PEREZ HERNANDEZ, NAYRE | P82: =+VLOOKUP(D82,'DISPOSITIVOS ACTIVOS'!$B$1:$H$299,7,FALSE) -> SALES CENTRAL | Q82: =IFERROR(+VLOOKUP(D82,'[1]Migracion feb25 Ver to ATT'!$B:$B,1,FALSE), "NO") -> 615-840-0789 | R82: =+IF(Q82="NO",25,15) -> 15
A83: AT&T | B83: 25 | C83: 3 | D83: 615-854-5649 | E83: MARCELA ROA | F83: 175 | G83: -35 | H83: 50 | I83: - | J83: 4.23 | K83: 1.92 | L83: 21.15 | M83: =+L83 -> 21.15 | N83: =+VLOOKUP(D83,'DISPOSITIVOS ACTIVOS'!B:D,3,FALSE) -> Iphone | O83: =+VLOOKUP(D83,'DISPOSITIVOS ACTIVOS'!B:G,6,FALSE) -> ROA, INGRID MARCELA | P83: =+VLOOKUP(D83,'DISPOSITIVOS ACTIVOS'!$B$1:$H$299,7,FALSE) -> SALES SOUTH | Q83: =IFERROR(+VLOOKUP(D83,'[1]Migracion feb25 Ver to ATT'!$B:$B,1,FALSE), "NO") -> 615-854-5649 | R83: =+IF(Q83="NO",25,15) -> 15
A84: AT&T | B84: 25 | C84: 3 | D84: 615-854-5797 | E84: CAROLINA TORREALBA | F84: 177 | G84: -35 | H84: 50 | I84: - | J84: 4.23 | K84: 1.92 | L84: 21.15 | M84: =+L84 -> 21.15 | N84: =+VLOOKUP(D84,'DISPOSITIVOS ACTIVOS'!B:D,3,FALSE) -> Iphone | O84: =+VLOOKUP(D84,'DISPOSITIVOS ACTIVOS'!B:G,6,FALSE) -> TORREALBA TORRES, CAROLINA | P84: =+VLOOKUP(D84,'DISPOSITIVOS ACTIVOS'!$B$1:$H$299,7,FALSE) -> SALES WEST | Q84: =IFERROR(+VLOOKUP(D84,'[1]Migracion feb25 Ver to ATT'!$B:$B,1,FALSE), "NO") -> 615-854-5797 | R84: =+IF(Q84="NO",25,15) -> 15
A85: AT&T | B85: 25 | C85: 3 | D85: 615-862-1976 | E85: JORGE TENGREDI | F85: 179 | G85: -16.67 | H85: 50 | I85: - | J85: 4.23 | K85: 1.92 | L85: 39.48 | M85: =+L85 -> 39.48 | N85: =+VLOOKUP(D85,'DISPOSITIVOS ACTIVOS'!B:D,3,FALSE) -> Galaxy | O85: =+VLOOKUP(D85,'DISPOSITIVOS ACTIVOS'!B:G,6,FALSE) -> TANGREDI, JORGE | P85: =+VLOOKUP(D85,'DISPOSITIVOS ACTIVOS'!$B$1:$H$299,7,FALSE) -> LOGISTICS CENTRAL | Q85: =IFERROR(+VLOOKUP(D85,'[1]Migracion feb25 Ver to ATT'!$B:$B,1,FALSE), "NO") -> 615-862-1976 | R85: =+IF(Q85="NO",25,15) -> 15
A86: AT&T | B86: 25 | C86: 3 | D86: 615-862-9402 | E86: RUDY BAHENA LG | F86: 181 | G86: -7.45 | H86: 50 | I86: - | J86: 4.87 | K86: 2.57 | L86: 49.99 | M86: =+L86 -> 49.99 | N86: =+VLOOKUP(D86,'DISPOSITIVOS ACTIVOS'!B:D,3,FALSE) -> Galaxy | O86: =+VLOOKUP(D86,'DISPOSITIVOS ACTIVOS'!B:G,6,FALSE) -> BAHENA, RUDY | P86: =+VLOOKUP(D86,'DISPOSITIVOS ACTIVOS'!$B$1:$H$299,7,FALSE) -> LOGISTICS WEST | Q86: =IFERROR(+VLOOKUP(D86,'[1]Migracion feb25 Ver to ATT'!$B:$B,1,FALSE), "NO") -> NO | R86: =+IF(Q86="NO",25,15) -> 25
A87: AT&T | B87: 25 | C87: 3 | D87: 615-878-0405 | E87: LUIS PARADA | F87: 183 | G87: -35 | H87: 50 | I87: - | J87: 4.23 | K87: 1.92 | L87: 21.15 | M87: =+L87 -> 21.15 | N87: Iphone | O87: =+VLOOKUP(D87,'DISPOSITIVOS ACTIVOS'!B:G,6,FALSE) -> TORRES, LUIS | P87: =+VLOOKUP(D87,'DISPOSITIVOS ACTIVOS'!$B$1:$H$299,7,FALSE) -> MERCHANDISER NORTH | Q87: =IFERROR(+VLOOKUP(D87,'[1]Migracion feb25 Ver to ATT'!$B:$B,1,FALSE), "NO") -> 615-878-0405 | R87: =+IF(Q87="NO",25,15) -> 15
A88: AT&T | B88: 25 | C88: 3 | D88: 615-879-8762 | E88: ANDRES FUENMAYOR | F88: 185 | G88: -16.67 | H88: 50 | I88: - | J88: 4.23 | K88: 1.92 | L88: 39.48 | M88: =+L88 -> 39.48 | N88: =+VLOOKUP(D88,'DISPOSITIVOS ACTIVOS'!B:D,3,FALSE) -> Galaxy | O88: =+VLOOKUP(D88,'DISPOSITIVOS ACTIVOS'!B:G,6,FALSE) -> FUENMAYOR, ANDRES | P88: =+VLOOKUP(D88,'DISPOSITIVOS ACTIVOS'!$B$1:$H$299,7,FALSE) -> LOGISTICS CENTRAL | Q88: =IFERROR(+VLOOKUP(D88,'[1]Migracion feb25 Ver to ATT'!$B:$B,1,FALSE), "NO") -> 615-879-8762 | R88: =+IF(Q88="NO",25,15) -> 15
A89: AT&T | B89: 25 | C89: 3 | D89: 615-881-4574 | E89: LIESKA MEMPHIS | F89: 187 | G89: - | H89: 50 | I89: - | J89: 0.67 | K89: 0.57 | L89: 51.24 | M89: =+L89 -> 51.24 | N89: Samsung | O89: =+VLOOKUP(D89,'DISPOSITIVOS ACTIVOS'!B:G,6,FALSE) -> #N/A | P89: =+VLOOKUP(D89,'DISPOSITIVOS ACTIVOS'!$B$1:$H$299,7,FALSE) -> #N/A | Q89: =IFERROR(+VLOOKUP(D89,'[1]Migracion feb25 Ver to ATT'!$B:$B,1,FALSE), "NO") -> 615-881-4574 | R89: =+IF(Q89="NO",25,15) -> 15
A90: AT&T | B90: 25 | C90: 3 | D90: 615-906-5129 | E90: RUDY BAHENA | F90: 189 | G90: -16.67 | H90: 50 | I90: - | J90: 4.23 | K90: 1.92 | L90: 39.48 | M90: =+L90 -> 39.48 | N90: =+VLOOKUP(D90,'DISPOSITIVOS ACTIVOS'!B:D,3,FALSE) -> Galaxy | O90: =+VLOOKUP(D90,'DISPOSITIVOS ACTIVOS'!B:G,6,FALSE) -> BAHENA, RUDY | P90: =+VLOOKUP(D90,'DISPOSITIVOS ACTIVOS'!$B$1:$H$299,7,FALSE) -> LOGISTICS WEST | Q90: =IFERROR(+VLOOKUP(D90,'[1]Migracion feb25 Ver to ATT'!$B:$B,1,FALSE), "NO") -> 615-906-5129 | R90: =+IF(Q90="NO",25,15) -> 15
A91: AT&T | B91: 25 | C91: 3 | D91: 615-939-6293 | E91: GABRIEL NASHVILLE | F91: 191 | G91: -7.45 | H91: 50 | I91: - | J91: 4.87 | K91: 2.57 | L91: 49.99 | M91: =+L91 -> 49.99 | N91: CANCELADO | O91: CANCELADO | P91: =+VLOOKUP(D91,'DISPOSITIVOS ACTIVOS'!$B$1:$H$299,7,FALSE) -> #N/A | Q91: =IFERROR(+VLOOKUP(D91,'[1]Migracion feb25 Ver to ATT'!$B:$B,1,FALSE), "NO") -> NO | R91: =+IF(Q91="NO",25,15) -> 25
A92: AT&T | B92: 25 | C92: 3 | D92: 615-939-8241 | E92: ALBERT CARDOZO | F92: 193 | G92: -35 | H92: 50 | I92: - | J92: 4.23 | K92: 1.92 | L92: 21.15 | M92: =+L92 -> 21.15 | N92: =+VLOOKUP(D92,'DISPOSITIVOS ACTIVOS'!B:D,3,FALSE) -> Iphone | O92: =+VLOOKUP(D92,'DISPOSITIVOS ACTIVOS'!B:G,6,FALSE) -> CARDOZO, ALBERT YVAN | P92: =+VLOOKUP(D92,'DISPOSITIVOS ACTIVOS'!$B$1:$H$299,7,FALSE) -> SALES RITEFILL DSD CENTRAL | Q92: =IFERROR(+VLOOKUP(D92,'[1]Migracion feb25 Ver to ATT'!$B:$B,1,FALSE), "NO") -> 615-939-8241 | R92: =+IF(Q92="NO",25,15) -> 15
A93: AT&T | B93: 25 | C93: 3 | D93: 615-939-9582 | E93: EDWIN GONZALEZ | F93: 195 | G93: -7.45 | H93: 50 | I93: - | J93: 4.87 | K93: 2.57 | L93: 49.99 | M93: =+L93 -> 49.99 | N93: =+VLOOKUP(D93,'DISPOSITIVOS ACTIVOS'!B:D,3,FALSE) -> Galaxy | O93: =+VLOOKUP(D93,'DISPOSITIVOS ACTIVOS'!B:G,6,FALSE) -> CASTILLO DUARTE, JOSE EDUARDO | P93: =+VLOOKUP(D93,'DISPOSITIVOS ACTIVOS'!$B$1:$H$299,7,FALSE) -> Finance | Q93: =IFERROR(+VLOOKUP(D93,'[1]Migracion feb25 Ver to ATT'!$B:$B,1,FALSE), "NO") -> NO | R93: =+IF(Q93="NO",25,15) -> 25
A94: AT&T | B94: 25 | C94: 3 | D94: 615-961-5944 | E94: JOSE BURGOS | F94: 197 | G94: -35 | H94: 50 | I94: - | J94: 4.23 | K94: 1.92 | L94: 21.15 | M94: =+L94 -> 21.15 | N94: =+VLOOKUP(D94,'DISPOSITIVOS ACTIVOS'!B:D,3,FALSE) -> Iphone | O94: =+VLOOKUP(D94,'DISPOSITIVOS ACTIVOS'!B:G,6,FALSE) -> SILVA, ELISA | P94: =+VLOOKUP(D94,'DISPOSITIVOS ACTIVOS'!$B$1:$H$299,7,FALSE) -> SALES WEST | Q94: =IFERROR(+VLOOKUP(D94,'[1]Migracion feb25 Ver to ATT'!$B:$B,1,FALSE), "NO") -> 615-961-5944 | R94: =+IF(Q94="NO",25,15) -> 15
A95: AT&T | B95: 25 | C95: 3 | D95: 615-969-5642 | E95: KARLA SOLIS | F95: 199 | G95: - | H95: 50 | I95: - | J95: 4.87 | K95: 2.57 | L95: 57.44 | M95: =+L95 -> 57.44 | N95: =+VLOOKUP(D95,'DISPOSITIVOS ACTIVOS'!B:D,3,FALSE) -> Iphone | O95: =+VLOOKUP(D95,'DISPOSITIVOS ACTIVOS'!B:G,6,FALSE) -> SOLIS SAN ANDRES, KARLA G | P95: =+VLOOKUP(D95,'DISPOSITIVOS ACTIVOS'!$B$1:$H$299,7,FALSE) -> SALES WEST | Q95: =IFERROR(+VLOOKUP(D95,'[1]Migracion feb25 Ver to ATT'!$B:$B,1,FALSE), "NO") -> NO | R95: =+IF(Q95="NO",25,15) -> 25
A96: AT&T | B96: 25 | C96: 3 | D96: 629-239-0377 | E96: CARMEN LONGA LG | F96: 201 | G96: - | H96: 50 | I96: - | J96: 4.87 | K96: 2.57 | L96: 57.44 | M96: =+L96 -> 57.44 | N96: =+VLOOKUP(D96,'DISPOSITIVOS ACTIVOS'!B:D,3,FALSE) -> Iphone | O96: =+VLOOKUP(D96,'DISPOSITIVOS ACTIVOS'!B:G,6,FALSE) -> LONGA, CARMEN B | P96: =+VLOOKUP(D96,'DISPOSITIVOS ACTIVOS'!$B$1:$H$299,7,FALSE) -> LOGISTICS WEST | Q96: =IFERROR(+VLOOKUP(D96,'[1]Migracion feb25 Ver to ATT'!$B:$B,1,FALSE), "NO") -> NO | R96: =+IF(Q96="NO",25,15) -> 25
A97: AT&T | B97: 25 | C97: 3 | D97: 629-239-0999 | E97: JOSE LUCIO | F97: 203 | G97: -35 | H97: 50 | I97: - | J97: 4.23 | K97: 1.92 | L97: 21.15 | M97: =+L97 -> 21.15 | N97: =+VLOOKUP(D97,'DISPOSITIVOS ACTIVOS'!B:D,3,FALSE) -> Iphone | O97: =+VLOOKUP(D97,'DISPOSITIVOS ACTIVOS'!B:G,6,FALSE) -> LUCIO FLORES, JOSE ANGEL | P97: =+VLOOKUP(D97,'DISPOSITIVOS ACTIVOS'!$B$1:$H$299,7,FALSE) -> SALES NORTH | Q97: =IFERROR(+VLOOKUP(D97,'[1]Migracion feb25 Ver to ATT'!$B:$B,1,FALSE), "NO") -> 629-239-0999 | R97: =+IF(Q97="NO",25,15) -> 15
A98: AT&T | B98: 25 | C98: 3 | D98: 629-256-6967 | E98: YNGEL GUTIERREZ | F98: 205 | G98: - | H98: 30 | I98: - | J98: 3.75 | K98: - | L98: 33.75 | M98: =+L98 -> 33.75 | N98: =+VLOOKUP(D98,'DISPOSITIVOS ACTIVOS'!B:D,3,FALSE) -> Ipad | O98: =+VLOOKUP(D98,'DISPOSITIVOS ACTIVOS'!B:G,6,FALSE) -> GUTIERREZ TOVAR, YNGEL J | P98: =+VLOOKUP(D98,'DISPOSITIVOS ACTIVOS'!$B$1:$H$299,7,FALSE) -> SALES CENTRAL | Q98: =IFERROR(+VLOOKUP(D98,'[1]Migracion feb25 Ver to ATT'!$B:$B,1,FALSE), "NO") -> NO | R98: =+IF(Q98="NO",25,15) -> 25
A99: AT&T | B99: 25 | C99: 3 | D99: 629-256-9168 | E99: YNGEL GUTIERREZ | F99: 207 | G99: -35 | H99: 50 | I99: - | J99: 4.23 | K99: 1.92 | L99: 21.15 | M99: =+L99 -> 21.15 | N99: =+VLOOKUP(D99,'DISPOSITIVOS ACTIVOS'!B:D,3,FALSE) -> Iphone | O99: =+VLOOKUP(D99,'DISPOSITIVOS ACTIVOS'!B:G,6,FALSE) -> GUTIERREZ TOVAR, YNGEL J | P99: =+VLOOKUP(D99,'DISPOSITIVOS ACTIVOS'!$B$1:$H$299,7,FALSE) -> SALES CENTRAL | Q99: =IFERROR(+VLOOKUP(D99,'[1]Migracion feb25 Ver to ATT'!$B:$B,1,FALSE), "NO") -> 629-256-9168 | R99: =+IF(Q99="NO",25,15) -> 15
A100: AT&T | B100: 25 | C100: 3 | D100: 629-264-3070 | E100: RICARDO BRITO HR | F100: 209 | G100: -6.75 | H100: 50 | I100: - | J100: 4.87 | K100: 2.57 | L100: 50.69 | M100: =+L100 -> 50.69 | N100: =+VLOOKUP(D100,'DISPOSITIVOS ACTIVOS'!B:D,3,FALSE) -> Iphone | O100: =+VLOOKUP(D100,'DISPOSITIVOS ACTIVOS'!B:G,6,FALSE) -> BRITO SALAZAR, RICARDO JOSE | P100: =+VLOOKUP(D100,'DISPOSITIVOS ACTIVOS'!$B$1:$H$299,7,FALSE) -> HR | Q100: =IFERROR(+VLOOKUP(D100,'[1]Migracion feb25 Ver to ATT'!$B:$B,1,FALSE), "NO") -> NO | R100: =+IF(Q100="NO",25,15) -> 25
...

Sheet DISPOSITIVOS ACTIVOS
A1: ID | B1: LINEA MOVIL | C1: Proveedor | D1: EQUIPMENT TYPE | E1: MODEL | F1: IMEI | G1: Usuario Asignado | H1: CECO | I1: LINEA | J1: LOCATION | K1: Estado | L1: Fecha de asignacion | M1: Fecha de ultima revision | N1: Condicion de equipo | O1: Comentarios | P1: Confirmation Letter
A2: 001 | B2: 615-708-0397 | C2: AT&T | D2: Iphone | E2: A2849 256GB Black Titanium | F2: 356964995021992 | G2: MADRIZ, JOHAN | H2: President | I2: Primera | J2: Nashville | K2: Activo | L2: 45658 | M2: 45717 | N2: Perfecto
A3: 002 | B3: 615-477-6490 | C3: AT&T | D3: Iphone | E3: A2848 256GB White Titanium | F3: 352917261435522 | G3: VILLATORO, MERARI | H3: VP | I3: Primera | J3: Nashville | K3: Activo | L3: 45658 | M3: 45717 | N3: Perfecto
A4: 003
A5: 004
A6: 005 | B6: 615-496-8278 | C6: AT&T | D6: Iphone | E6: iphone 16 PRO Max 512 GB Black Titanium | F6: 357205981304151 | G6: MADRIZ, JOHAN | H6: President | I6: Primera | J6: Nashville | K6: Activo | L6: 45658 | M6: 45717 | N6: Perfecto
A7: 006 | B7: 615-403-8760 | C7: AT&T | D7: Iphone | E7: iPhone 13 Pro Max A2484 256GB Alpine Green | F7: 356985725478830 | G7: VILLATORO, MERARI | H7: VP | I7: Primera | J7: Nashville | K7: Activo | L7: 45658 | M7: 45717 | N7: Perfecto
A8: 007 | B8: 615-417-9594 | C8: AT&T | D8: Iphone | E8: iPhone 13 Pro Max A2484 256GB Graphite | F8: 350566101441174 | G8: QUIJANO, NICOLAS | H8: CFO | I8: Primera | J8: Nashville | K8: Activo | L8: 45658 | M8: 45717 | N8: Perfecto | P8: Send
A9: 008 | B9: 615-691-3166 | C9: AT&T | D9: Iphone | E9: iPhone 13 Pro Max A2484 256GB Gold | F9: 356796480675498 | G9: QUIJANO, NICOLAS | H9: CFO | I9: Primera | J9: Nashville | K9: Activo | L9: 45658 | M9: 45717 | N9: Perfecto | P9: Send
A10: 009 | B10: 615-830-6700 | C10: AT&T | D10: Iphone | E10: Iphone 11 Pro | F10: 353247104496222 | G10: QUIJANO, NICOLAS | H10: CFO | I10: Primera | J10: Nashville | K10: Activo | L10: 45658 | M10: 45717 | N10: Perfecto | P10: Send
A11: 010 | B11: 615-626-4243 | C11: AT&T | D11: Iphone | E11: iPhone 13 Pro Max A2484 128GB Graphite | F11: 350019045940745 | G11: HERRERA MOLINA, JOSE CARLOS | H11: CEO | I11: Primera | J11: Nashville | K11: Activo | L11: 45658 | M11: 45717 | N11: Perfecto | P11: Send
A12: 011 | B12: 615-626-7710 | C12: VERIZON | D12: Ipad | E12: 10.2 IPAD 8 GEN 32GB SG | F12: 356747116811213 | G12: HERRERA MOLINA, JOSE CARLOS | H12: CEO | I12: Primera | J12: Nashville | K12: Activo | L12: 45658 | M12: 45717 | N12: Perfecto | P12: Send
A13: 012 | B13: 615-316-8577 | C13: AT&T | D13: Iphone | E13: iPhone 14 Plus A2632 128GB Midnight | F13: 353547798360296 | G13: DUQUE IYENGAR, DANIELA | H13: HR | I13: Primera | J13: Nashville | K13: Activo | L13: 45658 | M13: 45717 | N13: Perfecto | P13: Send
A14: 013 | B14: 615-971-0833 | C14: VERIZON | D14: Galaxy | E14: SAMSUNG GALAXY A23 5G UW | F14: 355978840919284 | G14: BEARD, JUSTIN O | H14: LOGISTICS WEST | I14: Tercera | J14: Memphis | K14: Activo | L14: 45658 | M14: 45717 | N14: Perfecto
A15: 014 | B15: 615-337-4949 | C15: AT&T | D15: Galaxy | E15: SAMSUNG GALAXY A23 5G UW | F15: 351700860699123 | G15: CONDE TORRES, DAVID A | H15: WAREHOUSE CENTRAL | I15: Tercera | J15: Nashville | K15: Activo | L15: 45658 | M15: 45717 | N15: Perfecto
A16: 015 | B16: 901-607-5291 | C16: AT&T | D16: Galaxy | E16: SAMSUNG GALAXY A23 5G UW | F16: 355978840897134 | G16: CORPUS, BENY A | H16: LOGISTICS CENTRAL | I16: Tercera | J16: Nashville | K16: Activo | L16: 45658 | M16: 45717 | N16: Perfecto
A17: 244 | B17: 615-390-4624 | C17: AT&T | D17: Iphone | E17: Iphone 14 Pro MaX | F17: 356485673725928 | G17: ESQUIVEL, HENRY | H17: WAREHOUSE CENTRAL | I17: Segunda | J17: Nashville | K17: Activo | L17: 45658 | M17: 45717 | N17: Perfecto
A18: 017 | B18: 615-299-3641 | C18: AT&T | D18: Motorola | E18: moto g stylus 5G XT2131-3 128GB Cosmic Emerald | F18: 355984450930637 | G18: FERNANDEZ, EDGAR | H18: LOGISTICS CENTRAL | I18: Tercera | J18: Nashville | K18: Activo | L18: 45658 | M18: 45717 | N18: Perfecto
A19: 018 | B19: 629-239-0377 | C19: AT&T | D19: Iphone | E19: iPhone 13 A2482 128GB Midnight | F19: 358091652355105 | G19: LONGA, CARMEN B | H19: LOGISTICS WEST | I19: Segunda | J19: Memphis | K19: Activo | L19: 45658 | M19: 45717 | N19: Perfecto
A20: 019 | B20: 502-558-5770 | C20: AT&T | D20: Galaxy | E20: SAMSUNG GALAXY A23 5G UW | F20: 355978840941007 | G20: MOJICA, FRANCISCO JAVIER | H20: LOGISTICS CENTRAL | I20: Tercera | J20: Nashville | K20: Activo | L20: 45658 | M20: 45717 | N20: Perfecto
A21: 020 | B21: 615-862-9402 | C21: AT&T | D21: Galaxy | E21: Galaxy A13 5G SM-A136U 64GB Black | F21: 351082120997815 | G21: BAHENA, RUDY | H21: LOGISTICS WEST | I21: Tercera | J21: Memphis | K21: Activo | L21: 45658 | M21: 45717 | N21: Perfecto
A22: 021 | B22: 629-201-9859 | C22: VERIZON | D22: Galaxy | E22: SAMSUNG GALAXY A23 5G UW | F22: 355978840948754 | G22: LAMA, DENIS | H22: LOGISTICS NORTH | I22: Tercera | J22: Cincinnatti | K22: Activo | L22: 45658 | M22: 45717 | N22: Perfecto
A23: 022 | B23: 901-585-9984 | C23: AT&T | D23: Galaxy | E23: SAMSUNG GALAXY A23 5G UW | F23: 355978840945446 | G23: DE LA TORRE, LUIS G | H23: LOGISTICS WEST | I23: Tercera | J23: Memphis | K23: Activo | L23: 45658 | M23: 45717 | N23: Perfecto
A24: 023 | B24: 615-598-2524 | C24: VERIZON | D24: Galaxy | E24: SAMSUNG GALAXY A23 5G UW | F24: 355978840949059 | G24: SALGUERO, RONALD | H24: LOGISTIC SOUTH | I24: Tercera | J24: Birmingham | K24: Activo | L24: 45762 | M24: 45762 | N24: Perfecto
A25: 024 | B25: 615-795-8193 | C25: AT&T | D25: Galaxy | E25: SAMSUNG GALAXY A13 | F25: 351082120939429 | G25: REMBERT, ANTORIUS DAVUN | H25: LOGISTICS SOUTH | I25: Tercera | J25: Birmingham | K25: Activo | L25: 45658 | M25: 45717 | N25: Perfecto
A26: 025 | B26: 502-974-3915 | C26: AT&T | D26: Iphone | E26: IPHONE13 128GB MDN NVZ ATT | F26: 358091652696490 | G26: ARMES, CLAUDIA | H26: SALES NORTH | I26: Tercera | J26: Cincinnatti | K26: Activo | L26: 45658 | M26: 45717 | N26: Perfecto
A27: 026 | B27: 615-417-0015 | C27: AT&T | D27: Iphone | E27: iPhone 13 A2482 128GB Midnight | F27: 354739183440614 | G27: BARAJAS, JESSICA | H27: SALES NORTH | I27: Tercera | J27: Cincinnatti | K27: Activo | L27: 45658 | M27: 45717 | N27: Perfecto
A28: 027 | B28: 615-417-2841 | C28: VERIZON | D28: Ipad | E28: 10.2 IPAD 8 GEN 32GB SG | F28: 356749110441328 | G28: BARAJAS, JESSICA | H28: SALES NORTH | I28: Tercera | J28: Cincinnatti | K28: Activo | L28: 45658 | M28: 45717 | N28: Perfecto
A29: 028 | B29: 615-456-2536 | C29: AT&T | D29: Iphone | E29: IPHONE13 128GB MDN NVZ ATT | F29: 358091652064830 | G29: CABANZO, DANNY | H29: SALES CENTRAL | I29: Tercera | J29: Nashville | K29: Activo | L29: 45658 | M29: 45717 | N29: Perfecto
... A54: 053 | B54: 317-500-7156 | C54: AT&T | D54: Iphone | E54: IPHONE13 128GB MDN NVZ ATT | F54: 358091652408037 | G54: SORIANO, NAYELY | H54: SALES NORTH | I54: Tercera | J54: Cincinnatti | K54: Activo | L54: 45658 | M54: 45717 | N54: Perfecto
A55: 054 | B55: 615-881-2222 | C55: VERIZON | D55: Ipad | E55: IPAD 9GEN 64 GRAY | F55: 355254195678622 | G55: SORIANO, NAYELY | H55: SALES NORTH | I55: Tercera | J55: Cincinnatti | K55: DESCONECTADA | L55: 45658 | M55: 45717 | N55: Perfecto | O55: DESCONECTADA Y PASADA A ATT
A56: 055 | B56: 615-945-4365 | C56: AT&T | D56: Ipad | E56: iPad 9th Gen. (2021) A2603 64GB Space Gray | F56: 359552545614718 | G56: TELLO, IVAN E | H56: SALES CENTRAL | I56: Tercera | J56: Nashville | K56: Activo | L56: 45658 | M56: 45717 | N56: Perfecto
A57: 056 | B57: 615-730-3104 | C57: AT&T | D57: Iphone | E57: iPhone 14 Plus A2632 128GB Midnight | F57: 353547795738981 | G57: TELLO, IVAN E | H57: SALES CENTRAL | I57: Tercera | J57: Nashville | K57: Activo | L57: 45658 | M57: 45717 | N57: Perfecto
A58: 057 | B58: 615-812-1894 | C58: VERIZON | D58: Ipad | E58: IPAD 9GEN 64 GRAY | F58: 357883402867509 | G58: TORREALBA TORRES, CAROLINA | H58: SALES WEST | I58: Tercera | J58: Memphis | K58: DESCONECTADA | L58: 45658 | M58: 45717 | N58: Perfecto
A59: 058 | B59: 615-854-5797 | C59: AT&T | D59: Iphone | E59: IPHONE13 128GB MDN NVZ ATT | F59: 350980291513736 | G59: TORREALBA TORRES, CAROLINA | H59: SALES WEST | I59: Tercera | J59: Memphis | K59: Activo | L59: 45658 | M59: 45717 | N59: Perfecto
A60: 059 | B60: 615-878-0405 | C60: AT&T | G60: TORRES, LUIS | H60: MERCHANDISER NORTH | I60: Tercera | J60: Cincinnatti | O60: Asignar o ver si tien asignado
A61: 060 | B61: 615-714-1323 | C61: VERIZON | D61: Ipad | E61: IPAD 9GEN 64 GRAY | F61: 357652533500689 | G61: TOVAR, ZULLYMAR | H61: SALES CENTRAL | I61: Segunda | J61: Nashville | K61: Activo | L61: 45658 | M61: 45717 | N61: Perfecto
A62: 061 | B62: 865-396-3528 | C62: AT&T | D62: Ipad | E62: iPad 9th Gen. (2021) A2603 64GB Space Gray | F62: 359552541604085 | G62: VELIZ, CARLOS A | H62: SALES CENTRAL | I62: Tercera | J62: Nashville | K62: Activo | L62: 45658 | M62: 45717 | N62: Perfecto
A63: 062 | B63: 629-345-1182 | C63: AT&T | D63: Ipad | E63: iPad 9th Gen. (2021) A2603 64GB Space Gray | F63: 357652530925137 | G63: LACRUZ, ROSMARY | H63: SALES WEST | I63: Tercera | J63: Memphis | K63: Activo | L63: 45658 | M63: 45717 | N63: Perfecto
A64: 063 | B64: 601-910-8492 | C64: AT&T | D64: Iphone | E64: IPHONE12 64G BLK-E NVZ ATT | F64: 351139862096055 | G64: LACRUZ, ROSMARY | H64: SALES WEST | I64: Tercera | J64: Memphis | K64: Activo | L64: 45658 | M64: 45717 | N64: Perfecto
A65: 064 | B65: 901-581-6397 | C65: AT&T | D65: Iphone | E65: iPhone 13 A2482 128GB Midnight | F65: 358091652248979 | G65: AVALOS, JOSEFINA | H65: SALES WEST | I65: Tercera | J65: Memphis | K65: Activo | L65: 45658 | M65: 45717 | N65: Perfecto
A66: 065 | B66: 901-275-9469 | C66: VERIZON | D66: Ipad | E66: IPAD 9GEN 64 GRAY | F66: 359552540047567 | G66: AVALOS, JOSEFINA | H66: SALES WEST | I66: Tercera | J66: Memphis | K66: Activo | L66: 45658 | M66: 45717 | N66: Perfecto
A67: 066 | B67: 615-944-5380 | C67: AT&T | D67: Ipad | E67: iPad 9th Gen. (2021) A2603 64GB Space Gray | F67: 359552545484377 | G67: PALENCIA RODRIGUEZ, LEONARDO R | H67: SALES CENTRAL | I67: Tercera | J67: Nashville | K67: Activo | L67: 45658 | M67: 45717 | N67: Perfecto
A68: 067 | B68: 615-828-8926 | C68: AT&T | D68: Iphone | E68: iPhone 14 Plus A2632 128GB Midnight | F68: 352820547105259 | G68: PALENCIA RODRIGUEZ, LEONARDO R | H68: SALES CENTRAL | I68: Tercera | J68: Nashville | K68: Activo | L68: 45658 | M68: 45717 | N68: Perfecto
A69: 068 | B69: 615-203-1637 | C69: VERIZON | D69: Ipad | E69: 10.2 IPAD 8 GEN 32GB SG | F69: 356750112980248 | G69: PEREZ HERNANDEZ, NAYRE | H69: SALES CENTRAL | I69: Tercera | J69: Nashville | K69: Activo | L69: 45658 | M69: 45717 | N69: Perfecto
A70: 069 | B70: 615-840-0789 | C70: AT&T | D70: Iphone | E70: IPHONE13 128GB MDN NVZ ATT | F70: 350980291914207 | G70: PEREZ HERNANDEZ, NAYRE | H70: SALES CENTRAL | I70: Tercera | J70: Nashville | K70: Activo | L70: 45658 | M70: 45717 | N70: Perfecto
A71: 070 | B71: 615-969-5642 | C71: AT&T | D71: Iphone | E71: iPhone 13 A2482 128GB Midnight | F71: 350980291790359 | G71: SOLIS SAN ANDRES, KARLA G | H71: SALES WEST | I71: Tercera | J71: Memphis | K71: Activo | L71: 45658 | M71: 45717 | N71: Perfecto
A72: 071 | B72: 901-275-5428 | C72: AT&T | D72: Iphone | E72: IPHONE13 128GB MDN NVZ ATT | F72: 358091652927259 | G72: RODRIGUEZ, VERUUZKO | H72: SALES CENTRAL | I72: Segunda | J72: Nashville | K72: Activo | L72: 45658 | M72: 45717 | N72: Perfecto
... A87: 086 | B87: 615-961-2627 | C87: VERIZON | D87: Ipad | E87: IPAD 9GEN 64 GRAY | F87: 350698362572957 | G87: LUCIO FLORES, JOSE ANGEL | H87: SALES NORTH | I87: Tercera | J87: Cincinnatti | K87: Activo | L87: 45658 | M87: 45717 | N87: Perfecto
A88: 246 | B88: 901-713-7796 | C88: AT&T | D88: Iphone | E88: Iphone 14 | F88: 354807370356289 | G88: FERREIRA, ANA CAROLINA | H88: MERCHANDISER WEST | I88: Tercera | J88: Memphis | K88: Activo | L88: 45658 | M88: 45717 | N88: Perfecto
A89: 088 | B89: 513-720-1147 | C89: AT&T | D89: Iphone | E89: iPhone 14 Plus A2632 128GB Midnight | F89: 353696749029201 | G89: ALVAREZ PALOMARES M, PAULA MAYREN | H89: MERCHANDISER NORTH | I89: Tercera | J89: Cincinnatti | K89: Activo | L89: 45658 | M89: 45717 | N89: Perfecto
A90: 089 | B90: 615-587-3400 | C90: VERIZON | D90: Iphone | E90: IPHONE12P 128G GRP NVZ TMO | F90: 351001682973048 | G90: DUARTE, ANGELA | H90: SALES CENTRAL | I90: Tercera | J90: Nashville | K90: Activo | L90: 45658 | M90: 45717 | N90: Perfecto
A91: 090 | B91: 615-961-0855 | C91: VERIZON | D91: Ipad | E91: IPAD 9GEN 64 GRAY | F91: 357883402125478 | G91: DUARTE, ANGELA | H91: SALES CENTRAL | I91: Tercera | J91: Nashville | K91: Activo | L91: 45658 | M91: 45717 | N91: Perfecto
A92: 091 | B92: 615-310-9970 | C92: AT&T | D92: Ipad | E92: IPAD 9GEN 64 GRAY | F92: 357883402696494 | G92: CARDOZO, ALBERT YVAN | H92: SALES RITEFILL DSD CENTRAL | I92: Tercera | J92: Nashville | K92: Activo | L92: 45658 | M92: 45717 | N92: Perfecto
A93: 092 | B93: 615-939-8241 | C93: AT&T | D93: Iphone | E93: IPHONE 12 GEN NVZW | F93: 350839224004728 | G93: CARDOZO, ALBERT YVAN | H93: SALES RITEFILL DSD CENTRAL | I93: Tercera | J93: Nashville | K93: Activo | L93: 45658 | M93: 45717 | N93: Perfecto
A94: 093 | B94: 615-589-4199 | C94: AT&T | D94: Iphone | E94: iPhone 13 A2482 128GB Midnight | F94: 351829684067157 | G94: PELAEZ, ELIZABETH | H94: SALES CENTRAL | I94: Tercera | J94: Nashville | K94: Activo | L94: 45658 | M94: 45717 | N94: Perfecto
A95: 094 | B95: 615-728-2262 | C95: VERIZON | D95: Galaxy | E95: SAMSUNG GALAXY A23 5G UW | F95: 355978840939803 | G95: PELAEZ, ELIZABETH | H95: SALES CENTRAL | I95: Tercera | J95: Nashville | K95: Activo | L95: 45658 | M95: 45717 | N95: Perfecto
A96: 095 | B96: 615-589-2741 | C96: AT&T | D96: Ipad | E96: iPad 9th Gen. (2021) A2603 64GB Space Gray | F96: 350698365094306 | G96: SILVA R, ROSMARY JOSE | H96: SALES SOUTH | I96: Tercera | J96: Birmingham | K96: Activo | L96: 45658 | M96: 45717 | N96: Perfecto
A97: 096 | B97: 205-529-6296 | C97: AT&T | D97: Iphone | E97: IPHONE13 128GB MDN NVZ ATT | F97: 359673359488781 | G97: SILVA R, ROSMARY JOSE | H97: SALES SOUTH | I97: Tercera | J97: Birmingham | K97: Activo | L97: 45658 | M97: 45717 | N97: Perfecto
A98: 097 | B98: 501-773-3738 | C98: AT&T | D98: Ipad | E98: iPad 9th Gen. (2021) A2603 64GB Space Gray | F98: 359552541123334 | G98: VILLAVICENCIO, ARTURO J | H98: SALES WEST | I98: Tercera | J98: Memphis | K98: Activo | L98: 45658 | M98: 45717 | N98: Perfecto | O98: Confirmar quien tiene este IPAD SI NAIROVI O EL
A99: 098 | B99: 615-319-8134 | C99: VERIZON | D99: Galaxy | E99: SAMSUNG GALAXY A23 5G UW | F99: 355978840923146 | G99: HERNANDEZ ARREGUIN, ANA AIDET | H99: HR | I99: Tercera | J99: Nashville | K99: Activo | L99: 45658 | M99: 45717 | N99: Perfecto | P99: Send
A100: 099 | B100: 629-264-3070 | C100: AT&T | D100: Iphone | E100: iPhone 13 A2482 128GB Midnight | F100: 357084344468932 | G100: BRITO SALAZAR, RICARDO JOSE | H100: HR | I100: Tercera | J100: Nashville | K100: Activo | L100: 45658 | M100: 45717 | N100: Perfecto | P100: Send
A101: 100 | B101: 615-830-4944 | C101: AT&T | D101: Galaxy | E101: SAMSUNG GALAXY A23 5G UW | F101: 355978840889404 | G101: PEREZ, YULIER | H101: LOGISTICS CENTRAL | I101: Tercera | J101: Nashville | K101: Activo | L101: 45658 | M101: 45717 | N101: Perfecto
A102: 101 | B102: 615-862-1976 | C102: AT&T | D102: Galaxy | E102: SAMSUNG GALAXY A23 5G UW | F102: 355978840929473 | G102: TANGREDI, JORGE | H102: LOGISTICS CENTRAL | I102: Tercera | J102: Nashville | K102: Activo | L102: 45658 | M102: 45717 | N102: Perfecto
A103: 102 | B103: 615-862-9112 | C103: VERIZON | D103: Galaxy | E103: SAMSUNG GALAXY A23 5G UW | F103: 355978840939845 | G103: VELAZCO GARCIA, JOEL | H103: LOGISTICS CENTRAL | I103: Tercera | J103: Nashville | K103: Activo | L103: 45658 | M103: 45717 | N103: Perfecto | O103: Revisar por que se migro
A104: 103 | B104: 615-651-0245 | C104: VERIZON | D104: Ipad | E104: IPAD 7TH GEN 32GB GRAY VZ | F104: 353205104482748 | G104: RODRIGUEZ, VERUUZKO | H104: SALES CENTRAL | I104: Segunda | J104: Nashville | K104: Activo | L104: 45658 | M104: 45717 | N104: Perfecto
A105: 104 | B105: 615-674-8479 | C105: AT&T | D105: Iphone | E105: iPhone 12 Pro Max 128 GB | F105: 359735196551665 | G105: PRADO, JORGE A | H105: COO | I105: Primera | J105: Nashville | K105: Activo | L105: 45658 | M105: 45717 | N105: Perfecto | O105: Revisar el IMEI Y TELEFONO ANTERIOR, BUSCARLO? DONDE ESTA?
A106: 105 | B106: 901-500-6953 | C106: AT&T | D106: Galaxy | E106: SAMSUNG GALAXY A23 5G UW | F106: 355978840934853 | G106: RODRIGUEZ MELENDEZ, CESAR ANIBAL | H106: LOGISTICS NORTH | I106: Tercera | J106: Cincinnatti | K106: Activo | L106: 45658 | M106: 45717 | N106: Perfecto
A107: 106 | B107: 615-948-1111 | C107: VERIZON | D107: Galaxy | E107: SAMSUNG GALAXY A23 5G UW | F107: 355978840945222 | G107: WATSON, JORDAN MATTHEW | H107: LOGISTICS NORTH | I107: Tercera | J107: Cincinnatti | K107: Activo | L107: 45658 | M107: 45717 | N107: Perfecto | O107: Revisar si esta en Verizon o ATT?
A108: 107 | B108: 615-636-7429 | C108: VERIZON | D108: Ipad | E108: IPAD 9GEN 64 GRAY | F108: 350698362550466 | G108: ARMES, CLAUDIA | H108: SALES NORTH | I108: Tercera | J108: Cincinnatti | K108: Activo | L108: 45658 | M108: 45717 | N108: Perfecto | O108: CONFIRMAR SI LO TIENE ELLA
A109: 108 | B109: 629-256-9168 | C109: VERIZON | D109: Iphone | E109: IPHONE12 64G BLK NVZ ATT | F109: 351139862265361 | G109: GUTIERREZ TOVAR, YNGEL J | H109: SALES CENTRAL | I109: Tercera | J109: Nashville | K109: Activo | L109: 45658 | M109: 45717 | N109: Perfecto
A110: 109 | B110: 615-879-8490 | C110: VERIZON | D110: Ipad | E110: IPAD 7TH GEN 32GB GRAY VZ | F110: 353204105703897 | G110: LOPEZ, ALEJANDRA C | H110: SALES WEST | I110: Segunda | J110: Memphis | K110: Activo | L110: 45658 | M110: 45717 | N110: Perfecto | O110: VER SI LO TIENE ALEJANDRA O VERUUZKO
A111: 110 | B111: 615-812-5934 | C111: AT&T | D111: Iphone | E111: iPhone 13 A2482 128GB Midnight | F111: 350980291515202 | G111: QUEVEDO, NAIROVI Y | H111: SALES WEST | I111: Tercera | J111: Memphis | K111: Activo | L111: 45658 | M111: 45717 | N111: Perfecto
A112: 111 | B112: 615-812-2408 | C112: VERIZON | D112: Ipad | E112: IPAD9TH GEN NON-VZW | F112: 359552541123334 | G112: QUEVEDO, NAIROVI Y | H112: SALES WEST | I112: Tercera | J112: Memphis | K112: Activo | L112: 45658 | M112: 45717 | N112: Perfecto | O112: Confirmar quien tiene este IPAD SI ARTURO O ELLA
A113: 112 | B113: 615-626-3219 | F113: 355103314581953 | G113: TOVAR, ZULLYMAR | H113: SALES CENTRAL | I113: Segunda | J113: Nashville | K113: Activo | L113: 45658 | M113: 45717 | N113: Perfecto | O113: CONFIRMAR LA LINEA DE ELLA
A114: 113 | B114: 865-396-3526 | C114: VERIZON | D114: Iphone | E114: IPHONE12 64G BLK NVZ ATT | F114: 350110421858518 | G114: VELIZ, CARLOS A | H114: SALES CENTRAL | I114: Tercera | J114: Nashville | K114: Activo | L114: 45658 | M114: 45717 | N114: Perfecto
A115: 114 | G115: DIAZ, MEYLING J | H115: MERCHANDISER WEST | I115: Tercera | J115: Memphis | K115: Activo | L115: 45658 | M115: 45717 | N115: Perfecto | O115: CONFIRMAR
A116: 115 | B116: 615-969-8609 | C116: VERIZON | D116: Ipad | E116: 10.2 IPAD 8 GEN 32GB SG | F116: 356751111122915 | G116: SOLIS SAN ANDRES, KARLA G | H116: SALES WEST | I116: Tercera | J116: Memphis | K116: DESCONECTADA | L116: 45658 | M116: 45717 | N116: Perfecto | O116: DESCONECTADA Y PASADA A ATT
A117: 116 | B117: 615-804-2180 | C117: VERIZON | D117: Ipad | E117: 10.2 IPAD 8 GEN 32GB SLR SO | F117: 356750111840153 | G117: CABRERA, OSMAN A | H117: SALES CENTRAL | I117: Tercera | J117: Nashville | K117: Activo | L117: 45658 | M117: 45717 | N117: Perfecto | O117: AVERIGUAR QUIEN LO TIENE, SALE JG MARTINEZ EN VERIZON
A118: 117 | B118: 629-239-0999 | C118: AT&T | D118: Iphone | E118: IPHONE13 128GB MDN NVZ ATT | F118: 358091652874097 | G118: LUCIO FLORES, JOSE ANGEL | H118: SALES NORTH | I118: Tercera | J118: Cincinnatti | K118: Activo | L118: 45658 | M118: 45717 | N118: Perfecto
A119: 118 | B119: 501-773-3763 | C119: AT&T | D119: Iphone | E119: IPHONE12 64G BLK NVZ ATT | F119: 3501104219697 | G119: VILLAVICENCIO, ARTURO J | H119: SALES WEST | I119: Tercera | J119: Memphis | K119: Activo | L119: 45658 | M119: 45717 | N119: Perfecto
A120: 119 | B120: 615-984-9515 | C120: VERIZON | D120: Galaxy | E120: SAMSUNG GALAXY A23 5G UW | F120: 355978840949711 | G120: SUAREZ LEZCANO, FERNANDO M | H120: SALES RITEFILL DSD CENTRAL | I120: Tercera | J120: Nashville | K120: Activo | L120: 45658 | M120: 45717 | N120: Perfecto | O120: SE FUE
A121: 120 | B121: 615-626-2116 | C121: VERIZON | D121: Iphone | E121: IPHONE13 128GB MDN NVZ ATT | F121: 358091652358661 | G121: SUAREZ LEZCANO, FERNANDO M | H121: SALES RITEFILL DSD CENTRAL | I121: Tercera | J121: Nashville | K121: Activo | L121: 45658 | M121: 45717 | N121: Perfecto | O121: SE FUE
A122: 121 | B122: 615-939-9582 | C122: AT&T | D122: Galaxy | E122: Galaxy A13 5G SM-A136U 64GB Black | F122: 351082120960722 | G122: CASTILLO DUARTE, JOSE EDUARDO | H122: Finance | I122: Tercera | J122: Nashville | K122: Activo | L122: 45658 | M122: 45717 | N122: Perfecto | P122: Send
A123: 122 | B123: 629-285-9899 | C123: AT&T | D123: Iphone | E123: iPhone 13 Pro Max A2484 128GB Graphite | F123: 352865675892301 | G123: LODYGENSKY, ISABELE | H123: Corpotative ESG 110002 | I123: Segunda | J123: Nashville | K123: Activo | L123: 45658 | M123: 45717 | N123: Perfecto | P123: Send
A124: 123 | B124: 901-427-2093 | C124: VERIZON | D124: Galaxy | E124: SAMSUNG GALAXY A23 5G UW | F124: 355978840924771 | G124: SUAREZ, ANDRES E | H124: LOGISTICS CENTRAL | I124: Tercera | J124: Nashville | K124: Activo | L124: 45658 | M124: 45717 | N124: Perfecto
A125: 124 | B125: 629-468-8256 | C125: AT&T | G125: VIVAS, REYNA E | H125: SALES RITEFILL DSD WEST | I125: Tercera | J125: Memphis | K125: Activo | L125: 45658 | M125: 45717 | N125: Perfecto
A126: 245 | B126: 629-318-9109 | C126: AT&T | D126: Ipad | E126: Ipad Wifi 64 GB Silver | F126: 356029485261308 | G126: VIVAS, REYNA E | H126: SALES RITEFILL DSD WEST | I126: Tercera | J126: Memphis | K126: Activo | L126: 45723 | M126: 45723 | N126: Perfecto
A127: 126 | B127: 629-318-8877 | C127: AT&T | D127: Ipad | E127: Ipad Wifi 64 GB Silver | F127: 356029485569361 | H127: SALES RITEFILL DSD SOUTH | I127: Tercera | J127: Birmingham | K127: Activo | L127: 45658 | M127: 45717 | N127: Perfecto
A128: 127 | B128: 659-268-2242 | C128: AT&T | H128: SALES RITEFILL DSD SOUTH | I128: Tercera | J128: Birmingham | K128: Activo | L128: 45658 | M128: 45717 | N128: Perfecto
A129: 128 | B129: 615-299-3640 | C129: AT&T | D129: Galaxy | E129: GALAXY A13 | F129: 351082120669125 | G129: DE LOS SANTOS, LUIS | H129: LOGISTIC SOUTH | I129: Tercera | J129: Birmingham | K129: Activo | L129: 45762 | M129: 45762 | N129: Perfecto
A130: 129 | B130: 901-410-6734 | C130: AT&T | D130: Galaxy | E130: GALAXY A13 | F130: 351082125564644 | G130: RODRIGUEZ SR, CHRISTIAN MICHEAL | H130: LOGISTIC SOUTH | I130: Tercera | J130: Birmingham | K130: Activo | L130: 45658 | M130: 45717 | N130: Perfecto
A131: 130 | B131: 615-795-8195 | C131: AT&T | D131: Galaxy | E131: SAMSUNG GALAXY A23 5G UW | F131: 355978840888703 | G131: FERRER BRACHO, MERVIN J | H131: LOGISTICS CENTRAL | I131: Tercera | J131: Nashville | K131: Activo | L131: 45658 | M131: 45717 | N131: Perfecto
A132: 131 | B132: 615-879-8762 | C132: AT&T | D132: Galaxy | E132: SAMSUNG GALAXY A23 5G UW | F132: 355978840899098 | G132: FUENMAYOR, ANDRES | H132: LOGISTICS CENTRAL | I132: Tercera | J132: Nashville | K132: Activo | L132: 45658 | M132: 45717 | N132: Perfecto
A133: 132 | B133: 615-906-5129 | C133: AT&T | D133: Galaxy | E133: SAMSUNG GALAXY A23 5G UW | F133: 355978840945693 | G133: BAHENA, RUDY | H133: LOGISTICS WEST | I133: Tercera | J133: Memphis | K133: Activo | L133: 45658 | M133: 45717 | N133: Perfecto
A134: 133 | B134: 812-893-5245 | C134: VERIZON | D134: Iphone | E134: IPHONE13 128GB MDN NVZ ATT | F134: 358091652066132 | G134: RIOS BLANDON, AUGUSTO C | H134: SALES NORTH | I134: Tercera | J134: Cincinnatti | K134: Activo | L134: 45658 | M134: 45717 | N134: Perfecto
A135: 134 | B135: 615-967-4046 | C135: AT&T | D135: Ipad | F135: 356751113340572 | G135: RIOS BLANDON, AUGUSTO C | H135: SALES NORTH | I135: Tercera | J135: Cincinnatti | K135: Activo | L135: 45658 | M135: 45717 | N135: Perfecto
A136: 135
A137: 136 | B137: 615-961-5944 | C137: VERIZON | D137: Iphone | E137: IPHONE13 128GB MDN NVZ ATT-2 | F137: 358091652491496 | G137: SILVA, ELISA | H137: SALES WEST | I137: Tercera | J137: Nashville | K137: Activo | L137: 45717 | M137: 45717 | N137: Perfecto
A138: 137 | B138: 615-768-6114 | C138: AT&T | D138: Ipad | E138: IP 10.9 64 BLUE 22 | F138: 355939974972648 | G138: SILVA, ELISA | H138: SALES WEST | I138: Tercera | J138: Nashville | K138: Activo | L138: 45717 | M138: 45717 | N138: Perfecto
...

Sheet MIGRACION SEPTIEMBRE 2025
A1: ID | B1: LINEA MOVIL | C1: Proveedor | D1: EQUIPMENT TYPE | E1: MODEL | F1: IMEI | G1: Usuario Asignado | H1: CECO | I1: LINEA | J1: LOCATION | K1: Estado | L1: Fecha de asignacion | M1: Fecha de ultima revision | N1: Condicion de equipo | O1: Comentarios | P1: etf | Q1: TRANSFERENCIA DE PIN
A2: 001 | B2: 615-708-0397 | C2: AT&T | D2: Iphone | E2: A2849 256GB Black Titanium | F2: 356964995021992 | G2: MADRIZ, JOHAN | H2: President | I2: Primera | J2: Nashville | K2: Activo | L2: 45658 | M2: 45717 | N2: Perfecto
A3: 002 | B3: 615-477-6490 | C3: AT&T | D3: Iphone | E3: A2848 256GB White Titanium | F3: 352917261435522 | G3: VILLATORO, MERARI | H3: VP | I3: Primera | J3: Nashville | K3: Activo | L3: 45658 | M3: 45717 | N3: Perfecto
A4: 003
A5: 004
A6: 005 | B6: 615-496-8278 | C6: AT&T | D6: Iphone | E6: iphone 16 PRO Max 512 GB Black Titanium | F6: 357205981304151 | G6: MADRIZ, JOHAN | H6: President | I6: Primera | J6: Nashville | K6: Activo | L6: 45658 | M6: 45717 | N6: Perfecto
A7: 006 | B7: 615-403-8760 | C7: AT&T | D7: Iphone | E7: iPhone 13 Pro Max A2484 256GB Alpine Green | F7: 356985725478830 | G7: VILLATORO, MERARI | H7: VP | I7: Primera | J7: Nashville | K7: Activo | L7: 45658 | M7: 45717 | N7: Perfecto
A8: 007 | B8: 615-417-9594 | C8: AT&T | D8: Iphone | E8: iPhone 13 Pro Max A2484 256GB Graphite | F8: 350566101441174 | G8: QUIJANO, NICOLAS | H8: CFO | I8: Primera | J8: Nashville | K8: Activo | L8: 45658 | M8: 45717 | N8: Perfecto | P8: Send
A9: 008 | B9: 615-691-3166 | C9: AT&T | D9: Iphone | E9: iPhone 13 Pro Max A2484 256GB Gold | F9: 356796480675498 | G9: QUIJANO, NICOLAS | H9: CFO | I9: Primera | J9: Nashville | K9: Activo | L9: 45658 | M9: 45717 | N9: Perfecto | P9: Send
A10: 009 | B10: 615-830-6700 | C10: AT&T | D10: Iphone | E10: Iphone 11 Pro | F10: 353247104496222 | G10: QUIJANO, NICOLAS | H10: CFO | I10: Primera | J10: Nashville | K10: Activo | L10: 45658 | M10: 45717 | N10: Perfecto | P10: Send
A11: 010 | B11: 615-626-4243 | C11: AT&T | D11: Iphone | E11: iPhone 13 Pro Max A2484 128GB Graphite | F11: 350019045940745 | G11: HERRERA MOLINA, JOSE CARLOS | H11: CEO | I11: Primera | J11: Nashville | K11: Activo | L11: 45658 | M11: 45717 | N11: Perfecto | P11: Send
A12: 011 | B12: 615-626-7710 | C12: VERIZON | D12: Ipad | E12: 10.2 IPAD 8 GEN 32GB SG | F12: 356747116811213 | G12: HERRERA MOLINA, JOSE CARLOS | H12: CEO | I12: Primera | J12: Nashville | K12: Activo | L12: 45658 | M12: 45717 | N12: Perfecto | O12: REVISADO SEPT 15 | P12: 0 | Q12: yes
A13: 012 | B13: 615-316-8577 | C13: AT&T | D13: Iphone | E13: iPhone 14 Plus A2632 128GB Midnight | F13: 353547798360296 | G13: DUQUE IYENGAR, DANIELA | H13: HR | I13: Primera | J13: Nashville | K13: Activo | L13: 45658 | M13: 45717 | N13: Perfecto | P13: Send
A14: 013 | B14: 615-971-0833 | C14: VERIZON | D14: Galaxy | E14: SAMSUNG GALAXY A23 5G UW | F14: 355978840919284 | G14: BEARD, JUSTIN O | H14: LOGISTICS WEST | I14: Tercera | J14: Memphis | K14: Activo | L14: 45658 | M14: 45717 | N14: Perfecto
A15: 014 | B15: 615-337-4949 | C15: AT&T | D15: Galaxy | E15: SAMSUNG GALAXY A23 5G UW | F15: 351700860699123 | G15: CONDE TORRES, DAVID A | H15: WAREHOUSE CENTRAL | I15: Tercera | J15: Nashville | K15: Activo | L15: 45658 | M15: 45717 | N15: Perfecto
A16: 015 | B16: 901-607-5291 | C16: AT&T | D16: Galaxy | E16: SAMSUNG GALAXY A23 5G UW | F16: 355978840897134 | G16: CORPUS, BENY A | H16: LOGISTICS CENTRAL | I16: Tercera | J16: Nashville | K16: Activo | L16: 45658 | M16: 45717 | N16: Perfecto
A17: 244 | B17: 615-390-4624 | C17: AT&T | D17: Iphone | E17: Iphone 14 Pro MaX | F17: 356485673725928 | G17: ESQUIVEL, HENRY | H17: WAREHOUSE CENTRAL | I17: Segunda | J17: Nashville | K17: Activo | L17: 45658 | M17: 45717 | N17: Perfecto
A18: 017 | B18: 615-299-3641 | C18: AT&T | D18: Motorola | E18: moto g stylus 5G XT2131-3 128GB Cosmic Emerald | F18: 355984450930637 | G18: FERNANDEZ, EDGAR | H18: LOGISTICS CENTRAL | I18: Tercera | J18: Nashville | K18: Activo | L18: 45658 | M18: 45717 | N18: Perfecto
A19: 018 | B19: 629-239-0377 | C19: AT&T | D19: Iphone | E19: iPhone 13 A2482 128GB Midnight | F19: 358091652355105 | G19: LONGA, CARMEN B | H19: LOGISTICS WEST | I19: Segunda | J19: Memphis | K19: Activo | L19: 45658 | M19: 45717 | N19: Perfecto
A20: 019 | B20: 502-558-5770 | C20: AT&T | D20: Galaxy | E20: SAMSUNG GALAXY A23 5G UW | F20: 355978840941007 | G20: MOJICA, FRANCISCO JAVIER | H20: LOGISTICS CENTRAL | I20: Tercera | J20: Nashville | K20: Activo | L20: 45658 | M20: 45717 | N20: Perfecto
A21: 020 | B21: 615-862-9402 | C21: AT&T | D21: Galaxy | E21: Galaxy A13 5G SM-A136U 64GB Black | F21: 351082120997815 | G21: BAHENA, RUDY | H21: LOGISTICS WEST | I21: Tercera | J21: Memphis | K21: Activo | L21: 45658 | M21: 45717 | N21: Perfecto
A22: 021 | B22: 629-201-9859 | C22: VERIZON | D22: Galaxy | E22: SAMSUNG GALAXY A23 5G UW | F22: 355978840948754 | G22: LAMA, DENIS | H22: LOGISTICS NORTH | I22: Tercera | J22: Cincinnatti | K22: Activo | L22: 45658 | M22: 45717 | N22: Perfecto
A23: 022 | B23: 901-585-9984 | C23: AT&T | D23: Galaxy | E23: SAMSUNG GALAXY A23 5G UW | F23: 355978840945446 | G23: DE LA TORRE, LUIS G | H23: LOGISTICS WEST | I23: Tercera | J23: Memphis | K23: Activo | L23: 45658 | M23: 45717 | N23: Perfecto
A24: 023 | B24: 615-598-2524 | C24: VERIZON | D24: Galaxy | E24: SAMSUNG GALAXY A23 5G UW | F24: 355978840949059 | G24: SALGUERO, RONALD | H24: LOGISTIC SOUTH | I24: Tercera | J24: Birmingham | K24: Activo | L24: 45762 | M24: 45762 | N24: Perfecto | P24: 0 | Q24: yes | S24: CAMBIAR NOMBRE VERIZON
A25: 024 | B25: 615-795-8193 | C25: AT&T | D25: Galaxy | E25: SAMSUNG GALAXY A13 | F25: 351082120939429 | G25: REMBERT, ANTORIUS DAVUN | H25: LOGISTICS SOUTH | I25: Tercera | J25: Birmingham | K25: Activo | L25: 45658 | M25: 45717 | N25: Perfecto
A26: 025 | B26: 502-974-3915 | C26: AT&T | D26: Iphone | E26: IPHONE13 128GB MDN NVZ ATT | F26: 358091652696490 | G26: ARMES, CLAUDIA | H26: SALES NORTH | I26: Tercera | J26: Cincinnatti | K26: Activo | L26: 45658 | M26: 45717 | N26: Perfecto
A27: 026 | B27: 615-417-0015 | C27: AT&T | D27: Iphone | E27: iPhone 13 A2482 128GB Midnight | F27: 354739183440614 | G27: BARAJAS, JESSICA | H27: SALES NORTH | I27: Tercera | J27: Cincinnatti | K27: Activo | L27: 45658 | M27: 45717 | N27: Perfecto
A28: 027 | B28: 615-417-2841 | C28: VERIZON | D28: Ipad | E28: 10.2 IPAD 8 GEN 32GB SG | F28: 356749110441328 | G28: BARAJAS, JESSICA | H28: SALES NORTH | I28: Tercera | J28: Cincinnatti | K28: Activo | L28: 45658 | M28: 45717 | N28: Perfecto | P28: 0 | Q28: yes
A29: 028 | B29: 615-456-2536 | C29: AT&T | D29: Iphone | E29: IPHONE13 128GB MDN NVZ ATT | F29: 358091652064830 | G29: CABANZO, DANNY | H29: SALES CENTRAL | I29: Tercera | J29: Nashville | K29: Activo | L29: 45658 | M29: 45717 | N29: Perfecto
A30: 029 | B30: 615-840-1465 | C30: VERIZON | D30: Ipad | E30: 10.2 IPAD 8 GEN 32GB SG | F30: 356747112510629 | G30: CABANZO, DANNY | H30: SALES CENTRAL | I30: Tercera | J30: Nashville | K30: Activo | L30: 45658 | M30: 45717 | N30: Perfecto
A31: 030 | B31: 314-580-3315 | C31: AT&T | D31: Iphone | E31: IPHONE13 128GB MDN NVZ ATT | F31: 358091652243426 | G31: CAICEDO, VICTOR M | H31: SALES WEST | I31: Tercera | J31: Memphis | K31: Activo | L31: 45658 | M31: 45717 | N31: Perfecto
A32: 031 | B32: 615-840-3639 | C32: VERIZON | D32: Ipad | E32: IP 10.9 64 SLV 22 | F32: 355939971952932 | G32: CAICEDO, VICTOR M | H32: SALES WEST | I32: Tercera | J32: Memphis | K32: Activo | L32: 45658 | M32: 45717 | N32: Perfecto | O32: REVISADO SEPT 15 | P32: 0 | Q32: yes | R32: REVISAR QUIEN LO TIENE
A33: 032 | B33: 629-729-3287 | C33: AT&T | D33: Ipad | E33: iPad 9th Gen. (2021) A2603 64GB Space Gray | F33: 357652533185275 | G33: CHANCHAMIRE, RAFAEL A | H33: SALES WEST | I33: Tercera | J33: Memphis | K33: Activo | L33: 45658 | M33: 45717 | N33: Perfecto
A34: 033 | B34: 901-649-5850 | C34: AT&T | D34: Iphone | E34: iPhone 14 A2649 128GB Midnight | F34: 354633859827800 | G34: CHANCHAMIRE, RAFAEL A | H34: SALES WEST | I34: Tercera | J34: Memphis | K34: Activo | L34: 45658 | M34: 45717 | N34: Perfecto
A35: 034 | B35: 513-675-0865 | C35: AT&T | D35: Iphone | E35: IPHONE13 128GB MDN NVZ ATT | F35: 350555043090645 | G35: CORDERO, IRIS | H35: SALES NORTH | I35: Tercera | J35: Cincinnatti | K35: Activo | L35: 45658 | M35: 45717 | N35: Perfecto
A36: 035 | B36: 615-648-0861 | C36: VERIZON | D36: Ipad | E36: IPAD WIFI 32GB GOLD | F36: 359455081195458 | G36: CORDERO, IRIS | H36: SALES NORTH | I36: Tercera | J36: Cincinnatti | K36: Activo | L36: 45658 | M36: 45717 | N36: Perfecto | P36: 0 | Q36: yes
A37: 036 | B37: 256-631-4188 | C37: AT&T | D37: Ipad | E37: iPad 9th Gen. (2021) A2603 64GB Space Gray | F37: 351036279350523 | G37: FLORES, JOSE DANIEL | H37: SALES SOUTH | I37: Tercera | J37: Birmingham | K37: Activo | L37: 45658 | M37: 45717 | N37: Perfecto
A38: 037 | B38: 256-724-1530 | C38: AT&T | D38: Iphone | E38: iPhone 13 A2482 128GB Midnight | F38: 359346671900953 | G38: FLORES, JOSE DANIEL | H38: SALES SOUTH | I38: Tercera | J38: Birmingham | K38: Activo | L38: 45658 | M38: 45717 | N38: Perfecto
A39: 038 | B39: 205-767-8090 | C39: AT&T | D39: Iphone | E39: IPHONE13 128GB MDN NVZ ATT | F39: 358469523459878 | G39: GUERRERO, JESUS | H39: SALES SOUTH | I39: Segunda | J39: Birmingham | K39: Activo | L39: 45658 | M39: 45717 | N39: Perfecto
A40: 039 | B40: 615-840-1479 | C40: VERIZON | D40: Ipad | E40: IPAD 9.7 128GB SILVER VZ | F40: 353036091434008 | G40: GUERRERO, JESUS | H40: SALES SOUTH | I40: Segunda | J40: Birmingham | K40: Activo | L40: 45658 | M40: 45717 | N40: Perfecto
A41: 040 | B41: 629-256-6967 | C41: AT&T | D41: Ipad | E41: iPad 9th Gen. (2021) A2603 64GB Space Gray | F41: 359552541402290 | G41: GUTIERREZ TOVAR, YNGEL J | H41: SALES CENTRAL | I41: Tercera | J41: Nashville | K41: Activo | L41: 45658 | M41: 45717 | N41: Perfecto
A42: 041 | B42: 314-309-4058 | C42: AT&T | D42: Iphone | E42: iPhone 13 A2482 128GB Midnight | F42: 359673359617900 | G42: LOPEZ, YESENIA | H42: SALES WEST | I42: Tercera | J42: Memphis | K42: Activo | L42: 45658 | M42: 45717 | N42: Perfecto
A43: 042 | B43: 615-586-0725 | C43: AT&T | D43: Ipad | E43: iPad 9th Gen. (2021) A2603 64GB Space Gray | F43: 350698365612057 | G43: LOPEZ, YESENIA | H43: SALES WEST | I43: Tercera | J43: Memphis | K43: Activo | L43: 45658 | M43: 45717 | N43: Perfecto
A44: 043 | B44: 615-626-3208 | C44: AT&T | D44: Iphone | E44: IPHONE13 128GB MDN NVZ ATT | F44: 358091652946366 | G44: LOPEZ, ALEJANDRA C | H44: SALES WEST | I44: Segunda | J44: Memphis | K44: Activo | L44: 45658 | M44: 45717 | N44: Perfecto
A45: 044 | B45: 901-464-6471 | C45: AT&T | D45: Iphone | E45: IPHONE13 128GB MDN NVZ ATT | F45: 358469523212749 | G45: MADRIGAL GARCIA, HELEN C | H45: SALES NORTH | I45: Segunda | J45: Cincinnatti | K45: Activo | L45: 45658 | M45: 45717 | N45: Perfecto
A46: 045 | B46: 901-467-5902 | C46: AT&T | D46: Ipad | E46: iPad 9th Gen. (2021) A2603 64GB Space Gray | F46: 351036279079825 | G46: MADRIGAL GARCIA, HELEN C | H46: SALES NORTH | I46: Segunda | J46: Cincinnatti | K46: Activo | L46: 45658 | M46: 45717 | N46: Perfecto
A47: 046 | B47: 615-626-2756 | C47: AT&T | D47: Iphone | E47: IPHONE13 128GB MDN NVZ ATT | F47: 358891503498404 | G47: NAJERA, LIZET | H47: SALES NORTH | I47: Tercera | J47: Cincinnatti | K47: Activo | L47: 45658 | M47: 45717 | N47: Perfecto
A48: 047 | B48: 615-920-4092 | C48: VERIZON | D48: Ipad | E48: 10.2 IPAD 8 GEN 32GB SG | F48: 356747113348383 | G48: NAJERA, LIZET | H48: SALES NORTH | I48: Tercera | J48: Cincinnatti | K48: Activo | L48: 45658 | M48: 45717 | N48: Perfecto
A49: 048 | B49: 615-804-0516 | C49: AT&T | D49: Iphone | E49: IPHONE13 128GB MDN NVZ ATT | F49: 358091652425510 | G49: REYES, YULIN | H49: SALES CENTRAL | I49: Tercera | J49: Nashville | K49: Activo | L49: 45658 | M49: 45717 | N49: Perfecto
A50: 049 | B50: 615-806-3926 | C50: VERIZON | D50: Ipad | E50: 10.2 IPAD 8 GEN 32GB SG | F50: 356747116798246 | G50: REYES, YULIN | H50: SALES CENTRAL | I50: Tercera | J50: Nashville | K50: Activo | L50: 45658 | M50: 45717 | N50: Perfecto | P50: 0 | Q50: YES
A51: 050 | B51: 615-812-4735 | C51: VERIZON | D51: Ipad | E51: 10.2 IPAD 8 GEN 32GB SG | F51: 356747116975323 | G51: ROA, INGRID MARCELA | H51: SALES SOUTH | I51: Tercera | J51: Birmingham | K51: Activo | L51: 45658 | M51: 45717 | N51: Perfecto
A52: 051 | B52: 615-854-5649 | C52: AT&T | D52: Iphone | E52: IPHONE13 128GB MDN NVZ ATT | F52: 356815603426132 | G52: ROA, INGRID MARCELA | H52: SALES SOUTH | I52: Tercera | J52: Birmingham | K52: Activo | L52: 45658 | M52: 45717 | N52: Perfecto
A53: 052 | B53: 865-334-0516 | C53: AT&T | D53: Iphone | E53: iPhone 14 Plus A2632 128GB Midnight | F53: 353696746318607 | G53: ROJAS, FABIOLA V | H53: MERCHANDISER CENTRAL | I53: Tercera | J53: Nashville | K53: Activo | L53: 45658 | M53: 45717 | N53: Perfecto
A54: 053 | B54: 317-500-7156 | C54: AT&T | D54: Iphone | E54: IPHONE13 128GB MDN NVZ ATT | F54: 358091652408037 | G54: SORIANO, NAYELY | H54: SALES NORTH | I54: Tercera | J54: Cincinnatti | K54: Activo | L54: 45658 | M54: 45717 | N54: Perfecto
A55: 054 | B55: 615-881-2222 | C55: VERIZON | D55: Ipad | E55: IPAD 9GEN 64 GRAY | F55: 355254195678622 | G55: SORIANO, NAYELY | H55: SALES NORTH | I55: Tercera | J55: Cincinnatti | K55: DESCONECTADA | L55: 45658 | M55: 45717 | N55: Perfecto | O55: DESCONECTADA Y PASADA A ATT | S55: desconectarla
A56: 055 | B56: 615-945-4365 | C56: AT&T | D56: Ipad | E56: iPad 9th Gen. (2021) A2603 64GB Space Gray | F56: 359552545614718 | G56: TELLO, IVAN E | H56: SALES CENTRAL | I56: Tercera | J56: Nashville | K56: Activo | L56: 45658 | M56: 45717 | N56: Perfecto
A57: 056 | B57: 615-730-3104 | C57: AT&T | D57: Iphone | E57: iPhone 14 Plus A2632 128GB Midnight | F57: 353547795738981 | G57: TELLO, IVAN E | H57: SALES CENTRAL | I57: Tercera | J57: Nashville | K57: Activo | L57: 45658 | M57: 45717 | N57: Perfecto
A58: 057 | B58: 615-812-1894 | C58: VERIZON | D58: Ipad | E58: IPAD 9GEN 64 GRAY | F58: 357883402867509 | G58: TORREALBA TORRES, CAROLINA | H58: SALES WEST | I58: Tercera | J58: Memphis | K58: DESCONECTADA | L58: 45658 | M58: 45717 | N58: Perfecto
A59: 058 | B59: 615-854-5797 | C59: AT&T | D59: Iphone | E59: IPHONE13 128GB MDN NVZ ATT | F59: 350980291513736 | G59: TORREALBA TORRES, CAROLINA | H59: SALES WEST | I59: Tercera | J59: Memphis | K59: Activo | L59: 45658 | M59: 45717 | N59: Perfecto
A60: 059 | B60: 615-878-0405 | C60: AT&T | G60: TORRES, LUIS | H60: MERCHANDISER NORTH | I60: Tercera | J60: Cincinnatti | O60: Asignar o ver si tien asignado
A61: 060 | B61: 615-714-1323 | C61: VERIZON | D61: Ipad | E61: IPAD 9GEN 64 GRAY | F61: 357652533500689 | G61: TOVAR, ZULLYMAR | H61: SALES CENTRAL | I61: Segunda | J61: Nashville | K61: Activo | L61: 45658 | M61: 45717 | N61: Perfecto | P61: 0 | Q61: yes
A62: 061 | B62: 865-396-3528 | C62: AT&T | D62: Ipad | E62: iPad 9th Gen. (2021) A2603 64GB Space Gray | F62: 359552541604085 | G62: VELIZ, CARLOS A | H62: SALES CENTRAL | I62: Tercera | J62: Nashville | K62: Activo | L62: 45658 | M62: 45717 | N62: Perfecto
A63: 062 | B63: 629-345-1182 | C63: AT&T | D63: Ipad | E63: iPad 9th Gen. (2021) A2603 64GB Space Gray | F63: 357652530925137 | G63: LACRUZ, ROSMARY | H63: SALES WEST | I63: Tercera | J63: Memphis | K63: Activo | L63: 45658 | M63: 45717 | N63: Perfecto
A64: 063 | B64: 601-910-8492 | C64: AT&T | D64: Iphone | E64: IPHONE12 64G BLK-E NVZ ATT | F64: 351139862096055 | G64: LACRUZ, ROSMARY | H64: SALES WEST | I64: Tercera | J64: Memphis | K64: Activo | L64: 45658 | M64: 45717 | N64: Perfecto
A65: 064 | B65: 901-581-6397 | C65: AT&T | D65: Iphone | E65: iPhone 13 A2482 128GB Midnight | F65: 358091652248979 | G65: AVALOS, JOSEFINA | H65: SALES WEST | I65: Tercera | J65: Memphis | K65: Activo | L65: 45658 | M65: 45717 | N65: Perfecto
A66: 065 | B66: 901-275-9469 | C66: VERIZON | D66: Ipad | E66: IPAD 9GEN 64 GRAY | F66: 359552540047567 | G66: AVALOS, JOSEFINA | H66: SALES WEST | I66: Tercera | J66: Memphis | K66: Activo | L66: 45658 | M66: 45717 | N66: Perfecto | P66: 0 | Q66: yes
A67: 066 | B67: 615-944-5380 | C67: AT&T | D67: Ipad | E67: iPad 9th Gen. (2021) A2603 64GB Space Gray | F67: 359552545484377 | G67: PALENCIA RODRIGUEZ, LEONARDO R | H67: SALES CENTRAL | I67: Tercera | J67: Nashville | K67: Activo | L67: 45658 | M67: 45717 | N67: Perfecto
A68: 067 | B68: 615-828-8926 | C68: AT&T | D68: Iphone | E68: iPhone 14 Plus A2632 128GB Midnight | F68: 352820547105259 | G68: PALENCIA RODRIGUEZ, LEONARDO R | H68: SALES CENTRAL | I68: Tercera | J68: Nashville | K68: Activo | L68: 45658 | M68: 45717 | N68: Perfecto
A69: 068 | B69: 615-203-1637 | C69: VERIZON | D69: Ipad | E69: 10.2 IPAD 8 GEN 32GB SG | F69: 356750112980248 | G69: PEREZ HERNANDEZ, NAYRE | H69: SALES CENTRAL | I69: Tercera | J69: Nashville | K69: Activo | L69: 45658 | M69: 45717 | N69: Perfecto | P69: 0 | Q69: Yes
A70: 069 | B70: 615-840-0789 | C70: AT&T | D70: Iphone | E70: IPHONE13 128GB MDN NVZ ATT | F70: 350980291914207 | G70: PEREZ HERNANDEZ, NAYRE | H70: SALES CENTRAL | I70: Tercera | J70: Nashville | K70: Activo | L70: 45658 | M70: 45717 | N70: Perfecto
A71: 070 | B71: 615-969-5642 | C71: AT&T | D71: Iphone | E71: iPhone 13 A2482 128GB Midnight | F71: 350980291790359 | G71: SOLIS SAN ANDRES, KARLA G | H71: SALES WEST | I71: Tercera | J71: Memphis | K71: Activo | L71: 45658 | M71: 45717 | N71: Perfecto
A72: 071 | B72: 901-275-5428 | C72: AT&T | D72: Iphone | E72: IPHONE13 128GB MDN NVZ ATT | F72: 358091652927259 | G72: RODRIGUEZ, VERUUZKO | H72: SALES CENTRAL | I72: Segunda | J72: Nashville | K72: Activo | L72: 45658 | M72: 45717 | N72: Perfecto
A73: 072 | B73: 423-321-4014 | C73: AT&T | D73: Iphone | E73: IPHONE13 128GB MDN NVZ ATT | F73: 358091652253870 | G73: CORADO, JUAN CARLOS | H73: SALES SOUTH | I73: Tercera | J73: Birmingham | K73: Activo | L73: 45658 | M73: 45717 | N73: Perfecto
A74: 073 | B74: 901-568-5966 | C74: VERIZON | D74: Ipad | E74: IPAD 9.7 32GB SPACE GRAY VZ | F74: 354887094162445 | G74: CORADO, JUAN CARLOS | H74: SALES SOUTH | I74: Tercera | J74: Birmingham | K74: Activo | L74: 45658 | M74: 45717 | N74: Perfecto | P74: 0 | Q74: yes
A75: 074 | B75: 615-207-2464 | C75: AT&T | D75: Iphone | E75: IPHONE13 128GB MDN NVZ ATT | F75: 355701905876441 | G75: CABRERA, OSMAN A | H75: SALES CENTRAL | I75: Tercera | J75: Nashville | K75: Activo | L75: 45658 | M75: 45717 | N75: Perfecto
A76: 075 | B76: 205-527-8021 | C76: AT&T | D76: Iphone | E76: iPhone 13 A2482 128GB Midnight | F76: 359673358192681 | G76: MAITA, JOSE | H76: SALES SOUTH | I76: Tercera | J76: Birmingham | K76: Activo | L76: 45658 | M76: 45717 | N76: Perfecto
A77: 076 | B77: 615-586-4787 | C77: AT&T | D77: Ipad | E77: iPad 9th Gen. (2021) A2603 64GB Space Gray | F77: 350698365491957 | G77: MAITA, JOSE | H77: SALES SOUTH | I77: Tercera | J77: Birmingham | K77: Activo | L77: 45658 | M77: 45717 | N77: Perfecto
A78: 077 | B78: 629-729-3294 | C78: AT&T | D78: Ipad | E78: iPad 9th Gen. (2021) A2603 64GB Space Gray | F78: 357652533102288 | G78: SHINE, EDILIA D | H78: SALES NORTH | I78: Tercera | J78: Cincinnatti | K78: Activo | L78: 45658 | M78: 45717 | N78: Perfecto
A79: 078 | B79: 463-209-9259 | C79: AT&T | D79: Iphone | E79: iPhone 13 A2482 128GB Midnight | F79: 358469523073430 | G79: SHINE, EDILIA D | H79: SALES NORTH | I79: Tercera | J79: Cincinnatti | K79: Activo | L79: 45658 | M79: 45717 | N79: Perfecto
A80: 079 | B80: 629-345-1645 | C80: AT&T | D80: Iphone | E80: iPhone 14 A2649 128GB Midnight | F80: 355241389009441 | G80: GARCIA, RADDY | H80: SALES NORTH | I80: Tercera | J80: Cincinnatti | K80: Activo | L80: 45658 | M80: 45717 | N80: Perfecto
A81: 080 | B81: 629-345-1728 | C81: AT&T | D81: Ipad | E81: iPad 9th Gen. (2021) A2603 64GB Space Gray | F81: 356134571555397 | G81: GARCIA, RADDY | H81: SALES NORTH | I81: Tercera | J81: Cincinnatti | K81: Activo | L81: 45658 | M81: 45717 | N81: Perfecto
A82: 081 | B82: 615-426-4622 | C82: AT&T | D82: Iphone | E82: iPhone 13 A2482 128GB Midnight | F82: 358091652370831 | G82: PATINO, ZEDERICK | H82: MERCHANDISER CENTRAL | I82: Tercera | J82: Nashville | K82: Activo | L82: 45658 | M82: 45717 | N82: Perfecto
A83: 082 | B83: 629-345-1381 | C83: AT&T | D83: Iphone | E83: iPhone 14 A2649 128GB Midnight | F83: 355241387671119 | G83: RIVERO, LUIS MARIANO | H83: SALES CENTRAL | I83: Tercera | J83: Nashville | K83: Activo | L83: 45658 | M83: 45717 | N83: Perfecto
A84: 083 | B84: 629-345-1574 | C84: AT&T | D84: Ipad | E84: iPad 9th Gen. (2021) A2603 64GB Space Gray | F84: 356134571624649 | G84: RIVERO, LUIS MARIANO | H84: SALES CENTRAL | I84: Tercera | J84: Nashville | K84: Activo | L84: 45658 | M84: 45717 | N84: Perfecto
A85: 084 | B85: 629-345-1642 | C85: AT&T | D85: Iphone | E85: iPhone 14 A2649 128GB Midnight | F85: 355241389008385 | G85: CALDERON, PILAR ESTRADA | H85: MERCHANDISER SOUTH | I85: Tercera | J85: Birmingham | K85: Activo | L85: 45658 | M85: 45717 | N85: Perfecto
A86: 085 | B86: 629-345-1705 | C86: AT&T | D86: Ipad | E86: iPad 9th Gen. (2021) A2603 64GB Space Gray | F86: 356134571250718 | G86: CALDERON, PILAR ESTRADA | H86: MERCHANDISER SOUTH | I86: Tercera | J86: Birmingham | K86: Activo | L86: 45658 | M86: 45717 | N86: Perfecto
A87: 086 | B87: 615-961-2627 | C87: VERIZON | D87: Ipad | E87: IPAD 9GEN 64 GRAY | F87: 350698362572957 | G87: LUCIO FLORES, JOSE ANGEL | H87: SALES NORTH | I87: Tercera | J87: Cincinnatti | K87: Activo | L87: 45658 | M87: 45717 | N87: Perfecto
A88: 246 | B88: 901-713-7796 | C88: AT&T | D88: Iphone | E88: Iphone 14 | F88: 354807370356289 | G88: FERREIRA, ANA CAROLINA | H88: MERCHANDISER WEST | I88: Tercera | J88: Memphis | K88: Activo | L88: 45658 | M88: 45717 | N88: Perfecto
A89: 088 | B89: 513-720-1147 | C89: AT&T | D89: Iphone | E89: iPhone 14 Plus A2632 128GB Midnight | F89: 353696749029201 | G89: ALVAREZ PALOMARES M, PAULA MAYREN | H89: MERCHANDISER NORTH | I89: Tercera | J89: Cincinnatti | K89: Activo | L89: 45658 | M89: 45717 | N89: Perfecto
A90: 089 | B90: 615-587-3400 | C90: VERIZON | D90: Iphone | E90: IPHONE12P 128G GRP NVZ TMO | F90: 351001682973048 | G90: DUARTE, ANGELA | H90: SALES CENTRAL | I90: Tercera | J90: Nashville | K90: Activo | L90: 45658 | M90: 45717 | N90: Perfecto
A91: 090 | B91: 615-961-0855 | C91: VERIZON | D91: Ipad | E91: IPAD 9GEN 64 GRAY | F91: 357883402125478 | G91: DUARTE, ANGELA | H91: SALES CENTRAL | I91: Tercera | J91: Nashville | K91: Activo | L91: 45658 | M91: 45717 | N91: Perfecto | O91: REVISADO SEPT 15 | P91: 0 | Q91: YES
A92: 091 | B92: 615-310-9970 | C92: AT&T | D92: Ipad | E92: IPAD 9GEN 64 GRAY | F92: 357883402696494 | G92: CARDOZO, ALBERT YVAN | H92: SALES RITEFILL DSD CENTRAL | I92: Tercera | J92: Nashville | K92: Activo | L92: 45658 | M92: 45717 | N92: Perfecto
A93: 092 | B93: 615-939-8241 | C93: AT&T | D93: Iphone | E93: IPHONE 12 GEN NVZW | F93: 350839224004728 | G93: CARDOZO, ALBERT YVAN | H93: SALES RITEFILL DSD CENTRAL | I93: Tercera | J93: Nashville | K93: Activo | L93: 45658 | M93: 45717 | N93: Perfecto
A94: 093 | B94: 615-589-4199 | C94: AT&T | D94: Iphone | E94: iPhone 13 A2482 128GB Midnight | F94: 351829684067157 | G94: PELAEZ, ELIZABETH | H94: SALES CENTRAL | I94: Tercera | J94: Nashville | K94: Activo | L94: 45658 | M94: 45717 | N94: Perfecto
A95: 094 | B95: 615-728-2262 | C95: VERIZON | D95: Galaxy | E95: SAMSUNG GALAXY A23 5G UW | F95: 355978840939803 | G95: PELAEZ, ELIZABETH | H95: SALES CENTRAL | I95: Tercera | J95: Nashville | K95: Activo | L95: 45658 | M95: 45717 | N95: Perfecto | P95: 9 | Q95: yes
A96: 095 | B96: 615-589-2741 | C96: AT&T | D96: Ipad | E96: iPad 9th Gen. (2021) A2603 64GB Space Gray | F96: 350698365094306 | G96: SILVA R, ROSMARY JOSE | H96: SALES SOUTH | I96: Tercera | J96: Birmingham | K96: Activo | L96: 45658 | M96: 45717 | N96: Perfecto
A97: 096 | B97: 205-529-6296 | C97: AT&T | D97: Iphone | E97: IPHONE13 128GB MDN NVZ ATT | F97: 359673359488781 | G97: SILVA R, ROSMARY JOSE | H97: SALES SOUTH | I97: Tercera | J97: Birmingham | K97: Activo | L97: 45658 | M97: 45717 | N97: Perfecto
A98: 097 | B98: 501-773-3738 | C98: AT&T | D98: Ipad | E98: iPad 9th Gen. (2021) A2603 64GB Space Gray | F98: 359552541123334 | G98: VILLAVICENCIO, ARTURO J | H98: SALES WEST | I98: Tercera | J98: Memphis | K98: Activo | L98: 45658 | M98: 45717 | N98: Perfecto | O98: Confirmar quien tiene este IPAD SI NAIROVI O EL
A99: 098 | B99: 615-319-8134 | C99: VERIZON | D99: Galaxy | E99: SAMSUNG GALAXY A23 5G UW | F99: 355978840923146 | G99: HERNANDEZ ARREGUIN, ANA AIDET | H99: HR | I99: Tercera | J99: Nashville | K99: Activo | L99: 45658 | M99: 45717 | N99: Perfecto | O99: REVISADO SEPT 15 | P99: 0 | Q99: YES
A100: 099 | B100: 629-264-3070 | C100: AT&T | D100: Iphone | E100: iPhone 13 A2482 128GB Midnight | F100: 357084344468932 | G100: BRITO SALAZAR, RICARDO JOSE | H100: HR | I100: Tercera | J100: Nashville | K100: Activo | L100: 45658 | M100: 45717 | N100: Perfecto | P100: Send
...

Sheet Sheet5
A1: LINEA MOVIL | B1: Proveedor | C1: EQUIPMENT TYPE | D1: MODEL | E1: IMEI | F1: Usuario Asignado | G1: CECO | H1: LINEA | I1: LOCATION | J1: Estado | K1: Fecha de asignacion | L1: Fecha de ultima revision | M1: Condicion de equipo | N1: Comentarios | O1: etf | P1: TRANSFERENCIA DE PIN | S1: Migracion
A2: 615-626-7710 | B2: VERIZON | C2: Ipad | D2: 10.2 IPAD 8 GEN 32GB SG | E2: 356747116811213 | F2: HERRERA MOLINA, JOSE CARLOS | G2: CEO | H2: Primera | I2: Nashville | J2: Activo | K2: 45658 | L2: 45717 | M2: Perfecto | N2: REVISADO SEPT 15 | O2: 0 | P2: yes
A3: 615-971-0833 | B3: VERIZON | C3: Galaxy | D3: SAMSUNG GALAXY A23 5G UW | E3: 355978840919284 | F3: BEARD, JUSTIN O | G3: LOGISTICS WEST | H3: Tercera | I3: Memphis | J3: Activo | K3: 45658 | L3: 45717 | M3: Perfecto
A4: 629-201-9859 | B4: VERIZON | C4: Galaxy | D4: SAMSUNG GALAXY A23 5G UW | E4: 355978840948754 | F4: LAMA, DENIS | G4: LOGISTICS NORTH | H4: Tercera | I4: Cincinnatti | J4: Activo | K4: 45658 | L4: 45717 | M4: Perfecto
A5: 615-598-2524 | B5: VERIZON | C5: Galaxy | D5: SAMSUNG GALAXY A23 5G UW | E5: 355978840949059 | F5: SALGUERO, RONALD | G5: LOGISTIC SOUTH | H5: Tercera | I5: Birmingham | J5: Activo | K5: 45762 | L5: 45762 | M5: Perfecto | O5: 0 | P5: yes | R5: CAMBIAR NOMBRE VERIZON
A6: 615-417-2841 | B6: VERIZON | C6: Ipad | D6: 10.2 IPAD 8 GEN 32GB SG | E6: 356749110441328 | F6: BARAJAS, JESSICA | G6: SALES NORTH | H6: Tercera | I6: Cincinnatti | J6: Activo | K6: 45658 | L6: 45717 | M6: Perfecto | O6: 0 | P6: yes
A7: 615-840-1465 | B7: VERIZON | C7: Ipad | D7: 10.2 IPAD 8 GEN 32GB SG | E7: 356747112510629 | F7: CABANZO, DANNY | G7: SALES CENTRAL | H7: Tercera | I7: Nashville | J7: Activo | K7: 45658 | L7: 45717 | M7: Perfecto
A8: 615-648-0861 | B8: VERIZON | C8: Ipad | D8: IPAD WIFI 32GB GOLD | E8: 359455081195458 | F8: CORDERO, IRIS | G8: SALES NORTH | H8: Tercera | I8: Cincinnatti | J8: Activo | K8: 45658 | L8: 45717 | M8: Perfecto | O8: 0 | P8: yes
A9: 615-840-1479 | B9: VERIZON | C9: Ipad | D9: IPAD 9.7 128GB SILVER VZ | E9: 353036091434008 | F9: GUERRERO, JESUS | G9: SALES SOUTH | H9: Segunda | I9: Birmingham | J9: Activo | K9: 45658 | L9: 45717 | M9: Perfecto
A10: 615-806-3926 | B10: VERIZON | C10: Ipad | D10: 10.2 IPAD 8 GEN 32GB SG | E10: 356747116798246 | F10: REYES, YULIN | G10: SALES CENTRAL | H10: Tercera | I10: Nashville | J10: Activo | K10: 45658 | L10: 45717 | M10: Perfecto | O10: 0 | P10: YES
A11: 615-812-4735 | B11: VERIZON | C11: Ipad | D11: 10.2 IPAD 8 GEN 32GB SG | E11: 356747116975323 | F11: ROA, INGRID MARCELA | G11: SALES SOUTH | H11: Tercera | I11: Birmingham | J11: Activo | K11: 45658 | L11: 45717 | M11: Perfecto
A12: 615-714-1323 | B12: VERIZON | C12: Ipad | D12: IPAD 9GEN 64 GRAY | E12: 357652533500689 | F12: TOVAR, ZULLYMAR | G12: SALES CENTRAL | H12: Segunda | I12: Nashville | J12: Activo | K12: 45658 | L12: 45717 | M12: Perfecto | O12: 0 | P12: yes
A13: 901-275-9469 | B13: VERIZON | C13: Ipad | D13: IPAD 9GEN 64 GRAY | E13: 359552540047567 | F13: AVALOS, JOSEFINA | G13: SALES WEST | H13: Tercera | I13: Memphis | J13: Activo | K13: 45658 | L13: 45717 | M13: Perfecto | O13: 0 | P13: yes
A14: 615-203-1637 | B14: VERIZON | C14: Ipad | D14: 10.2 IPAD 8 GEN 32GB SG | E14: 356750112980248 | F14: PEREZ HERNANDEZ, NAYRE | G14: SALES CENTRAL | H14: Tercera | I14: Nashville | J14: Activo | K14: 45658 | L14: 45717 | M14: Perfecto | O14: 0 | P14: Yes
A15: 901-568-5966 | B15: VERIZON | C15: Ipad | D15: IPAD 9.7 32GB SPACE GRAY VZ | E15: 354887094162445 | F15: CORADO, JUAN CARLOS | G15: SALES SOUTH | H15: Tercera | I15: Birmingham | J15: Activo | K15: 45658 | L15: 45717 | M15: Perfecto | O15: 0 | P15: yes
A16: 615-961-2627 | B16: VERIZON | C16: Ipad | D16: IPAD 9GEN 64 GRAY | E16: 350698362572957 | F16: LUCIO FLORES, JOSE ANGEL | G16: SALES NORTH | H16: Tercera | I16: Cincinnatti | J16: Activo | K16: 45658 | L16: 45717 | M16: Perfecto
A17: 615-587-3400 | B17: VERIZON | C17: Iphone | D17: IPHONE12P 128G GRP NVZ TMO | E17: 351001682973048 | F17: DUARTE, ANGELA | G17: SALES CENTRAL | H17: Tercera | I17: Nashville | J17: Activo | K17: 45658 | L17: 45717 | M17: Perfecto
A18: 615-961-0855 | B18: VERIZON | C18: Ipad | D18: IPAD 9GEN 64 GRAY | E18: 357883402125478 | F18: DUARTE, ANGELA | G18: SALES CENTRAL | H18: Tercera | I18: Nashville | J18: Activo | K18: 45658 | L18: 45717 | M18: Perfecto | N18: REVISADO SEPT 15 | O18: 0 | P18: YES
A19: 615-728-2262 | B19: VERIZON | C19: Galaxy | D19: SAMSUNG GALAXY A23 5G UW | E19: 355978840939803 | F19: PELAEZ, ELIZABETH | G19: SALES CENTRAL | H19: Tercera | I19: Nashville | J19: Activo | K19: 45658 | L19: 45717 | M19: Perfecto | O19: 9 | P19: yes
A20: 615-319-8134 | B20: VERIZON | C20: Galaxy | D20: SAMSUNG GALAXY A23 5G UW | E20: 355978840923146 | F20: HERNANDEZ ARREGUIN, ANA AIDET | G20: HR | H20: Tercera | I20: Nashville | J20: Activo | K20: 45658 | L20: 45717 | M20: Perfecto | N20: REVISADO SEPT 15 | O20: 0 | P20: YES
A21: 615-651-0245 | B21: VERIZON | C21: Ipad | D21: IPAD 7TH GEN 32GB GRAY VZ | E21: 353205104482748 | F21: RODRIGUEZ, VERUUZKO | G21: SALES CENTRAL | H21: Segunda | I21: Nashville | J21: Activo | K21: 45658 | L21: 45717 | M21: Perfecto
A22: 615-948-1111 | B22: VERIZON | C22: Galaxy | D22: SAMSUNG GALAXY A23 5G UW | E22: 355978840945222 | F22: WATSON, JORDAN MATTHEW | G22: LOGISTICS NORTH | H22: Tercera | I22: Cincinnatti | J22: Activo | K22: 45658 | L22: 45717 | M22: Perfecto | N22: Revisar si esta en Verizon o ATT? | O22: 0 | P22: YES
A23: 812-893-5245 | B23: VERIZON | C23: Iphone | D23: IPHONE13 128GB MDN NVZ ATT | E23: 358091652066132 | F23: RIOS BLANDON, AUGUSTO C | G23: SALES NORTH | H23: Tercera | I23: Cincinnatti | J23: Activo | K23: 45658 | L23: 45717 | M23: Perfecto
A24: 513-781-1073 | B24: VERIZON | D24: Samsung Galaxy S21SG | F24: Cesar Nunez | N24: REVISADO SEPT 15 | O24: 0
A25: 615-840-3639 | B25: VERIZON | C25: Ipad | D25: IP 10.9 64 SLV 22 | E25: 355939971952932 | F25: CAICEDO, VICTOR M | G25: SALES WEST | H25: Tercera | I25: Memphis | J25: Activo | K25: 45658 | L25: 45717 | M25: Perfecto | N25: REVISADO SEPT 15 | O25: 0 | P25: yes | Q25: REVISAR QUIEN LO TIENE
A26: 615-881-2222 | B26: VERIZON | C26: Ipad | D26: IPAD 9GEN 64 GRAY | E26: 355254195678622 | F26: SORIANO, NAYELY | G26: SALES NORTH | H26: Tercera | I26: Cincinnatti | J26: DESCONECTADA | K26: 45658 | L26: 45717 | M26: Perfecto | N26: DESCONECTADA Y PASADA A ATT
A27: 615-862-9112 | B27: VERIZON | C27: Galaxy | D27: SAMSUNG GALAXY A23 5G UW | E27: 355978840939845 | F27: VELAZCO GARCIA, JOEL | G27: LOGISTICS CENTRAL | H27: Tercera | I27: Nashville | J27: Activo | K27: 45658 | L27: 45717 | M27: Perfecto | N27: Revisar por que se migro
A28: 615-636-7429 | B28: VERIZON | C28: Ipad | D28: IPAD 9GEN 64 GRAY | E28: 350698362550466 | F28: ARMES, CLAUDIA | G28: SALES NORTH | H28: Tercera | I28: Cincinnatti | J28: Activo | K28: 45658 | L28: 45717 | M28: Perfecto | N28: CONFIRMAR SI LO TIENE ELLA | O28: 0 | P28: YES | Q28: REVISAR QUIEN LO TIENE
A29: 615-879-8490 | B29: VERIZON | C29: Ipad | D29: IPAD 7TH GEN 32GB GRAY VZ | E29: 353204105703897 | F29: LOPEZ, ALEJANDRA C | G29: SALES WEST | H29: Segunda | I29: Memphis | J29: Activo | K29: 45658 | L29: 45717 | M29: Perfecto | P29: yes
A30: 615-812-2408 | B30: VERIZON | C30: Ipad | D30: IPAD9TH GEN NON-VZW | E30: 359552541123334 | F30: QUEVEDO, NAIROVI Y | G30: SALES WEST | H30: Tercera | I30: Memphis | J30: Activo | K30: 45658 | L30: 45717 | M30: Perfecto | N30: REVISADO SEPT 15 | O30: 0 | P30: yes | Q30: sale ocmo veruuzko pero lo tiene alejandra
A31: 615-804-2180 | B31: VERIZON | C31: Ipad | D31: 10.2 IPAD 8 GEN 32GB SLR SO | E31: 356750111840153 | F31: CABRERA, OSMAN A | G31: SALES CENTRAL | H31: Tercera | I31: Nashville | J31: Activo | K31: 45658 | L31: 45717 | M31: Perfecto | N31: AVERIGUAR QUIEN LO TIENE, SALE JG MARTINEZ EN VERIZON | Q31: revisar quien la tiene
A32: 901-427-2093 | B32: VERIZON | C32: Galaxy | D32: SAMSUNG GALAXY A23 5G UW | E32: 355978840924771 | F32: SUAREZ, ANDRES E | G32: LOGISTICS CENTRAL | H32: Tercera | I32: Nashville | J32: Activo | K32: 45658 | L32: 45717 | M32: Perfecto | O32: 0 | P32: yes
A33: 615-832-0906 | B33: VERIZON | D33: ipad | F33: jg martine | N33: REVISADO SEPT 15 | O33: 0 | P33: yes
A34: 901-495-4023 | B34: VERIZON | D34: Ipad | F34: DESCONECTARLO

Sheet Cambios por escrito
A1: Fecha | B1: Cambio | C1: Ejecutado
A2: 45729 | B2: Nuevo telefono para ana ferrerira, el viejo se arruino. | C2: SI
A3: 45729 | B3: Nuevo telefono para nuevo amalia | C3: NO | D3: a medias, confirmar
A4: 45729 | B4: Nuevo ipad para nuevo amalia | C4: NO | D4: a medias, confirmar
A5: 45729 | B5: Cambio de telefono al nuevo route leader | C5: NO
A6: 45729 | B6: IPAD RITEFILL DSD ALABAMA | C6: NO | D6: a medias, confirmar
A7: 45729 | B7: IPOHNE RITEFILL DSD ALABAMA | C7: SI
A8: 17 marzo | B8: Jorge Tangredi por fernando lescano de DSD
A9: 17 marzo | B9: Jorge Tangredi por fernando lescano de DSD
A11: cambio de tangredi a Endri fernandez

Sheet HISTORIAL DE CAMBIOS Y REEMPLAZ
A1: ID | B1: EQUIPMENT TYPE | C1: MODEL | D1: IMEI | E1: Accion | F1: Usuario anterior | G1: Nuevo usuario | H1: Fecha del cambio | I1: Motivo | J1: Donde se hizo o cambio | K1: Linea | L1: Proveedor | M1: Ususario que registro el cambio
A2: 244 | B2: Iphone | C2: Iphone 14 Pro MaX | D2: 356485673725928 | E2: Activo | F2: Nuevo | G2: ESQUIVEL, HENRY | H2: 45720 | I2: Actualizacion de telefono | J2: En Teams, edwin | K2: Misma linea de Henry | M2: Ch
A3: 016 | B3: Iphone | C3: IPHONE13 128GB MDN NVZ ATT | D3: 358091652600849 | E3: Baja | F3: ESQUIVEL, HENRY | G3: 45720 | M3: ch
A4: 126 | B4: Ipad | C4: Ipad Wifi 64 GB Silver | D4: 356029485569361 | E4: Asignacion | F4: Nuevo | G4: VIVAS, REYNA | H4: 45723 | I4: Asignado nuevo desde el Stock | J4: Correo don Nico 7 marzo | K4: 629-318-8877 | L4: AT&T | M4: ch
A5: 245 | B5: Ipad | C5: Ipad Wifi 64 GB Silver | D5: 356029485261308 | E5: Asignacion | F5: Nuevo | G5: VIVAS, REYNA | H5: 45726 | I5: Asignado nuevo desde el Stock | J5: Correo don Nico 7 marzo | K5: 629-318-9109 | L5: AT&T | M5: Ch
A6: 246 | B6: Iphone | C6: Iphone 14 | D6: 354807370356289 | E6: Asignacion | F6: Nuevo | G6: FERREIRA, ANA CAROLINA | H6: 45730 | I6: Asignado nuevo desde el Stock | J6: Teams Alejandra y eduardo 13 marzo | K6: 901-713-7796 | L6: AT&T | M6: Ch
A7: 087 | B7: Iphone | C7: IPHONE11 64G BLACK NVZ ATT | D7: 356868118528082 | E7: Baja | F7: FERREIRA, ANA CAROLINA | G7: disponible | H7: 45730 | I7: Actualizacion de telefono | J7: Teams Alejandra y eduardo 13 marzo | K7: DISPONIBLE | L7: DISPONIBLE | M7: Ch
M8: Ch
M9: Ch
M10: Ch

Sheet STOCK DISPOSITIVOS
A1: ID | B1: Linea movil | C1: Proveedor | D1: EQUIPMENT TYPE | E1: MODEL | F1: IMEI | G1: ESTADO | H1: UBICACION | I1: FECHA DE ENTRADA | J1: CONDICION | K1: OBSERVACIONES | L1: ENTREGADO POR EDWIN | M1: FECHA DE ENTREGA
A2: 200 | B2: SIN LINEA | C2: VERIZON | D2: Iphone | E2: IPHONE13 128GB MDN NVZ ATT | F2: 358469523212749 | G2: Disponible | H2: Nashville | I2: 45658
A3: 201 | B3: SIN LINEA | C3: VERIZON | D3: Galaxy | E3: SAMSUNG GALAXY A23 5G UW | F3: 355978840905119 | G3: Disponible | H3: Memphis | I3: 45658 | J3: Pantalla Rota
A4: 202 | B4: SIN LINEA | C4: VERIZON | D4: Galaxy | E4: SAMSUNG GALAXY A23 5G UW | F4: 355978840887846 | G4: Disponible | H4: Memphis | I4: 45658
A5: 203 | B5: SIN LINEA | C5: VERIZON | D5: Galaxy | E5: SAMSUNG GALAXY A23 5G UW | F5: 355978840949604 | G5: Disponible | H5: Memphis | I5: 45658
A6: 204 | B6: SIN LINEA | C6: VERIZON | D6: Galaxy | E6: SAMSUNG GALAXY A23 5G UW | F6: 355978840888265 | G6: Disponible | H6: Memphis | I6: 45658
A7: 205 | B7: SIN LINEA | C7: VERIZON | D7: Samsung | E7: Galaxy A13 | F7: 351082126308546 | G7: Disponible | H7: Nashville | I7: 45658 | J7: bloqueado
A8: 207 | B8: SIN LINEA | C8: VERIZON | D8: Galaxy | E8: GALAXY A23 | F8: 355978840907032 | G8: Disponible | H8: Nashville | I8: 45658
A9: 208 | B9: SIN LINEA | C9: VERIZON | D9: Galaxy | E9: GALAXY A23 | F9: 355978840914517 | G9: Disponible | H9: Nashville | I9: 45658
A10: 209 | B10: SIN LINEA | C10: N/A | D10: Galaxy | E10: GALAXY | F10: 351082125235047 | G10: Disponible | H10: Nashville | I10: 45658
A11: 210 | B11: SIN LINEA | C11: AT&T | D11: Galaxy | E11: GALAXY A13 | F11: 351082121009370 | G11: Disponible | H11: Nashville | I11: 45658
A12: 211 | B12: SIN LINEA | C12: VERIZON | D12: Galaxy | E12: GALAXY A13 | F12: 351082120933729 | G12: Disponible | H12: Nashville | I12: 45658
A13: 212 | B13: SIN LINEA | C13: AT&T | D13: Iphone | E13: IPHONE 14 PLUS | F13: 353547799505980 | G13: Disponible | H13: Nashville | I13: 45658
A14: 213 | B14: SIN LINEA | C14: AT&T | D14: Iphone | E14: Iphone 12 | F14: DEBORA | G14: Disponible | H14: Nashville | I14: 45658
A15: 214 | B15: SIN LINEA | C15: AT&T | D15: Galaxy | E15: GALAXY S21 | F15: 351867620257227 | G15: Disponible | H15: Nashville | I15: 45658
A16: 216 | B16: SIN LINEA | C16: AT&T | D16: Iphone | E16: iPhone SE (2022) A2595 64GB Midnight | F16: 350422143443614 | G16: Disponible | H16: Nashville | I16: 45658 | J16: DESACTIVADO
A17: 217 | B17: SIN LINEA | C17: AT&T | D17: Galaxy | E17: Galaxy A13 5G SM-A136U 64GB Black | F17: 351082121083334 | G17: Disponible | H17: Nashville | I17: 45658 | J17: DESACTIVADO
A18: 218 | B18: SIN LINEA | C18: AT&T | D18: Galaxy | E18: Galaxy A13 5G SM-A136U 64GB Black | F18: 351082120960722 | G18: Disponible | H18: Nashville | I18: 45658 | J18: DESACTIVADO
A19: 219 | B19: SIN LINEA | C19: AT&T | D19: Galaxy | E19: Galaxy A13 5G SM-A136U 64GB Black | F19: 351082120939429 | G19: Disponible | H19: Nashville | I19: 45658 | J19: DESACTIVADO
A20: 220 | B20: SIN LINEA | C20: VERIZON | D20: Galaxy | E20: SAMSUNG GALAXY A23 5G UW | F20: 355978840949711 | G20: Disponible | H20: Nashville | I20: 45658 | J20: DESACTIVADO
A21: 221 | B21: SIN LINEA | C21: VERIZON | D21: Galaxy | E21: SAMSUNG GALAXY A23 5G UW | F21: 355978840923146 | G21: Disponible | H21: Nashville | I21: 45658 | J21: DESACTIVADO
A22: 222 | B22: SIN LINEA | C22: VERIZON | D22: Galaxy | E22: SAMSUNG GALAXY A23 5G UW | F22: 355978840939803 | G22: Disponible | H22: Nashville | I22: 45658 | J22: DESACTIVADO
A23: 223 | B23: SIN LINEA | C23: VERIZON | D23: Galaxy | E23: SAMSUNG GALAXY A23 5G UW | F23: 355978840893695 | G23: Disponible | H23: Nashville | I23: 45658 | J23: PANTALLA ROTA
A24: 224 | B24: SIN LINEA | C24: AT&T | D24: Galaxy | E24: GALAXY A13 | F24: 351082125564644 | G24: Disponible | H24: Nashville | I24: 45658 | J24: PANTALLA ROTA
A25: 225 | B25: SIN LINEA | C25: AT&T | D25: Galaxy | E25: GALAXY S21 | F25: 351700860724517 | G25: Disponible | H25: Nashville | I25: 45658 | J25: PANTALLA ROTA
A26: 226 | B26: SIN LINEA | C26: VERIZON | D26: Galaxy | E26: GALAXY A23 | F26: 355978840905150 | G26: Disponible | H26: Nashville | I26: 45658 | J26: NO PRENDE NI CARGA
A27: 227 | B27: SIN LINEA | C27: VERIZON | D27: Galaxy | E27: GALAXY A42 | F27: 350760505489398 | G27: Disponible | H27: Nashville | I27: 45658 | J27: PANTALLA ROTA
A28: 228 | B28: SIN LINEA | C28: AT&T | D28: Galaxy | E28: GALAXY S21 | F28: 351867620294691 | G28: Disponible | H28: Nashville | I28: 45658 | J28: BLOQUEADO
A29: 229 | B29: SIN LINEA | C29: VERIZON | D29: Galaxy | E29: GALAXY A23 | F29: 355978840919698 | G29: Disponible | H29: Nashville | I29: 45658 | J29: BLOQUEADO
A30: 230 | B30: SIN LINEA | C30: AT&T | D30: Galaxy | E30: GALAXY A13 | F30: 351082120925667 | G30: Disponible | H30: Nashville | I30: 45658 | J30: BLOQUEADO
A31: 231 | B31: SIN LINEA | C31: AT&T | D31: Galaxy | E31: GALAXY S21 | F31: 351867620295847 | G31: Disponible | H31: Nashville | I31: 45658 | J31: RASPADO
A32: 232 | B32: SIN LINEA | C32: AT&T | D32: Galaxy | E32: GALAXY A53 | F32: 351024052368565 | G32: Disponible | H32: Nashville | I32: 45658 | J32: BUENA CONDICION
A33: 233 | B33: SIN LINEA | C33: VERIZON | D33: Galaxy | E33: GALAXY A23 | F33: 355978840945131 | G33: Disponible | H33: Nashville | I33: 45658 | J33: BUENA CONDICION
A34: 234 | B34: SIN LINEA | C34: AT&T | D34: Galaxy | E34: GALAXY S21 | F34: 351867620293321 | G34: Disponible | H34: Nashville | I34: 45658 | J34: BUENA CONDICION
A35: 235 | B35: SIN LINEA | C35: AT&T | D35: Galaxy | E35: GALAXY S21 | F35: 351700860705797 | G35: Disponible | H35: Nashville | I35: 45658 | J35: BUENA CONDICION
... A38: 238 | B38: SIN LINEA | C38: AT&T | D38: Galaxy | E38: GALAXY S21 | F38: 351867620292034 | G38: Disponible | H38: Nashville | I38: 45658 | J38: ROTO
A39: 239 | B39: SIN LINEA | D39: Galaxy | E39: GALAXI A53 | F39: 350012621678177 | G39: Disponible | H39: Nashville | I39: 45658 | J39: BUENA CONDICION
A40: 240 | B40: SIN LINEA | C40: VERIZON | D40: Galaxy | E40: GALAXY A13 | F40: 351082122246005 | G40: Disponible | H40: Nashville | I40: 45658 | J40: BUENA CONDICION
A41: 241 | B41: SIN LINEA | C41: AT&T | D41: Galaxy | E41: GALAXY A13 | F41: 351082120669125 | G41: Disponible | H41: Nashville | I41: 45658 | J41: BUENA CONDICION
A42: 242 | B42: SIN LINEA | C42: AT&T | D42: Galaxy | E42: GALAXY A32 | F42: 350091125597968 | G42: Disponible | H42: Nashville | I42: 45658 | J42: BLOQUEADO
A43: 243 | B43: SIN LINEA | C43: Verizon | D43: Galaxy | E43: GALAXY A32 | F43: 355978840945628 | G43: Disponible | H43: Nashville | I43: 45658 | J43: BLOQUEADO
A44: 244 | B44: 615-390-4624 | C44: AT&T | D44: Iphone | E44: Iphone 14 Pro MaX | F44: 356485673725928 | G44: Activo | H44: Nashville | I44: 45720 | J44: Perfecto
A45: 016 | B45: 615-390-4624 | C45: AT&T | D45: Iphone | E45: IPHONE13 128GB MDN NVZ ATT | F45: 358091652600849 | G45: Disponible | H45: Nashville | I45: 45720 | J45: Perfecto
A46: 126 | B46: 629-318-8877 | C46: AT&T | D46: Ipad | E46: Ipad Wifi 64 GB Silver | F46: 356029485569361 | G46: Disponible | H46: Memphis | I46: 45723 | J46: Perfecto
A47: 245 | B47: 629-318-9109 | C47: AT&T | D47: Ipad | E47: Ipad Wifi 64 GB Silver | F47: 356029485261308 | G47: Activo | H47: Memphis | I47: 45726 | J47: Perfecto | K47: IPAD NUEVA PARA VENDEDORA DSD MEMHPIS
E52: dispositivo de simcards
E53: ETF FEE DE VERIZON PARA TENERLO EN EL RADAR.
E54: MIN 10
E56: ANALISIS EN BASE A LAS REGIONES DE LOS PRECIOS
E57: SI HAY PRODUCTOS QUE ANTES SE VENDIA MAS O MENOS Y VER ESTO.
E58: A NIVEL DE PRODUCTOS / Cajas vendemos menos del ano pasado.
E59: Tenemos mas vendedores y tenemos menos volumen.
E60: Impacto en elasticidad
E61: Analisis de rentabilidad o marginal de las marcas o de los productos.
E62: min 20
E63: Dentro de las menos rentables es por precio, productos, etc.
E64: no se vende por el inventario y la fuerza de venta.
... E70: fillrate de $300,000. $
E71: =300000*35% -> 105000

Sheet STOCK DISPOSITIVOS (2)
A1: ID | B1: Linea movil | C1: Proveedor | D1: EQUIPMENT TYPE | E1: MODEL | F1: IMEI | G1: ESTADO | H1: UBICACION | I1: FECHA DE ENTRADA | J1: CONDICION | K1: OBSERVACIONES | L1: ENTREGADO POR EDWIN | M1: FECHA DE ENTREGA
A2: 200 | B2: 317-366-4495 | C2: VERIZON | D2: Iphone | E2: IPHONE13 128GB MDN NVZ ATT | F2: 358469523212749 | G2: Disponible | H2: Nashville | I2: 45658
A3: 201 | B3: 615-728-2728 | C3: VERIZON | D3: Galaxy | E3: SAMSUNG GALAXY A23 5G UW | F3: 355978840905119 | G3: Disponible | H3: Memphis | I3: 45658 | J3: Pantalla Rota
A4: 202 | B4: 615-728-2734 | C4: VERIZON | D4: Galaxy | E4: SAMSUNG GALAXY A23 5G UW | F4: 355978840887846 | G4: Disponible | H4: Memphis | I4: 45658
A5: 203 | B5: 615-924-1526 | C5: VERIZON | D5: Galaxy | E5: SAMSUNG GALAXY A23 5G UW | F5: 355978840949604 | G5: Disponible | H5: Memphis | I5: 45658
A6: 204 | B6: 615-930-7736 | C6: VERIZON | D6: Galaxy | E6: SAMSUNG GALAXY A23 5G UW | F6: 355978840888265 | G6: Disponible | H6: Memphis | I6: 45658
A7: 205 | B7: 615-979-9910 | C7: VERIZON | D7: Samsung | E7: Galaxy A13 | F7: 351082126308546 | G7: Disponible | H7: Nashville | I7: 45658 | J7: bloqueado
A8: 207 | B8: SIN LINEA | C8: VERIZON | D8: Galaxy | E8: GALAXY A23 | F8: 355978840907032 | G8: Disponible | H8: Nashville | I8: 45658
A9: 208 | B9: SIN LINEA | C9: VERIZON | D9: Galaxy | E9: GALAXY A23 | F9: 355978840914517 | G9: Disponible | H9: Nashville | I9: 45658
A10: 209 | B10: SIN LINEA | C10: N/A | D10: Galaxy | E10: GALAXY | F10: 351082125235047 | G10: Disponible | H10: Nashville | I10: 45658
A11: 210 | B11: SIN LINEA | C11: AT&T | D11: Galaxy | E11: GALAXY A13 | F11: 351082121009370 | G11: Disponible | H11: Nashville | I11: 45658
A12: 211 | B12: SIN LINEA | C12: VERIZON | D12: Galaxy | E12: GALAXY A13 | F12: 351082120933729 | G12: Disponible | H12: Nashville | I12: 45658
A13: 212 | B13: SIN LINEA | C13: AT&T | D13: Iphone | E13: IPHONE 14 PLUS | F13: 353547799505980 | G13: Disponible | H13: Nashville | I13: 45658
A14: 213 | B14: SIN LINEA | C14: AT&T | D14: Iphone | E14: Iphone 12 | F14: DEBORA | G14: Disponible | H14: Nashville | I14: 45658
A15: 214 | B15: SIN LINEA | C15: AT&T | D15: Galaxy | E15: GALAXY S21 | F15: 351867620257227 | G15: Disponible | H15: Nashville | I15: 45658
A16: 216 | B16: 629-468-0618 | C16: AT&T | D16: Iphone | E16: iPhone SE (2022) A2595 64GB Midnight | F16: 350422143443614 | G16: Disponible | H16: Nashville | I16: 45658 | J16: DESACTIVADO
A17: 217 | B17: 615-939-6293 | C17: AT&T | D17: Galaxy | E17: Galaxy A13 5G SM-A136U 64GB Black | F17: 351082121083334 | G17: Disponible | H17: Nashville | I17: 45658 | J17: DESACTIVADO
A18: 218 | B18: 615-939-9582 | C18: AT&T | D18: Galaxy | E18: Galaxy A13 5G SM-A136U 64GB Black | F18: 351082120960722 | G18: Disponible | H18: Nashville | I18: 45658 | J18: DESACTIVADO
A19: 219 | B19: 629-468-8256 | C19: AT&T | D19: Galaxy | E19: Galaxy A13 5G SM-A136U 64GB Black | F19: 351082120939429 | G19: Disponible | H19: Nashville | I19: 45658 | J19: DESACTIVADO
A20: 220 | C20: VERIZON | D20: Galaxy | E20: SAMSUNG GALAXY A23 5G UW | F20: 355978840949711 | G20: Disponible | H20: Nashville | I20: 45658 | J20: DESACTIVADO
A21: 221 | B21: 615-319-8134 | C21: VERIZON | D21: Galaxy | E21: SAMSUNG GALAXY A23 5G UW | F21: 355978840923146 | G21: Disponible | H21: Nashville | I21: 45658 | J21: DESACTIVADO
A22: 222 | B22: 615-728-2262 | C22: VERIZON | D22: Galaxy | E22: SAMSUNG GALAXY A23 5G UW | F22: 355978840939803 | G22: Disponible | H22: Nashville | I22: 45658 | J22: DESACTIVADO
A23: 223 | B23: 615-881-6408 | C23: VERIZON | D23: Galaxy | E23: SAMSUNG GALAXY A23 5G UW | F23: 355978840893695 | G23: Disponible | H23: Nashville | I23: 45658 | J23: PANTALLA ROTA
A24: 224 | B24: SIN LINEA | C24: AT&T | D24: Galaxy | E24: GALAXY A13 | F24: 351082125564644 | G24: Disponible | H24: Nashville | I24: 45658 | J24: PANTALLA ROTA
A25: 225 | B25: SIN LINEA | C25: AT&T | D25: Galaxy | E25: GALAXY S21 | F25: 351700860724517 | G25: Disponible | H25: Nashville | I25: 45658 | J25: PANTALLA ROTA
A26: 226 | B26: SIN LINEA | C26: VERIZON | D26: Galaxy | E26: GALAXY A23 | F26: 355978840905150 | G26: Disponible | H26: Nashville | I26: 45658 | J26: NO PRENDE NI CARGA
A27: 227 | B27: SIN LINEA | C27: VERIZON | D27: Galaxy | E27: GALAXY A42 | F27: 350760505489398 | G27: Disponible | H27: Nashville | I27: 45658 | J27: PANTALLA ROTA
A28: 228 | B28: SIN LINEA | C28: AT&T | D28: Galaxy | E28: GALAXY S21 | F28: 351867620294691 | G28: Disponible | H28: Nashville | I28: 45658 | J28: BLOQUEADO
A29: 229 | B29: SIN LINEA | C29: VERIZON | D29: Galaxy | E29: GALAXY A23 | F29: 355978840919698 | G29: Disponible | H29: Nashville | I29: 45658 | J29: BLOQUEADO
A30: 230 | B30: SIN LINEA | C30: AT&T | D30: Galaxy | E30: GALAXY A13 | F30: 351082120925667 | G30: Disponible | H30: Nashville | I30: 45658 | J30: BLOQUEADO
A31: 231 | B31: SIN LINEA | C31: AT&T | D31: Galaxy | E31: GALAXY S21 | F31: 351867620295847 | G31: Disponible | H31: Nashville | I31: 45658 | J31: RASPADO
A32: 232 | B32: SIN LINEA | C32: AT&T | D32: Galaxy | E32: GALAXY A53 | F32: 351024052368565 | G32: Disponible | H32: Nashville | I32: 45658 | J32: BUENA CONDICION
A33: 233 | B33: SIN LINEA | C33: VERIZON | D33: Galaxy | E33: GALAXY A23 | F33: 355978840945131 | G33: Disponible | H33: Nashville | I33: 45658 | J33: BUENA CONDICION
A34: 234 | B34: SIN LINEA | C34: AT&T | D34: Galaxy | E34: GALAXY S21 | F34: 351867620293321 | G34: Disponible | H34: Nashville | I34: 45658 | J34: BUENA CONDICION
A35: 235 | B35: SIN LINEA | C35: AT&T | D35: Galaxy | E35: GALAXY S21 | F35: 351700860705797 | G35: Disponible | H35: Nashville | I35: 45658 | J35: BUENA CONDICION
... A38: 238 | B38: SIN LINEA | C38: AT&T | D38: Galaxy | E38: GALAXY S21 | F38: 351867620292034 | G38: Disponible | H38: Nashville | I38: 45658 | J38: ROTO
A39: 239 | B39: SIN LINEA | D39: Galaxy | E39: GALAXI A53 | F39: 350012621678177 | G39: Disponible | H39: Nashville | I39: 45658 | J39: BUENA CONDICION
A40: 240 | B40: SIN LINEA | C40: VERIZON | D40: Galaxy | E40: GALAXY A13 | F40: 351082122246005 | G40: Disponible | H40: Nashville | I40: 45658 | J40: BUENA CONDICION
A41: 241 | B41: SIN LINEA | C41: AT&T | D41: Galaxy | E41: GALAXY A13 | F41: 351082120669125 | G41: Disponible | H41: Nashville | I41: 45658 | J41: BUENA CONDICION
A42: 242 | B42: SIN LINEA | C42: AT&T | D42: Galaxy | E42: GALAXY A32 | F42: 350091125597968 | G42: Disponible | H42: Nashville | I42: 45658 | J42: BLOQUEADO
A43: 243 | B43: SIN LINEA | C43: Verizon | D43: Galaxy | E43: GALAXY A32 | F43: 355978840945628 | G43: Disponible | H43: Nashville | I43: 45658 | J43: BLOQUEADO
A44: 244 | B44: 615-390-4624 | C44: AT&T | D44: Iphone | E44: Iphone 14 Pro MaX | F44: 356485673725928 | G44: Activo | H44: Nashville | I44: 45720 | J44: Perfecto
A45: 016 | B45: 615-390-4624 | C45: AT&T | D45: Iphone | E45: IPHONE13 128GB MDN NVZ ATT | F45: 358091652600849 | G45: Disponible | H45: Nashville | I45: 45720 | J45: Perfecto
A46: 245 | C46: AT&T | D46: Ipad | E46: Ipad Wifi 64 GB Silver | F46: 356029485569361 | G46: Activo | H46: Memphis | I46: 45723 | J46: Perfecto | K46: IPAD NUEVA PARA VENDEDORA DSD MEMHPIS

Sheet Email Confirmacion
A1: Usuario Asignado | B1: Dispositivo | C1: MODEL | D1: LINEA MOVIL | E1: IMEI | F1: Confirmacion o comentarios | G1: SEND | H1: RECIBIDO
A2: RRHH
A3: DUQUE IYENGAR, DANIELA | B3: Iphone | C3: iPhone 14 Plus A2632 128GB Midnight | D3: 615-316-8577 | E3: 353547798360296 | G3: x
A4: HERNANDEZ ARREGUIN, ANA AIDET | B4: Galaxy | C4: SAMSUNG GALAXY A23 5G UW | D4: 615-319-8134 | E4: 355978840923146 | G4: x
A5: BRITO SALAZAR, RICARDO JOSE | B5: Iphone | C5: iPhone 13 A2482 128GB Midnight | D5: 629-264-3070 | E5: 357084344468932 | G5: x
A6: FINANCE
A7: QUIJANO, NICOLAS | B7: Iphone | C7: iPhone 13 Pro Max A2484 256GB Graphite | D7: 615-417-9594 | E7: 350566101441174 | G7: x
A8: QUIJANO, NICOLAS | B8: Iphone | C8: iPhone 13 Pro Max A2484 256GB Gold | D8: 615-691-3166 | E8: 356796480675498 | G8: x
A9: QUIJANO, NICOLAS | B9: Iphone | C9: Iphone 11 Pro | D9: 615-830-6700 | E9: 353247104496222 | G9: x
A10: CASTILLO DUARTE, JOSE EDUARDO | B10: Galaxy | C10: Galaxy A13 5G SM-A136U 64GB Black | D10: 615-939-9582 | E10: 351082120960722 | G10: x
A11: ESG
A12: LODYGENSKY, ISABELE | B12: Iphone | C12: iPhone 13 Pro Max A2484 128GB Graphite | D12: 629-285-9899 | E12: 352865675892301 | G12: x
A13: CEO
A14: HERRERA MOLINA, JOSE CARLOS | B14: Iphone | C14: iPhone 13 Pro Max A2484 128GB Graphite | D14: 615-626-4243 | E14: 350019045940745 | G14: x
A15: HERRERA MOLINA, JOSE CARLOS | B15: Ipad | C15: 10.2 IPAD 8 GEN 32GB SG | D15: 615-626-7710 | E15: 356747116811213 | G15: x

Sheet DISCON or SUSPEND
A1: ID | B1: LINEA MOVIL | D1: Proveedor | E1: EQUIPMENT TYPE | F1: MODEL | G1: IMEI | H1: Usuario Asignado | I1: CECO | J1: LINEA | K1: LOCATION | L1: Estado | M1: Fecha de asignacion | N1: Fecha de ultima revision | O1: Condicion de equipo | P1: Comentarios | R1: Fecha de desconeccion
A2: 002 | B2: 615-946-7544 | D2: VERIZON | E2: 5G MIFI | F2: 5G MIFI M1000 | G2: 990013090331153 | H2: MADRIZ, JOHAN | I2: President | J2: Primera | K2: Nashville | L2: Activo | M2: 45658 | N2: 45717 | O2: Perfecto | Q2: DESCONECTADA | R2: 45726
A3: 004 | B3: 615-474-6646 | D3: AT&T | E3: Netgear | F3: Nighthawk LTE Mobile Hotspot Router MR1100 2018 Steel Gray | G3: 15161004027051 | H3: MADRIZ, JOHAN | I3: President | J3: Primera | K3: Nashville | L3: Activo | M3: 45658 | N3: 45717 | O3: Perfecto | Q3: DESCONECTADA | R3: 45726
A4: 003 | B4: 615-812-8133 | D4: VERIZON | E4: Ipad | F4: IPAD PRO 12.9 256 GRY | G4: 352782113859653 | H4: MADRIZ, JOHAN | I4: President | J4: Primera | K4: Nashville | L4: Activo | M4: 45658 | N4: 45717 | O4: Perfecto | Q4: DESCONECTADA | R4: 45726
B5: 615-585-1725 | C5: SALES DSD IPAD | D5: AT&T | P5: Suspendida por don nico por no uso con patricia | Q5: SUSPENDIDA | R5: 45726
B6: 615-585-1725 | C6: SALES DSD IPAD | D6: AT&T | P6: Suspendida por don nico por no uso con patricia | Q6: SUSPENDIDA | R6: 45726
B7: 463-867-7910 | C7: NEW INDY USER... | D7: AT&T | P7: Suspendida por don nico por no uso con patricia | Q7: SUSPENDIDA | R7: 45726
B8: 470-330-9757 | C8: KAREN ORELLANA | D8: AT&T | P8: Suspendida por don nico por no uso con patricia | Q8: SUSPENDIDA | R8: 45726
B9: 470-737-8596 | C9: ISRAEL LOPEZ | D9: AT&T | P9: Suspendida por don nico por no uso con patricia | Q9: SUSPENDIDA | R9: 45726
B10: 615-305-1999 | C10: IPAD SALES | D10: AT&T | P10: Suspendida por don nico por no uso con patricia | Q10: SUSPENDIDA | R10: 45726
B11: 615-476-5992 | C11: MONICA AYALA | D11: AT&T | P11: Suspendida por don nico por no uso con patricia | Q11: SUSPENDIDA | R11: 45726
B12: 615-939-6293 | C12: GABRIEL NASHV... | D12: AT&T | P12: Suspendida por don nico por no uso con patricia | Q12: SUSPENDIDA | R12: 45726
B13: 629-318-9009 | C13: IPAD DE NACOMY | D13: AT&T | P13: Suspendida por don nico por no uso con patricia | Q13: SUSPENDIDA | R13: 45726
B14: 629-468-1066 | C14: REPLACEMENT L... | D14: AT&T | P14: Suspendida por don nico por no uso con patricia | Q14: SUSPENDIDA | R14: 45726
B15: 901-456-2279 | C15: CARLOS PEREZ | D15: AT&T | P15: Suspendida por don nico por no uso con patricia | Q15: SUSPENDIDA | R15: 45726

Sheet Sheet1
A1: Requerimientos de don Nico
A2: Lista de lo que estamos pagados con la ultima factura, lineas actuales de ATT (cobrado) | K2: A LA PAR ponerle que yo deberia de pagar $25 las actuales.
A3: lineas con Verizon de migracion, $15 por linea
A4: Verizon en otro listado y cuanto estamos pagados.
A7: agregar tema de salida en dispositivos
A9: revisar telefonos de johan y meraria
